Workbook

Sheet Summary
A1: Konbaung Chronicle knowledge graph: extraction evaluation
A2: Two independent random samples of 61 pages each (122 of 1,215 pages; 1,201 sentences; 2,808 extracted triples). Judge: ChatGPT (OpenAI), reading each sampled Burmese sentence with its surrounding narrative. Extraction model: Gemini 3.1 Flash Lite.
A4: Measure | B4: First 5% | C4: Second 5% | D4: Combined | E4: Definition
A5: Triples judged | B5: =COUNTIF(Triples!$A$2:$A$2809,"First 5%") -> 1423 | C5: =COUNTIF(Triples!$A$2:$A$2809,"Second 5%") -> 1385 | D5: =COUNTA(Triples!$A$2:$A$2809) -> 2808 | E5: Extracted subject–predicate–object triples on the sampled pages
A6: Supported | B6: =COUNTIFS(Triples!$A$2:$A$2809,"First 5%",Triples!$I$2:$I$2809,"supported") -> 1339 | C6: =COUNTIFS(Triples!$A$2:$A$2809,"Second 5%",Triples!$I$2:$I$2809,"supported") -> 1285 | D6: =COUNTIF(Triples!$I$2:$I$2809,"supported") -> 2624 | E6: Relationship, actor, action and object supported by the Burmese and narrative context
A7: Soft error | B7: =COUNTIFS(Triples!$A$2:$A$2809,"First 5%",Triples!$I$2:$I$2809,"soft") -> 37 | C7: =COUNTIFS(Triples!$A$2:$A$2809,"Second 5%",Triples!$I$2:$I$2809,"soft") -> 48 | D7: =COUNTIF(Triples!$I$2:$I$2809,"soft") -> 85 | E7: Relationship true; a construction, label or detail needs repair
A8: Hard error | B8: =COUNTIFS(Triples!$A$2:$A$2809,"First 5%",Triples!$I$2:$I$2809,"hard") -> 45 | C8: =COUNTIFS(Triples!$A$2:$A$2809,"Second 5%",Triples!$I$2:$I$2809,"hard") -> 48 | D8: =COUNTIF(Triples!$I$2:$I$2809,"hard") -> 93 | E8: A substantive claim conflicts with the source (wrong actor, place, event, direction or office)
A9: Unresolved | B9: =COUNTIFS(Triples!$A$2:$A$2809,"First 5%",Triples!$I$2:$I$2809,"uncertain") -> 2 | C9: =COUNTIFS(Triples!$A$2:$A$2809,"Second 5%",Triples!$I$2:$I$2809,"uncertain") -> 4 | D9: =COUNTIF(Triples!$I$2:$I$2809,"uncertain") -> 6 | E9: Two readings possible; not counted as correct or as an error
A10: Semantic precision | B10: =(B6+B7)/B5 -> 0.96697119 | C10: =(C6+C7)/C5 -> 0.96245487 | D10: =(D6+D7)/D5 -> 0.96474359 | E10: (Supported + Soft) / Triples judged
A11: No-flag precision | B11: =B6/B5 -> 0.94096978 | C11: =C6/C5 -> 0.92779783 | D11: =D6/D5 -> 0.93447293 | E11: Supported / Triples judged
A12: Hard error rate | B12: =B8/B5 -> 0.031623331 | C12: =C8/C5 -> 0.03465704 | D12: =D8/D5 -> 0.033119658 | E12: Hard / Triples judged
A13: Source relationships | B13: =COUNTIFS(Recall!$A$2:$A$1523,"First 5%",Recall!$H$2:$H$1523,"yes") -> 757 | C13: =COUNTIFS(Recall!$A$2:$A$1523,"Second 5%",Recall!$H$2:$H$1523,"yes") -> 757 | D13: =COUNTIF(Recall!$H$2:$H$1523,"yes") -> 1514 | E13: Relationships the judge identified in the Burmese, on pages with extraction output
A14: Covered | B14: =COUNTIFS(Recall!$A$2:$A$1523,"First 5%",Recall!$G$2:$G$1523,"covered",Recall!$H$2:$H$1523,"yes") -> 677 | C14: =COUNTIFS(Recall!$A$2:$A$1523,"Second 5%",Recall!$G$2:$G$1523,"covered",Recall!$H$2:$H$1523,"yes") -> 675 | D14: =COUNTIFS(Recall!$G$2:$G$1523,"covered",Recall!$H$2:$H$1523,"yes") -> 1352 | E14: Represented adequately by one or more triples
A15: Partial | B15: =COUNTIFS(Recall!$A$2:$A$1523,"First 5%",Recall!$G$2:$G$1523,"partial",Recall!$H$2:$H$1523,"yes") -> 24 | C15: =COUNTIFS(Recall!$A$2:$A$1523,"Second 5%",Recall!$G$2:$G$1523,"partial",Recall!$H$2:$H$1523,"yes") -> 22 | D15: =COUNTIFS(Recall!$G$2:$G$1523,"partial",Recall!$H$2:$H$1523,"yes") -> 46 | E15: Represented, but a substantive aspect is missing
A16: Incorrect | B16: =COUNTIFS(Recall!$A$2:$A$1523,"First 5%",Recall!$G$2:$G$1523,"incorrect",Recall!$H$2:$H$1523,"yes") -> 17 | C16: =COUNTIFS(Recall!$A$2:$A$1523,"Second 5%",Recall!$G$2:$G$1523,"incorrect",Recall!$H$2:$H$1523,"yes") -> 27 | D16: =COUNTIFS(Recall!$G$2:$G$1523,"incorrect",Recall!$H$2:$H$1523,"yes") -> 44 | E16: Represented, but wrongly
A17: Missing | B17: =COUNTIFS(Recall!$A$2:$A$1523,"First 5%",Recall!$G$2:$G$1523,"missing",Recall!$H$2:$H$1523,"yes") -> 39 | C17: =COUNTIFS(Recall!$A$2:$A$1523,"Second 5%",Recall!$G$2:$G$1523,"missing",Recall!$H$2:$H$1523,"yes") -> 33 | D17: =COUNTIFS(Recall!$G$2:$G$1523,"missing",Recall!$H$2:$H$1523,"yes") -> 72 | E17: Not represented
A18: Inclusive recall | B18: =(B14+B15)/B13 -> 0.92602378 | C18: =(C14+C15)/C13 -> 0.92073976 | D18: =(D14+D15)/D13 -> 0.92338177 | E18: (Covered + Partial) / Source relationships
A19: Full-only recall | B19: =B14/B13 -> 0.89431968 | C19: =C14/C13 -> 0.89167768 | D19: =D14/D13 -> 0.89299868 | E19: Covered / Source relationships
A21: 95% intervals (page-cluster bootstrap, 20,000 resamples)
A22: Semantic precision | B22: 94.7–98.3% | C22: 94.3–97.8% | D22: 95.1–97.6%
A23: Inclusive recall | B23: 89.4–95.4% | C23: 89.7–94.4% | D23: 90.4–94.2%
A24: Full-only recall | B24: 86.3–92.3% | C24: 86.4–91.8% | D24: 87.2–91.2%
A25: Intervals are copied from the audit records (metrics_final.json) and reflect sampling variation only.
A27: Notes
A28: The judge credits reasonable grouping, paraphrase and contextually supplied actors. Claims are judged against what the chronicle says, not against external historical fact.
A29: Precision is measured per triple; recall per source relationship. The two use different units, so no F1 is reported.
A30: Volume 3, page 511 (second sample) has no extraction output; its 8 source relationships are excluded from recall above. Including them, combined inclusive recall is 91.9%.
A31: Samples: first drawn with seed 20260915; second with seed 20260916 from the remaining pages.
A32: English translations are the pipeline's model translations, shown for convenience; the judge worked from the Burmese.
A33: Sheets: Triples (every judged triple), Recall (every source relationship and its matching triples), Sentences (every sampled sentence).

Sheet Triples
A1: Tranche | B1: Volume | C1: Page | D1: Sentence ID | E1: Triple ID | F1: Subject | G1: Predicate | H1: Object | I1: Verdict | J1: Judge reasoning | K1: Suggested correction | L1: Burmese sentence | M1: English translation (auxiliary)
A2: First 5% | B2: vol1 | C2: 71 | D2: vol1_s000407 | E2: vol1_s000407_t01_3c02a13d586a | F2: Alaungmintayagyi | G2: PERFORMED_RITUAL_DEPARTURE_FROM | H2: Cittakuta_gate | I2: hard | J2: The Cittakuta gate belongs to the comparison with Sakra, not to the king’s actual departure. The king leaves through the eastern right-hand gate. The triple literalizes the simile. | K2: Alaungmintayagyi | DEPARTED_THROUGH | eastern right-hand gate (or retain Cittakuta explicitly as a simile) | L2: ထိုအခါ အလောင်းမင်းတရားကြီး ဘုရားလည်း သက္ကရာဇ် တစ်ထောင့် တစ်ရာ့ လေးဆယ့် လေးခု၊ ကဆုန်လပြည့်ကျော်ရှစ်ရက် သောကြာနေ့၊ မွန်းယိမ်းနှစ်ချက်တီးကျော် နှစ်မောင်းတွင် အတန္တုအားဖြင့် တာဝတိံသာ မဟာသုဒဿနမြို့သို့ ချီတက်လာကုန်သော အသူရာစစ်သည်တို့ကို နှိပ်နင်းအံ့သောငှာ မင်္ဂလာရှိသော စိတ္တကုဋ် တံခါးမှ သိကြားထွက်စံသကဲ့သို့ အောင်တံခွန်ကို လွှားလွှားလွှင့်တော်မူ၍ သားတော်မြတ် နှစ်ပါးနှင့်တကွ ဆွေတော် မျိုးတော် ကျွန်တော်ရင်း မြင်းရည်တက် လေးဆယ့်ခြောက်ခေါင်း အစု အမှုထမ်း လက်နက်စွဲ သူရဲအပေါင်း ခြံရံလျက် မင်းတို့စံပယ်ခြင်းဖြင့် စည်တော်ရွမ်း၍ အရှေ့မျက်နှာ လက်ယာတံခါးမှ ရွှေထီးဖြန့်လျက် ထွက်တော် မူသည်ကို မွန်တို့တပ်က မြင်လျှင် သောသောထ၍ ကြည့်ကြစဉ် ကောင်းကင်အရပ်က သိမ်းငှက်တစ်ခုသည် စွန်ရဲကို တိုက်၍ ရှေ့တော်တူရူ ဦးခေါင်းငိုက်ဆိုက် ကျလာသည်ကို ရဲမက်တော်တို့ လှံနှင့်နှိပ်၍ ရလိုက်သည်။ | M2: At that time, Alaungmintayagyi Paya, in the year 1144, on the eighth day of the waning moon of Kason, a Friday, at the time just past two strokes of the afternoon, in order to suppress the Asura soldiers who were marching toward the Tavatimsa Mahasudassana city as if by analogy, raised the victory banner high as if Sakra were emerging from the auspicious Cittakuta gate, and surrounded by his two noble sons, his relatives, his kin, his loyal servants, forty-six cavalrymen, and all the armed soldiers and service personnel, with the royal drums beating in the royal manner, he emerged from the right gate on the eastern side with the golden umbrella spread; when the Mon army saw this, they rose up in a clamor to watch, and at that moment, a hawk from the sky attacked a kite, and it fell headlong directly in front of him, which the royal soldiers struck with spears and caught.
A3: First 5% | B3: vol1 | C3: 71 | D3: vol1_s000407 | E3: vol1_s000407_t02_97f3bf59b463 | F3: Alaungmintayagyi | G3: DISPLAYED_ROYAL_REGALIA | H3: victory_banner_and_golden_umbrella | I3: supported | J3: Supported by the Burmese sentence and allowed narrative context; grouping and contextually inferred participants accepted. | L3: ထိုအခါ အလောင်းမင်းတရားကြီး ဘုရားလည်း သက္ကရာဇ် တစ်ထောင့် တစ်ရာ့ လေးဆယ့် လေးခု၊ ကဆုန်လပြည့်ကျော်ရှစ်ရက် သောကြာနေ့၊ မွန်းယိမ်းနှစ်ချက်တီးကျော် နှစ်မောင်းတွင် အတန္တုအားဖြင့် တာဝတိံသာ မဟာသုဒဿနမြို့သို့ ချီတက်လာကုန်သော အသူရာစစ်သည်တို့ကို နှိပ်နင်းအံ့သောငှာ မင်္ဂလာရှိသော စိတ္တကုဋ် တံခါးမှ သိကြားထွက်စံသကဲ့သို့ အောင်တံခွန်ကို လွှားလွှားလွှင့်တော်မူ၍ သားတော်မြတ် နှစ်ပါးနှင့်တကွ ဆွေတော် မျိုးတော် ကျွန်တော်ရင်း မြင်းရည်တက် လေးဆယ့်ခြောက်ခေါင်း အစု အမှုထမ်း လက်နက်စွဲ သူရဲအပေါင်း ခြံရံလျက် မင်းတို့စံပယ်ခြင်းဖြင့် စည်တော်ရွမ်း၍ အရှေ့မျက်နှာ လက်ယာတံခါးမှ ရွှေထီးဖြန့်လျက် ထွက်တော် မူသည်ကို မွန်တို့တပ်က မြင်လျှင် သောသောထ၍ ကြည့်ကြစဉ် ကောင်းကင်အရပ်က သိမ်းငှက်တစ်ခုသည် စွန်ရဲကို တိုက်၍ ရှေ့တော်တူရူ ဦးခေါင်းငိုက်ဆိုက် ကျလာသည်ကို ရဲမက်တော်တို့ လှံနှင့်နှိပ်၍ ရလိုက်သည်။ | M3: At that time, Alaungmintayagyi Paya, in the year 1144, on the eighth day of the waning moon of Kason, a Friday, at the time just past two strokes of the afternoon, in order to suppress the Asura soldiers who were marching toward the Tavatimsa Mahasudassana city as if by analogy, raised the victory banner high as if Sakra were emerging from the auspicious Cittakuta gate, and surrounded by his two noble sons, his relatives, his kin, his loyal servants, forty-six cavalrymen, and all the armed soldiers and service personnel, with the royal drums beating in the royal manner, he emerged from the right gate on the eastern side with the golden umbrella spread; when the Mon army saw this, they rose up in a clamor to watch, and at that moment, a hawk from the sky attacked a kite, and it fell headlong directly in front of him, which the royal soldiers struck with spears and caught.
A4: First 5% | B4: vol1 | C4: 71 | D4: vol1_s000407 | E4: vol1_s000407_t03_0be63211651d | F4: Alaungmintayagyi | G4: MOBILIZED_MILITARY_ASSETS | H4: cavalry_and_armed_soldiers | I4: supported | J4: Supported by the Burmese sentence and allowed narrative context; grouping and contextually inferred participants accepted. | L4: ထိုအခါ အလောင်းမင်းတရားကြီး ဘုရားလည်း သက္ကရာဇ် တစ်ထောင့် တစ်ရာ့ လေးဆယ့် လေးခု၊ ကဆုန်လပြည့်ကျော်ရှစ်ရက် သောကြာနေ့၊ မွန်းယိမ်းနှစ်ချက်တီးကျော် နှစ်မောင်းတွင် အတန္တုအားဖြင့် တာဝတိံသာ မဟာသုဒဿနမြို့သို့ ချီတက်လာကုန်သော အသူရာစစ်သည်တို့ကို နှိပ်နင်းအံ့သောငှာ မင်္ဂလာရှိသော စိတ္တကုဋ် တံခါးမှ သိကြားထွက်စံသကဲ့သို့ အောင်တံခွန်ကို လွှားလွှားလွှင့်တော်မူ၍ သားတော်မြတ် နှစ်ပါးနှင့်တကွ ဆွေတော် မျိုးတော် ကျွန်တော်ရင်း မြင်းရည်တက် လေးဆယ့်ခြောက်ခေါင်း အစု အမှုထမ်း လက်နက်စွဲ သူရဲအပေါင်း ခြံရံလျက် မင်းတို့စံပယ်ခြင်းဖြင့် စည်တော်ရွမ်း၍ အရှေ့မျက်နှာ လက်ယာတံခါးမှ ရွှေထီးဖြန့်လျက် ထွက်တော် မူသည်ကို မွန်တို့တပ်က မြင်လျှင် သောသောထ၍ ကြည့်ကြစဉ် ကောင်းကင်အရပ်က သိမ်းငှက်တစ်ခုသည် စွန်ရဲကို တိုက်၍ ရှေ့တော်တူရူ ဦးခေါင်းငိုက်ဆိုက် ကျလာသည်ကို ရဲမက်တော်တို့ လှံနှင့်နှိပ်၍ ရလိုက်သည်။ | M4: At that time, Alaungmintayagyi Paya, in the year 1144, on the eighth day of the waning moon of Kason, a Friday, at the time just past two strokes of the afternoon, in order to suppress the Asura soldiers who were marching toward the Tavatimsa Mahasudassana city as if by analogy, raised the victory banner high as if Sakra were emerging from the auspicious Cittakuta gate, and surrounded by his two noble sons, his relatives, his kin, his loyal servants, forty-six cavalrymen, and all the armed soldiers and service personnel, with the royal drums beating in the royal manner, he emerged from the right gate on the eastern side with the golden umbrella spread; when the Mon army saw this, they rose up in a clamor to watch, and at that moment, a hawk from the sky attacked a kite, and it fell headlong directly in front of him, which the royal soldiers struck with spears and caught.
A5: First 5% | B5: vol1 | C5: 71 | D5: vol1_s000407 | E5: vol1_s000407_t04_d0b57d421653 | F5: Alaungmintayagyi | G5: COMMANDED_LOYALTY_OF | H5: sons_and_kin_and_servants | I5: supported | J5: Supported by the Burmese sentence and allowed narrative context; grouping and contextually inferred participants accepted. | L5: ထိုအခါ အလောင်းမင်းတရားကြီး ဘုရားလည်း သက္ကရာဇ် တစ်ထောင့် တစ်ရာ့ လေးဆယ့် လေးခု၊ ကဆုန်လပြည့်ကျော်ရှစ်ရက် သောကြာနေ့၊ မွန်းယိမ်းနှစ်ချက်တီးကျော် နှစ်မောင်းတွင် အတန္တုအားဖြင့် တာဝတိံသာ မဟာသုဒဿနမြို့သို့ ချီတက်လာကုန်သော အသူရာစစ်သည်တို့ကို နှိပ်နင်းအံ့သောငှာ မင်္ဂလာရှိသော စိတ္တကုဋ် တံခါးမှ သိကြားထွက်စံသကဲ့သို့ အောင်တံခွန်ကို လွှားလွှားလွှင့်တော်မူ၍ သားတော်မြတ် နှစ်ပါးနှင့်တကွ ဆွေတော် မျိုးတော် ကျွန်တော်ရင်း မြင်းရည်တက် လေးဆယ့်ခြောက်ခေါင်း အစု အမှုထမ်း လက်နက်စွဲ သူရဲအပေါင်း ခြံရံလျက် မင်းတို့စံပယ်ခြင်းဖြင့် စည်တော်ရွမ်း၍ အရှေ့မျက်နှာ လက်ယာတံခါးမှ ရွှေထီးဖြန့်လျက် ထွက်တော် မူသည်ကို မွန်တို့တပ်က မြင်လျှင် သောသောထ၍ ကြည့်ကြစဉ် ကောင်းကင်အရပ်က သိမ်းငှက်တစ်ခုသည် စွန်ရဲကို တိုက်၍ ရှေ့တော်တူရူ ဦးခေါင်းငိုက်ဆိုက် ကျလာသည်ကို ရဲမက်တော်တို့ လှံနှင့်နှိပ်၍ ရလိုက်သည်။ | M5: At that time, Alaungmintayagyi Paya, in the year 1144, on the eighth day of the waning moon of Kason, a Friday, at the time just past two strokes of the afternoon, in order to suppress the Asura soldiers who were marching toward the Tavatimsa Mahasudassana city as if by analogy, raised the victory banner high as if Sakra were emerging from the auspicious Cittakuta gate, and surrounded by his two noble sons, his relatives, his kin, his loyal servants, forty-six cavalrymen, and all the armed soldiers and service personnel, with the royal drums beating in the royal manner, he emerged from the right gate on the eastern side with the golden umbrella spread; when the Mon army saw this, they rose up in a clamor to watch, and at that moment, a hawk from the sky attacked a kite, and it fell headlong directly in front of him, which the royal soldiers struck with spears and caught.
A6: First 5% | B6: vol1 | C6: 71 | D6: vol1_s000407 | E6: vol1_s000407_t05_008bb89c30b3 | F6: Mon_army | G6: OBSERVED_ROYAL_DISPLAY_OF | H6: Alaungmintayagyi | I6: supported | J6: Supported by the Burmese sentence and allowed narrative context; grouping and contextually inferred participants accepted. | L6: ထိုအခါ အလောင်းမင်းတရားကြီး ဘုရားလည်း သက္ကရာဇ် တစ်ထောင့် တစ်ရာ့ လေးဆယ့် လေးခု၊ ကဆုန်လပြည့်ကျော်ရှစ်ရက် သောကြာနေ့၊ မွန်းယိမ်းနှစ်ချက်တီးကျော် နှစ်မောင်းတွင် အတန္တုအားဖြင့် တာဝတိံသာ မဟာသုဒဿနမြို့သို့ ချီတက်လာကုန်သော အသူရာစစ်သည်တို့ကို နှိပ်နင်းအံ့သောငှာ မင်္ဂလာရှိသော စိတ္တကုဋ် တံခါးမှ သိကြားထွက်စံသကဲ့သို့ အောင်တံခွန်ကို လွှားလွှားလွှင့်တော်မူ၍ သားတော်မြတ် နှစ်ပါးနှင့်တကွ ဆွေတော် မျိုးတော် ကျွန်တော်ရင်း မြင်းရည်တက် လေးဆယ့်ခြောက်ခေါင်း အစု အမှုထမ်း လက်နက်စွဲ သူရဲအပေါင်း ခြံရံလျက် မင်းတို့စံပယ်ခြင်းဖြင့် စည်တော်ရွမ်း၍ အရှေ့မျက်နှာ လက်ယာတံခါးမှ ရွှေထီးဖြန့်လျက် ထွက်တော် မူသည်ကို မွန်တို့တပ်က မြင်လျှင် သောသောထ၍ ကြည့်ကြစဉ် ကောင်းကင်အရပ်က သိမ်းငှက်တစ်ခုသည် စွန်ရဲကို တိုက်၍ ရှေ့တော်တူရူ ဦးခေါင်းငိုက်ဆိုက် ကျလာသည်ကို ရဲမက်တော်တို့ လှံနှင့်နှိပ်၍ ရလိုက်သည်။ | M6: At that time, Alaungmintayagyi Paya, in the year 1144, on the eighth day of the waning moon of Kason, a Friday, at the time just past two strokes of the afternoon, in order to suppress the Asura soldiers who were marching toward the Tavatimsa Mahasudassana city as if by analogy, raised the victory banner high as if Sakra were emerging from the auspicious Cittakuta gate, and surrounded by his two noble sons, his relatives, his kin, his loyal servants, forty-six cavalrymen, and all the armed soldiers and service personnel, with the royal drums beating in the royal manner, he emerged from the right gate on the eastern side with the golden umbrella spread; when the Mon army saw this, they rose up in a clamor to watch, and at that moment, a hawk from the sky attacked a kite, and it fell headlong directly in front of him, which the royal soldiers struck with spears and caught.
A7: First 5% | B7: vol1 | C7: 71 | D7: vol1_s000407 | E7: vol1_s000407_t06_9f6b39839bb4 | F7: Omen | G7: SIGNALED_VICTORY_FOR | H7: Alaungmintayagyi | I7: supported | J7: Supported by the Burmese sentence and allowed narrative context; grouping and contextually inferred participants accepted. | L7: ထိုအခါ အလောင်းမင်းတရားကြီး ဘုရားလည်း သက္ကရာဇ် တစ်ထောင့် တစ်ရာ့ လေးဆယ့် လေးခု၊ ကဆုန်လပြည့်ကျော်ရှစ်ရက် သောကြာနေ့၊ မွန်းယိမ်းနှစ်ချက်တီးကျော် နှစ်မောင်းတွင် အတန္တုအားဖြင့် တာဝတိံသာ မဟာသုဒဿနမြို့သို့ ချီတက်လာကုန်သော အသူရာစစ်သည်တို့ကို နှိပ်နင်းအံ့သောငှာ မင်္ဂလာရှိသော စိတ္တကုဋ် တံခါးမှ သိကြားထွက်စံသကဲ့သို့ အောင်တံခွန်ကို လွှားလွှားလွှင့်တော်မူ၍ သားတော်မြတ် နှစ်ပါးနှင့်တကွ ဆွေတော် မျိုးတော် ကျွန်တော်ရင်း မြင်းရည်တက် လေးဆယ့်ခြောက်ခေါင်း အစု အမှုထမ်း လက်နက်စွဲ သူရဲအပေါင်း ခြံရံလျက် မင်းတို့စံပယ်ခြင်းဖြင့် စည်တော်ရွမ်း၍ အရှေ့မျက်နှာ လက်ယာတံခါးမှ ရွှေထီးဖြန့်လျက် ထွက်တော် မူသည်ကို မွန်တို့တပ်က မြင်လျှင် သောသောထ၍ ကြည့်ကြစဉ် ကောင်းကင်အရပ်က သိမ်းငှက်တစ်ခုသည် စွန်ရဲကို တိုက်၍ ရှေ့တော်တူရူ ဦးခေါင်းငိုက်ဆိုက် ကျလာသည်ကို ရဲမက်တော်တို့ လှံနှင့်နှိပ်၍ ရလိုက်သည်။ | M7: At that time, Alaungmintayagyi Paya, in the year 1144, on the eighth day of the waning moon of Kason, a Friday, at the time just past two strokes of the afternoon, in order to suppress the Asura soldiers who were marching toward the Tavatimsa Mahasudassana city as if by analogy, raised the victory banner high as if Sakra were emerging from the auspicious Cittakuta gate, and surrounded by his two noble sons, his relatives, his kin, his loyal servants, forty-six cavalrymen, and all the armed soldiers and service personnel, with the royal drums beating in the royal manner, he emerged from the right gate on the eastern side with the golden umbrella spread; when the Mon army saw this, they rose up in a clamor to watch, and at that moment, a hawk from the sky attacked a kite, and it fell headlong directly in front of him, which the royal soldiers struck with spears and caught.
A8: First 5% | B8: vol1 | C8: 71 | D8: vol1_s000408 | E8: vol1_s000408_t01_b0fbd1f80d6b | F8: Alaungmintayagyi | G8: INTERPRETED_OMEN_AS | H8: inevitable_victory | I8: supported | J8: Supported by the Burmese sentence and allowed narrative context; grouping and contextually inferred participants accepted. | L8: ထိုနိမိတ်ကို မြင်တော်မူလျှင် စွန်နံဖြစ်သော မွန်ကို သိမ်းနံဖြစ်သော ငါမင်းတရားသည် ယခုနေ့ အောင်မြင် တော်မူမည် မချွတ်ဟု ဘတ်တော်မူပြီးမှ ငါတည်း မင်းမျိုးမင်းမြစ် မှန်သည်ဖြစ်၍ ရဟန်းရှင်လူ ပြည်သူတကာ သာသနာတော်မြတ်၏ စီးပွား၊ မယ်တော်, ခမည်းတော်, ဆွေတော် မျိုးတော်တို့၏ စီးပွား၊ သားတော်အစဉ် မြေးတော်အဆက် မြစ်တော်အညွန့် တိုင်အောင် ဆောင်တော်မူထိုက်သည် မှန်လျှင် သိကြား၊ စတုလောကပါလာ၊ သာသနာတော်မြတ်ကို စောင့်ကုန်သော သမ္မာဒေဝ နတ်မြတ်အပေါင်း ကောင်းသော ကြည့်ရှုခြင်းဖြင့် ညီညာ ရွက်ဆောင်သည်ဖြစ်၍ အလွယ်တကူ ရန်သူတော်တို့ကို လှံထင်ဆောက်ကာ ပြီးမြောက် အောင်မြင်တော်မူစေ သောဟု ရွှေကရားဖြင့် ရေစက်သွန်းတော်မူပြီးလျှင် ရေ မြေသို့ရောက်သည်နှင့် တစ်ပြိုင်နက် “အောင်ခါ ရောက်ပြီ၊ အောင်ချိန်သင့်ပြီ၊ အောင်ခါတန်ပြီ”ဟု ညွှန်းသော စကားဖြင့် အောင်သံပေးတော်မူသည်ကို မြန်မာစစ်သည် မွန်စစ်သည် အပေါင်းတို့သည် နားရင်းကြပ်ကြပ်အပ်၍ ဟစ်ကြော်ဘိကဲ့သို့ တပ်လုံး ကြားလေ၏။ | M8: Upon seeing this omen, he declared, 'I, King Alaungmintaya, who am the hawk, will undoubtedly be victorious this day over the Mon, who are the kite,' and after declaring this, he poured water from a golden ewer, saying, 'Since I am truly of royal lineage, if it is true that I am worthy to carry out the welfare of the noble religion for all monks and laypeople, the welfare of my mother, father, relatives, and kin, and the welfare of my sons, grandsons, and great-grandsons, then may Sakra, the Four Heavenly Kings, and all the noble Samma-deva spirits who guard the noble religion look upon me with favor, act in unison, and cause me to easily pierce the enemies with spears and achieve complete victory,' and as soon as the water reached the earth, he gave the signal for victory with the words, 'The time for victory has arrived, the time for victory is appropriate, the time for victory is due,' which the Burmese soldiers and all the Mon soldiers heard throughout the entire camp as if they were shouting it right into their ears.
A9: First 5% | B9: vol1 | C9: 71 | D9: vol1_s000408 | E9: vol1_s000408_t02_c56a1c317678 | F9: Alaungmintayagyi | G9: INVOKED_SUPERNATURAL_PROTECTION_OF | H9: Sakra_and_Four_Heavenly_Kings_and_Samma_deva_spirits | I9: supported | J9: Supported by the Burmese sentence and allowed narrative context; grouping and contextually inferred participants accepted. | L9: ထိုနိမိတ်ကို မြင်တော်မူလျှင် စွန်နံဖြစ်သော မွန်ကို သိမ်းနံဖြစ်သော ငါမင်းတရားသည် ယခုနေ့ အောင်မြင် တော်မူမည် မချွတ်ဟု ဘတ်တော်မူပြီးမှ ငါတည်း မင်းမျိုးမင်းမြစ် မှန်သည်ဖြစ်၍ ရဟန်းရှင်လူ ပြည်သူတကာ သာသနာတော်မြတ်၏ စီးပွား၊ မယ်တော်, ခမည်းတော်, ဆွေတော် မျိုးတော်တို့၏ စီးပွား၊ သားတော်အစဉ် မြေးတော်အဆက် မြစ်တော်အညွန့် တိုင်အောင် ဆောင်တော်မူထိုက်သည် မှန်လျှင် သိကြား၊ စတုလောကပါလာ၊ သာသနာတော်မြတ်ကို စောင့်ကုန်သော သမ္မာဒေဝ နတ်မြတ်အပေါင်း ကောင်းသော ကြည့်ရှုခြင်းဖြင့် ညီညာ ရွက်ဆောင်သည်ဖြစ်၍ အလွယ်တကူ ရန်သူတော်တို့ကို လှံထင်ဆောက်ကာ ပြီးမြောက် အောင်မြင်တော်မူစေ သောဟု ရွှေကရားဖြင့် ရေစက်သွန်းတော်မူပြီးလျှင် ရေ မြေသို့ရောက်သည်နှင့် တစ်ပြိုင်နက် “အောင်ခါ ရောက်ပြီ၊ အောင်ချိန်သင့်ပြီ၊ အောင်ခါတန်ပြီ”ဟု ညွှန်းသော စကားဖြင့် အောင်သံပေးတော်မူသည်ကို မြန်မာစစ်သည် မွန်စစ်သည် အပေါင်းတို့သည် နားရင်းကြပ်ကြပ်အပ်၍ ဟစ်ကြော်ဘိကဲ့သို့ တပ်လုံး ကြားလေ၏။ | M9: Upon seeing this omen, he declared, 'I, King Alaungmintaya, who am the hawk, will undoubtedly be victorious this day over the Mon, who are the kite,' and after declaring this, he poured water from a golden ewer, saying, 'Since I am truly of royal lineage, if it is true that I am worthy to carry out the welfare of the noble religion for all monks and laypeople, the welfare of my mother, father, relatives, and kin, and the welfare of my sons, grandsons, and great-grandsons, then may Sakra, the Four Heavenly Kings, and all the noble Samma-deva spirits who guard the noble religion look upon me with favor, act in unison, and cause me to easily pierce the enemies with spears and achieve complete victory,' and as soon as the water reached the earth, he gave the signal for victory with the words, 'The time for victory has arrived, the time for victory is appropriate, the time for victory is due,' which the Burmese soldiers and all the Mon soldiers heard throughout the entire camp as if they were shouting it right into their ears.
A10: First 5% | B10: vol1 | C10: 71 | D10: vol1_s000408 | E10: vol1_s000408_t03_d6fdde6ee5ab | F10: Alaungmintayagyi | G10: PERFORMED_RITUAL_OATH_VIA | H10: pouring_water_from_golden_ewer | I10: supported | J10: Supported by the Burmese sentence and allowed narrative context; grouping and contextually inferred participants accepted. | L10: ထိုနိမိတ်ကို မြင်တော်မူလျှင် စွန်နံဖြစ်သော မွန်ကို သိမ်းနံဖြစ်သော ငါမင်းတရားသည် ယခုနေ့ အောင်မြင် တော်မူမည် မချွတ်ဟု ဘတ်တော်မူပြီးမှ ငါတည်း မင်းမျိုးမင်းမြစ် မှန်သည်ဖြစ်၍ ရဟန်းရှင်လူ ပြည်သူတကာ သာသနာတော်မြတ်၏ စီးပွား၊ မယ်တော်, ခမည်းတော်, ဆွေတော် မျိုးတော်တို့၏ စီးပွား၊ သားတော်အစဉ် မြေးတော်အဆက် မြစ်တော်အညွန့် တိုင်အောင် ဆောင်တော်မူထိုက်သည် မှန်လျှင် သိကြား၊ စတုလောကပါလာ၊ သာသနာတော်မြတ်ကို စောင့်ကုန်သော သမ္မာဒေဝ နတ်မြတ်အပေါင်း ကောင်းသော ကြည့်ရှုခြင်းဖြင့် ညီညာ ရွက်ဆောင်သည်ဖြစ်၍ အလွယ်တကူ ရန်သူတော်တို့ကို လှံထင်ဆောက်ကာ ပြီးမြောက် အောင်မြင်တော်မူစေ သောဟု ရွှေကရားဖြင့် ရေစက်သွန်းတော်မူပြီးလျှင် ရေ မြေသို့ရောက်သည်နှင့် တစ်ပြိုင်နက် “အောင်ခါ ရောက်ပြီ၊ အောင်ချိန်သင့်ပြီ၊ အောင်ခါတန်ပြီ”ဟု ညွှန်းသော စကားဖြင့် အောင်သံပေးတော်မူသည်ကို မြန်မာစစ်သည် မွန်စစ်သည် အပေါင်းတို့သည် နားရင်းကြပ်ကြပ်အပ်၍ ဟစ်ကြော်ဘိကဲ့သို့ တပ်လုံး ကြားလေ၏။ | M10: Upon seeing this omen, he declared, 'I, King Alaungmintaya, who am the hawk, will undoubtedly be victorious this day over the Mon, who are the kite,' and after declaring this, he poured water from a golden ewer, saying, 'Since I am truly of royal lineage, if it is true that I am worthy to carry out the welfare of the noble religion for all monks and laypeople, the welfare of my mother, father, relatives, and kin, and the welfare of my sons, grandsons, and great-grandsons, then may Sakra, the Four Heavenly Kings, and all the noble Samma-deva spirits who guard the noble religion look upon me with favor, act in unison, and cause me to easily pierce the enemies with spears and achieve complete victory,' and as soon as the water reached the earth, he gave the signal for victory with the words, 'The time for victory has arrived, the time for victory is appropriate, the time for victory is due,' which the Burmese soldiers and all the Mon soldiers heard throughout the entire camp as if they were shouting it right into their ears.
A11: First 5% | B11: vol1 | C11: 71 | D11: vol1_s000408 | E11: vol1_s000408_t04_53fd29578911 | F11: Alaungmintayagyi | G11: CLAIMED_LEGITIMACY_THROUGH | H11: royal_lineage_and_Buddhist_welfare | I11: supported | J11: Supported by the Burmese sentence and allowed narrative context; grouping and contextually inferred participants accepted. | L11: ထိုနိမိတ်ကို မြင်တော်မူလျှင် စွန်နံဖြစ်သော မွန်ကို သိမ်းနံဖြစ်သော ငါမင်းတရားသည် ယခုနေ့ အောင်မြင် တော်မူမည် မချွတ်ဟု ဘတ်တော်မူပြီးမှ ငါတည်း မင်းမျိုးမင်းမြစ် မှန်သည်ဖြစ်၍ ရဟန်းရှင်လူ ပြည်သူတကာ သာသနာတော်မြတ်၏ စီးပွား၊ မယ်တော်, ခမည်းတော်, ဆွေတော် မျိုးတော်တို့၏ စီးပွား၊ သားတော်အစဉ် မြေးတော်အဆက် မြစ်တော်အညွန့် တိုင်အောင် ဆောင်တော်မူထိုက်သည် မှန်လျှင် သိကြား၊ စတုလောကပါလာ၊ သာသနာတော်မြတ်ကို စောင့်ကုန်သော သမ္မာဒေဝ နတ်မြတ်အပေါင်း ကောင်းသော ကြည့်ရှုခြင်းဖြင့် ညီညာ ရွက်ဆောင်သည်ဖြစ်၍ အလွယ်တကူ ရန်သူတော်တို့ကို လှံထင်ဆောက်ကာ ပြီးမြောက် အောင်မြင်တော်မူစေ သောဟု ရွှေကရားဖြင့် ရေစက်သွန်းတော်မူပြီးလျှင် ရေ မြေသို့ရောက်သည်နှင့် တစ်ပြိုင်နက် “အောင်ခါ ရောက်ပြီ၊ အောင်ချိန်သင့်ပြီ၊ အောင်ခါတန်ပြီ”ဟု ညွှန်းသော စကားဖြင့် အောင်သံပေးတော်မူသည်ကို မြန်မာစစ်သည် မွန်စစ်သည် အပေါင်းတို့သည် နားရင်းကြပ်ကြပ်အပ်၍ ဟစ်ကြော်ဘိကဲ့သို့ တပ်လုံး ကြားလေ၏။ | M11: Upon seeing this omen, he declared, 'I, King Alaungmintaya, who am the hawk, will undoubtedly be victorious this day over the Mon, who are the kite,' and after declaring this, he poured water from a golden ewer, saying, 'Since I am truly of royal lineage, if it is true that I am worthy to carry out the welfare of the noble religion for all monks and laypeople, the welfare of my mother, father, relatives, and kin, and the welfare of my sons, grandsons, and great-grandsons, then may Sakra, the Four Heavenly Kings, and all the noble Samma-deva spirits who guard the noble religion look upon me with favor, act in unison, and cause me to easily pierce the enemies with spears and achieve complete victory,' and as soon as the water reached the earth, he gave the signal for victory with the words, 'The time for victory has arrived, the time for victory is appropriate, the time for victory is due,' which the Burmese soldiers and all the Mon soldiers heard throughout the entire camp as if they were shouting it right into their ears.
A12: First 5% | B12: vol1 | C12: 71 | D12: vol1_s000408 | E12: vol1_s000408_t05_515c37baf5b4 | F12: Alaungmintayagyi | G12: ISSUED_COMMAND_TO | H12: Burmese_and_Mon_soldiers | I12: soft | J12: Both armies hear the king’s victory cry. The triple turns that joint audience into the recipients of a command, including the enemy. The utterance is real, but its relation to the audience is misconstructed. | K12: Alaungmintayagyi | GAVE_VICTORY_SIGNAL_HEARD_BY | Burmese and Mon soldiers | L12: ထိုနိမိတ်ကို မြင်တော်မူလျှင် စွန်နံဖြစ်သော မွန်ကို သိမ်းနံဖြစ်သော ငါမင်းတရားသည် ယခုနေ့ အောင်မြင် တော်မူမည် မချွတ်ဟု ဘတ်တော်မူပြီးမှ ငါတည်း မင်းမျိုးမင်းမြစ် မှန်သည်ဖြစ်၍ ရဟန်းရှင်လူ ပြည်သူတကာ သာသနာတော်မြတ်၏ စီးပွား၊ မယ်တော်, ခမည်းတော်, ဆွေတော် မျိုးတော်တို့၏ စီးပွား၊ သားတော်အစဉ် မြေးတော်အဆက် မြစ်တော်အညွန့် တိုင်အောင် ဆောင်တော်မူထိုက်သည် မှန်လျှင် သိကြား၊ စတုလောကပါလာ၊ သာသနာတော်မြတ်ကို စောင့်ကုန်သော သမ္မာဒေဝ နတ်မြတ်အပေါင်း ကောင်းသော ကြည့်ရှုခြင်းဖြင့် ညီညာ ရွက်ဆောင်သည်ဖြစ်၍ အလွယ်တကူ ရန်သူတော်တို့ကို လှံထင်ဆောက်ကာ ပြီးမြောက် အောင်မြင်တော်မူစေ သောဟု ရွှေကရားဖြင့် ရေစက်သွန်းတော်မူပြီးလျှင် ရေ မြေသို့ရောက်သည်နှင့် တစ်ပြိုင်နက် “အောင်ခါ ရောက်ပြီ၊ အောင်ချိန်သင့်ပြီ၊ အောင်ခါတန်ပြီ”ဟု ညွှန်းသော စကားဖြင့် အောင်သံပေးတော်မူသည်ကို မြန်မာစစ်သည် မွန်စစ်သည် အပေါင်းတို့သည် နားရင်းကြပ်ကြပ်အပ်၍ ဟစ်ကြော်ဘိကဲ့သို့ တပ်လုံး ကြားလေ၏။ | M12: Upon seeing this omen, he declared, 'I, King Alaungmintaya, who am the hawk, will undoubtedly be victorious this day over the Mon, who are the kite,' and after declaring this, he poured water from a golden ewer, saying, 'Since I am truly of royal lineage, if it is true that I am worthy to carry out the welfare of the noble religion for all monks and laypeople, the welfare of my mother, father, relatives, and kin, and the welfare of my sons, grandsons, and great-grandsons, then may Sakra, the Four Heavenly Kings, and all the noble Samma-deva spirits who guard the noble religion look upon me with favor, act in unison, and cause me to easily pierce the enemies with spears and achieve complete victory,' and as soon as the water reached the earth, he gave the signal for victory with the words, 'The time for victory has arrived, the time for victory is appropriate, the time for victory is due,' which the Burmese soldiers and all the Mon soldiers heard throughout the entire camp as if they were shouting it right into their ears.
A13: First 5% | B13: vol1 | C13: 71 | D13: vol1_s000408 | E13: vol1_s000408_t06_8c758f29b409 | F13: Burmese_and_Mon_soldiers | G13: HEARD_ROYAL_SIGNAL_OF | H13: victory | I13: supported | J13: Supported by the Burmese sentence and allowed narrative context; grouping and contextually inferred participants accepted. | L13: ထိုနိမိတ်ကို မြင်တော်မူလျှင် စွန်နံဖြစ်သော မွန်ကို သိမ်းနံဖြစ်သော ငါမင်းတရားသည် ယခုနေ့ အောင်မြင် တော်မူမည် မချွတ်ဟု ဘတ်တော်မူပြီးမှ ငါတည်း မင်းမျိုးမင်းမြစ် မှန်သည်ဖြစ်၍ ရဟန်းရှင်လူ ပြည်သူတကာ သာသနာတော်မြတ်၏ စီးပွား၊ မယ်တော်, ခမည်းတော်, ဆွေတော် မျိုးတော်တို့၏ စီးပွား၊ သားတော်အစဉ် မြေးတော်အဆက် မြစ်တော်အညွန့် တိုင်အောင် ဆောင်တော်မူထိုက်သည် မှန်လျှင် သိကြား၊ စတုလောကပါလာ၊ သာသနာတော်မြတ်ကို စောင့်ကုန်သော သမ္မာဒေဝ နတ်မြတ်အပေါင်း ကောင်းသော ကြည့်ရှုခြင်းဖြင့် ညီညာ ရွက်ဆောင်သည်ဖြစ်၍ အလွယ်တကူ ရန်သူတော်တို့ကို လှံထင်ဆောက်ကာ ပြီးမြောက် အောင်မြင်တော်မူစေ သောဟု ရွှေကရားဖြင့် ရေစက်သွန်းတော်မူပြီးလျှင် ရေ မြေသို့ရောက်သည်နှင့် တစ်ပြိုင်နက် “အောင်ခါ ရောက်ပြီ၊ အောင်ချိန်သင့်ပြီ၊ အောင်ခါတန်ပြီ”ဟု ညွှန်းသော စကားဖြင့် အောင်သံပေးတော်မူသည်ကို မြန်မာစစ်သည် မွန်စစ်သည် အပေါင်းတို့သည် နားရင်းကြပ်ကြပ်အပ်၍ ဟစ်ကြော်ဘိကဲ့သို့ တပ်လုံး ကြားလေ၏။ | M13: Upon seeing this omen, he declared, 'I, King Alaungmintaya, who am the hawk, will undoubtedly be victorious this day over the Mon, who are the kite,' and after declaring this, he poured water from a golden ewer, saying, 'Since I am truly of royal lineage, if it is true that I am worthy to carry out the welfare of the noble religion for all monks and laypeople, the welfare of my mother, father, relatives, and kin, and the welfare of my sons, grandsons, and great-grandsons, then may Sakra, the Four Heavenly Kings, and all the noble Samma-deva spirits who guard the noble religion look upon me with favor, act in unison, and cause me to easily pierce the enemies with spears and achieve complete victory,' and as soon as the water reached the earth, he gave the signal for victory with the words, 'The time for victory has arrived, the time for victory is appropriate, the time for victory is due,' which the Burmese soldiers and all the Mon soldiers heard throughout the entire camp as if they were shouting it right into their ears.
A14: First 5% | B14: vol1 | C14: 71 | D14: vol1_s000409 | E14: vol1_s000409_t01_7dd4a7d1314c | F14: Alaungmintayagyi | G14: EXERTED_ROYAL_AUTHORITY_THROUGH | H14: voice_and_charisma | I14: supported | J14: Supported by the Burmese sentence and allowed narrative context; grouping and contextually inferred participants accepted. | L14: ထိုအခါ ပမာအားဖြင့် ကေသရရာဇာ ခြင်္သေ့မင်းသည် ရွှေဂူဝမှ ခုန်ကြွစံပယ်လျက် ထွက်၍ ဟောက်မြူးသောအသံကို တောင်ယံကမ်းပါး ကျက်စားရှိကုန်သော သားအပေါင်းတို့သည် ကြောက်ခြင်းပြင်းရကား ကမ်းပါးချောက်သို့ ဦးစောက်ကျဘိ သကဲ့သို့ မွန်စစ်သည် အပေါင်းတို့သည် အလောင်းမင်းတရားကြီးဘုရား အသံတော်ကို ကြားလျှင် ဘုန်းအာဏာတော်အား သတိမတည်နိုင်၍ လက်နက်လွတ်ကျသော ဟူ၏။ | M14: At that time, it is said that just as when the lion king, the Kesararaja, leaps out from the mouth of a golden cave and roars, all the animals living on the mountain slopes are so terrified that they fall headlong into the ravines, so too, when the Mon soldiers heard the voice of Alaungmintayagyi Paya, they could not maintain their composure due to his royal power and authority, and they dropped their weapons.
A15: First 5% | B15: vol1 | C15: 71 | D15: vol1_s000409 | E15: vol1_s000409_t02_02d08094e321 | F15: Mon_soldiers | G15: SUFFERED_MORALE_COLLAPSE_FROM | H15: Alaungmintayagyi_voice | I15: supported | J15: Supported by the Burmese sentence and allowed narrative context; grouping and contextually inferred participants accepted. | L15: ထိုအခါ ပမာအားဖြင့် ကေသရရာဇာ ခြင်္သေ့မင်းသည် ရွှေဂူဝမှ ခုန်ကြွစံပယ်လျက် ထွက်၍ ဟောက်မြူးသောအသံကို တောင်ယံကမ်းပါး ကျက်စားရှိကုန်သော သားအပေါင်းတို့သည် ကြောက်ခြင်းပြင်းရကား ကမ်းပါးချောက်သို့ ဦးစောက်ကျဘိ သကဲ့သို့ မွန်စစ်သည် အပေါင်းတို့သည် အလောင်းမင်းတရားကြီးဘုရား အသံတော်ကို ကြားလျှင် ဘုန်းအာဏာတော်အား သတိမတည်နိုင်၍ လက်နက်လွတ်ကျသော ဟူ၏။ | M15: At that time, it is said that just as when the lion king, the Kesararaja, leaps out from the mouth of a golden cave and roars, all the animals living on the mountain slopes are so terrified that they fall headlong into the ravines, so too, when the Mon soldiers heard the voice of Alaungmintayagyi Paya, they could not maintain their composure due to his royal power and authority, and they dropped their weapons.
A16: First 5% | B16: vol1 | C16: 71 | D16: vol1_s000409 | E16: vol1_s000409_t03_60475c497770 | F16: Mon_soldiers | G16: ABANDONED_WEAPONS_DUE_TO | H16: royal_power | I16: supported | J16: Supported by the Burmese sentence and allowed narrative context; grouping and contextually inferred participants accepted. | L16: ထိုအခါ ပမာအားဖြင့် ကေသရရာဇာ ခြင်္သေ့မင်းသည် ရွှေဂူဝမှ ခုန်ကြွစံပယ်လျက် ထွက်၍ ဟောက်မြူးသောအသံကို တောင်ယံကမ်းပါး ကျက်စားရှိကုန်သော သားအပေါင်းတို့သည် ကြောက်ခြင်းပြင်းရကား ကမ်းပါးချောက်သို့ ဦးစောက်ကျဘိ သကဲ့သို့ မွန်စစ်သည် အပေါင်းတို့သည် အလောင်းမင်းတရားကြီးဘုရား အသံတော်ကို ကြားလျှင် ဘုန်းအာဏာတော်အား သတိမတည်နိုင်၍ လက်နက်လွတ်ကျသော ဟူ၏။ | M16: At that time, it is said that just as when the lion king, the Kesararaja, leaps out from the mouth of a golden cave and roars, all the animals living on the mountain slopes are so terrified that they fall headlong into the ravines, so too, when the Mon soldiers heard the voice of Alaungmintayagyi Paya, they could not maintain their composure due to his royal power and authority, and they dropped their weapons.
A17: First 5% | B17: vol1 | C17: 71 | D17: vol1_s000410 | E17: vol1_s000410_t01_6fb674c9e392 | F17: Royal_army | G17: EXECUTED_COMMAND_OF | H17: Alaungmintayagyi | I17: supported | J17: Supported by the Burmese sentence and allowed narrative context; grouping and contextually inferred participants accepted. | L17: " ယင်းသို့ စင်တွင် တပ်မတော်မှ အောင်စည် အောင်မောင်း သောင်းသောင်းသောသော တီးမှုတ်စေလျက် အမှတ်ပေးတော်မူလျှင် လေးဆယ့်ငါးတပ် စွဲမှတ်ရှိနေကုန်သော မြင်းစီးသူရဲ၊ သေနတ်စွဲသူရဲ၊ လေးစွဲသူရဲ၊ ရထားစွဲသူရဲ၊ တင်ကျည်းစွဲ သူရဲတို့လည်း တစ်ပြိုင်နက် ကြော်ငြာလျက် အဆုတ်အဆိုင်းမရှိ ချွံချွံရွပ်ရွပ် ထိုးခုတ်ပစ်ခတ်ကြသည်ကို မွန်တို့လည်း မဆုတ်မနစ် ကြိုး၍ခံသည်၊ မနည်းကြာ တစ်ဦးကိုတစ်ဦး မတိုးမဝှေ့ နိုင်၊ အထွေးထွေးရှိစဉ် အလောင်း မင်းတရားကြီးဘုရား ကိုယ်တော်တိုင် ကွပ်သည်ကို ရဲမက်တော်တို့မြင်လျှင် အသက်ကို ပန်းတစ်ပွင့် အနှိုင်းမမှတ် စွန့်စား ထိုးခုတ် ပစ်ခတ်ကြသောကြောင့် မွန်တို့ အရှအန အသေအပျောက် များသည်နှင့် မနည်းကြာအမ်း၍ ရှိနေစဉ် တပ်မတော်နှင့်တကွ တောင်ဘိ၏သို့ တစ်ဟုန်တည်း တိုက်တော်မူလျှင် မွန်တို့ မခံနိုင်၍ အဆီးအတားမရှိ ပျက်လေ၏။ | M17: In this way, when the royal army gave the signal by beating the victory drums and gongs loudly, the forty-five units of cavalrymen, musketeers, archers, charioteers, and spearmen all at once shouted and charged forward without hesitation, stabbing and shooting fiercely; the Mon also resisted with unyielding effort, and for a while, they could not push or shove one another, and while they were in this state of entanglement, the royal soldiers saw Alaungmintayagyi Paya himself directing the battle, and because they fought, stabbed, and shot with such abandon, regarding their lives as no more than a flower, the Mon suffered many casualties and deaths, and while they were wavering for a while, he attacked with the royal army in one swift rush toward the south, and the Mon could not withstand it and were defeated without obstruction.
A18: First 5% | B18: vol1 | C18: 71 | D18: vol1_s000410 | E18: vol1_s000410_t02_ef2633dfdf11 | F18: Alaungmintayagyi | G18: DIRECTED_BATTLE_PERSONALLY | H18: royal_army | I18: supported | J18: Supported by the Burmese sentence and allowed narrative context; grouping and contextually inferred participants accepted. | L18: " ယင်းသို့ စင်တွင် တပ်မတော်မှ အောင်စည် အောင်မောင်း သောင်းသောင်းသောသော တီးမှုတ်စေလျက် အမှတ်ပေးတော်မူလျှင် လေးဆယ့်ငါးတပ် စွဲမှတ်ရှိနေကုန်သော မြင်းစီးသူရဲ၊ သေနတ်စွဲသူရဲ၊ လေးစွဲသူရဲ၊ ရထားစွဲသူရဲ၊ တင်ကျည်းစွဲ သူရဲတို့လည်း တစ်ပြိုင်နက် ကြော်ငြာလျက် အဆုတ်အဆိုင်းမရှိ ချွံချွံရွပ်ရွပ် ထိုးခုတ်ပစ်ခတ်ကြသည်ကို မွန်တို့လည်း မဆုတ်မနစ် ကြိုး၍ခံသည်၊ မနည်းကြာ တစ်ဦးကိုတစ်ဦး မတိုးမဝှေ့ နိုင်၊ အထွေးထွေးရှိစဉ် အလောင်း မင်းတရားကြီးဘုရား ကိုယ်တော်တိုင် ကွပ်သည်ကို ရဲမက်တော်တို့မြင်လျှင် အသက်ကို ပန်းတစ်ပွင့် အနှိုင်းမမှတ် စွန့်စား ထိုးခုတ် ပစ်ခတ်ကြသောကြောင့် မွန်တို့ အရှအန အသေအပျောက် များသည်နှင့် မနည်းကြာအမ်း၍ ရှိနေစဉ် တပ်မတော်နှင့်တကွ တောင်ဘိ၏သို့ တစ်ဟုန်တည်း တိုက်တော်မူလျှင် မွန်တို့ မခံနိုင်၍ အဆီးအတားမရှိ ပျက်လေ၏။ | M18: In this way, when the royal army gave the signal by beating the victory drums and gongs loudly, the forty-five units of cavalrymen, musketeers, archers, charioteers, and spearmen all at once shouted and charged forward without hesitation, stabbing and shooting fiercely; the Mon also resisted with unyielding effort, and for a while, they could not push or shove one another, and while they were in this state of entanglement, the royal soldiers saw Alaungmintayagyi Paya himself directing the battle, and because they fought, stabbed, and shot with such abandon, regarding their lives as no more than a flower, the Mon suffered many casualties and deaths, and while they were wavering for a while, he attacked with the royal army in one swift rush toward the south, and the Mon could not withstand it and were defeated without obstruction.
A19: First 5% | B19: vol1 | C19: 71 | D19: vol1_s000410 | E19: vol1_s000410_t03_46bb5d1bcdce | F19: Mon_forces | G19: RESISTED_MILITARY_ASSAULT_OF | H19: royal_army | I19: supported | J19: Supported by the Burmese sentence and allowed narrative context; grouping and contextually inferred participants accepted. | L19: " ယင်းသို့ စင်တွင် တပ်မတော်မှ အောင်စည် အောင်မောင်း သောင်းသောင်းသောသော တီးမှုတ်စေလျက် အမှတ်ပေးတော်မူလျှင် လေးဆယ့်ငါးတပ် စွဲမှတ်ရှိနေကုန်သော မြင်းစီးသူရဲ၊ သေနတ်စွဲသူရဲ၊ လေးစွဲသူရဲ၊ ရထားစွဲသူရဲ၊ တင်ကျည်းစွဲ သူရဲတို့လည်း တစ်ပြိုင်နက် ကြော်ငြာလျက် အဆုတ်အဆိုင်းမရှိ ချွံချွံရွပ်ရွပ် ထိုးခုတ်ပစ်ခတ်ကြသည်ကို မွန်တို့လည်း မဆုတ်မနစ် ကြိုး၍ခံသည်၊ မနည်းကြာ တစ်ဦးကိုတစ်ဦး မတိုးမဝှေ့ နိုင်၊ အထွေးထွေးရှိစဉ် အလောင်း မင်းတရားကြီးဘုရား ကိုယ်တော်တိုင် ကွပ်သည်ကို ရဲမက်တော်တို့မြင်လျှင် အသက်ကို ပန်းတစ်ပွင့် အနှိုင်းမမှတ် စွန့်စား ထိုးခုတ် ပစ်ခတ်ကြသောကြောင့် မွန်တို့ အရှအန အသေအပျောက် များသည်နှင့် မနည်းကြာအမ်း၍ ရှိနေစဉ် တပ်မတော်နှင့်တကွ တောင်ဘိ၏သို့ တစ်ဟုန်တည်း တိုက်တော်မူလျှင် မွန်တို့ မခံနိုင်၍ အဆီးအတားမရှိ ပျက်လေ၏။ | M19: In this way, when the royal army gave the signal by beating the victory drums and gongs loudly, the forty-five units of cavalrymen, musketeers, archers, charioteers, and spearmen all at once shouted and charged forward without hesitation, stabbing and shooting fiercely; the Mon also resisted with unyielding effort, and for a while, they could not push or shove one another, and while they were in this state of entanglement, the royal soldiers saw Alaungmintayagyi Paya himself directing the battle, and because they fought, stabbed, and shot with such abandon, regarding their lives as no more than a flower, the Mon suffered many casualties and deaths, and while they were wavering for a while, he attacked with the royal army in one swift rush toward the south, and the Mon could not withstand it and were defeated without obstruction.
A20: First 5% | B20: vol1 | C20: 71 | D20: vol1_s000410 | E20: vol1_s000410_t04_3fe015232093 | F20: Mon_forces | G20: SUFFERED_DEFEAT_BY | H20: royal_army | I20: supported | J20: Supported by the Burmese sentence and allowed narrative context; grouping and contextually inferred participants accepted. | L20: " ယင်းသို့ စင်တွင် တပ်မတော်မှ အောင်စည် အောင်မောင်း သောင်းသောင်းသောသော တီးမှုတ်စေလျက် အမှတ်ပေးတော်မူလျှင် လေးဆယ့်ငါးတပ် စွဲမှတ်ရှိနေကုန်သော မြင်းစီးသူရဲ၊ သေနတ်စွဲသူရဲ၊ လေးစွဲသူရဲ၊ ရထားစွဲသူရဲ၊ တင်ကျည်းစွဲ သူရဲတို့လည်း တစ်ပြိုင်နက် ကြော်ငြာလျက် အဆုတ်အဆိုင်းမရှိ ချွံချွံရွပ်ရွပ် ထိုးခုတ်ပစ်ခတ်ကြသည်ကို မွန်တို့လည်း မဆုတ်မနစ် ကြိုး၍ခံသည်၊ မနည်းကြာ တစ်ဦးကိုတစ်ဦး မတိုးမဝှေ့ နိုင်၊ အထွေးထွေးရှိစဉ် အလောင်း မင်းတရားကြီးဘုရား ကိုယ်တော်တိုင် ကွပ်သည်ကို ရဲမက်တော်တို့မြင်လျှင် အသက်ကို ပန်းတစ်ပွင့် အနှိုင်းမမှတ် စွန့်စား ထိုးခုတ် ပစ်ခတ်ကြသောကြောင့် မွန်တို့ အရှအန အသေအပျောက် များသည်နှင့် မနည်းကြာအမ်း၍ ရှိနေစဉ် တပ်မတော်နှင့်တကွ တောင်ဘိ၏သို့ တစ်ဟုန်တည်း တိုက်တော်မူလျှင် မွန်တို့ မခံနိုင်၍ အဆီးအတားမရှိ ပျက်လေ၏။ | M20: In this way, when the royal army gave the signal by beating the victory drums and gongs loudly, the forty-five units of cavalrymen, musketeers, archers, charioteers, and spearmen all at once shouted and charged forward without hesitation, stabbing and shooting fiercely; the Mon also resisted with unyielding effort, and for a while, they could not push or shove one another, and while they were in this state of entanglement, the royal soldiers saw Alaungmintayagyi Paya himself directing the battle, and because they fought, stabbed, and shot with such abandon, regarding their lives as no more than a flower, the Mon suffered many casualties and deaths, and while they were wavering for a while, he attacked with the royal army in one swift rush toward the south, and the Mon could not withstand it and were defeated without obstruction.
A21: First 5% | B21: vol1 | C21: 71 | D21: vol1_s000410 | E21: vol1_s000410_t05_0fefbe13d092 | F21: Royal_soldiers | G21: DEMONSTRATED_LOYALTY_THROUGH | H21: self_sacrifice | I21: supported | J21: Supported by the Burmese sentence and allowed narrative context; grouping and contextually inferred participants accepted. | L21: " ယင်းသို့ စင်တွင် တပ်မတော်မှ အောင်စည် အောင်မောင်း သောင်းသောင်းသောသော တီးမှုတ်စေလျက် အမှတ်ပေးတော်မူလျှင် လေးဆယ့်ငါးတပ် စွဲမှတ်ရှိနေကုန်သော မြင်းစီးသူရဲ၊ သေနတ်စွဲသူရဲ၊ လေးစွဲသူရဲ၊ ရထားစွဲသူရဲ၊ တင်ကျည်းစွဲ သူရဲတို့လည်း တစ်ပြိုင်နက် ကြော်ငြာလျက် အဆုတ်အဆိုင်းမရှိ ချွံချွံရွပ်ရွပ် ထိုးခုတ်ပစ်ခတ်ကြသည်ကို မွန်တို့လည်း မဆုတ်မနစ် ကြိုး၍ခံသည်၊ မနည်းကြာ တစ်ဦးကိုတစ်ဦး မတိုးမဝှေ့ နိုင်၊ အထွေးထွေးရှိစဉ် အလောင်း မင်းတရားကြီးဘုရား ကိုယ်တော်တိုင် ကွပ်သည်ကို ရဲမက်တော်တို့မြင်လျှင် အသက်ကို ပန်းတစ်ပွင့် အနှိုင်းမမှတ် စွန့်စား ထိုးခုတ် ပစ်ခတ်ကြသောကြောင့် မွန်တို့ အရှအန အသေအပျောက် များသည်နှင့် မနည်းကြာအမ်း၍ ရှိနေစဉ် တပ်မတော်နှင့်တကွ တောင်ဘိ၏သို့ တစ်ဟုန်တည်း တိုက်တော်မူလျှင် မွန်တို့ မခံနိုင်၍ အဆီးအတားမရှိ ပျက်လေ၏။ | M21: In this way, when the royal army gave the signal by beating the victory drums and gongs loudly, the forty-five units of cavalrymen, musketeers, archers, charioteers, and spearmen all at once shouted and charged forward without hesitation, stabbing and shooting fiercely; the Mon also resisted with unyielding effort, and for a while, they could not push or shove one another, and while they were in this state of entanglement, the royal soldiers saw Alaungmintayagyi Paya himself directing the battle, and because they fought, stabbed, and shot with such abandon, regarding their lives as no more than a flower, the Mon suffered many casualties and deaths, and while they were wavering for a while, he attacked with the royal army in one swift rush toward the south, and the Mon could not withstand it and were defeated without obstruction.
A22: First 5% | B22: vol1 | C22: 71 | D22: vol1_s000411 | E22: vol1_s000411_t01_7937cc94dec9 | F22: Mon_main_army | G22: SUFFERED_COLLAPSE_OF | H22: defensive_structure | I22: supported | J22: Supported by the Burmese sentence and allowed narrative context; grouping and contextually inferred participants accepted. | L22: အရှေ့မျက်နှာက မွန်တို့ တပ်မ ပျက်လျှင် တောင်မျက်နှာ၊ အနောက်မျက်နှာ၊ မြောက်မျက်နှာ၊ ရံတပ်အလုံးလည်း ပျက်ပြန်လေ၏။ | M22: When the Mon main army on the eastern side was defeated, the southern, western, and northern sides, and all the supporting units, were also defeated.
A23: First 5% | B23: vol1 | C23: 71 | D23: vol1_s000411 | E23: vol1_s000411_t02_d89bf0092878 | F23: Mon_supporting_units | G23: SUFFERED_COLLAPSE_OF | H23: defensive_structure | I23: supported | J23: Supported by the Burmese sentence and allowed narrative context; grouping and contextually inferred participants accepted. | L23: အရှေ့မျက်နှာက မွန်တို့ တပ်မ ပျက်လျှင် တောင်မျက်နှာ၊ အနောက်မျက်နှာ၊ မြောက်မျက်နှာ၊ ရံတပ်အလုံးလည်း ပျက်ပြန်လေ၏။ | M23: When the Mon main army on the eastern side was defeated, the southern, western, and northern sides, and all the supporting units, were also defeated.
A24: First 5% | B24: vol1 | C24: 71 | D24: vol1_s000412 | E24: vol1_s000412_t01_836e01a281d6 | F24: Northern_wind | G24: AIDED_MILITARY_PURSUIT_OF | H24: royal_soldiers | I24: supported | J24: Supported by the Burmese sentence and allowed narrative context; grouping and contextually inferred participants accepted. | L24: ယင်းသောအခါ ကဆုန် နွေလ ဖြစ်လျက် မြောက်လေ ပြင်းစွာလာလတ်၍ မြူမှုန်ခြောင်းခြောင်း တောင်သို့ဘိကာ မွန်တို့ ဆုတ်ခွာသည်ကို ရဲမက်တော်တို့ လိုက်ထပ်ထိုးခုတ် ပစ်ခတ်လျှင် မွန်စစ်သည်တို့ ခါးဝတ်မဆည်း စစ်ကြီး ထောင်းထောင်းပျက်၍ ကိုယ်လွတ် ဆုတ်ခွာရလေ၏။ | M24: At that time, it being the summer month of Kason, a strong north wind blew, and as the Mon retreated toward the south amidst clouds of dust, the royal soldiers pursued them, stabbing and shooting, so the Mon soldiers, unable to even fasten their waistcloths, suffered a total collapse of their great army and had to retreat to save their own lives.
... A31: First 5% | B31: vol1 | C31: 77 | D31: vol1_s000476 | E31: vol1_s000476_t02_0709fa67e2f8 | F31: Musopo King | G31: MOBILIZED_MILITARY_FORCE | H31: 2000-3000 soldiers | I31: supported | J31: Supported by the Burmese sentence and allowed narrative context; grouping and contextually inferred participants accepted. | L31: ယင်းသောအခါ အဝဗိုလ်မှူး ငွေခွန်ဝန်က မူဆိုးပိုမင်းသည် ထန်းလုံးတပ်ကို သံမြို့မှတ်၍ လူနှစ်ထောင် သုံးထောင်နှင့် အခိုင်နေလေသည်မှာ မြောက်ဘက်တစ်လွှား ငါးစို့တစ်ခွင်၊ မြို့ကျေးရွာများကို သိမ်းရုံးပြီးလျှင် ခင်ဦးစား လက်ယာပျံချီကို မြောက်ဘက် မျက်နှာက ရံစေမည်၊ အဲနရဲ၊ အဲကန်ကောင်းတို့ကိုလည်း ကျောက်မြောင်းတိုင် မြို့ ရွာများကို သိမ်းယူဆန်တက်၍ အရှေ့မျက်နှာက ရံစေမည်။ | M31: At that time, the Ava commander, the Ngwekwanwun, stated that the Musopo King [the Mon King] had designated the Thanlon fort as a fortified city and was holding it firmly with two or three thousand men, and that after seizing the towns and villages in the Ngasint region across the north, he would have Khin-U-sa Let-ya-pyanchi surround it from the northern front, and would have Aenarae and Aekankaung seize the Kyaukmyaung-taing towns and villages and march up to surround it from the eastern front.
A32: First 5% | B32: vol1 | C32: 77 | D32: vol1_s000476 | E32: vol1_s000476_t03_e18c108df2bc | F32: Musopo King | G32: APPOINTED_COMMANDER | H32: Khin-U-sa Let-ya-pyanchi | I32: hard | J32: The speaking commander is the Ava Mon commander Ngwekhunwun, introduced by အဝဗိုလ်မှူး ငွေခွန်ဝန်က. The Moksobo ruler is the target of the encirclement, not the issuer of these assignments. | K32: Ngwekhunwun | ASSIGNED_NORTHERN_ENCIRCLEMENT_TO | Khin-U-sa Let-ya-pyanchi | L32: ယင်းသောအခါ အဝဗိုလ်မှူး ငွေခွန်ဝန်က မူဆိုးပိုမင်းသည် ထန်းလုံးတပ်ကို သံမြို့မှတ်၍ လူနှစ်ထောင် သုံးထောင်နှင့် အခိုင်နေလေသည်မှာ မြောက်ဘက်တစ်လွှား ငါးစို့တစ်ခွင်၊ မြို့ကျေးရွာများကို သိမ်းရုံးပြီးလျှင် ခင်ဦးစား လက်ယာပျံချီကို မြောက်ဘက် မျက်နှာက ရံစေမည်၊ အဲနရဲ၊ အဲကန်ကောင်းတို့ကိုလည်း ကျောက်မြောင်းတိုင် မြို့ ရွာများကို သိမ်းယူဆန်တက်၍ အရှေ့မျက်နှာက ရံစေမည်။ | M32: At that time, the Ava commander, the Ngwekwanwun, stated that the Musopo King [the Mon King] had designated the Thanlon fort as a fortified city and was holding it firmly with two or three thousand men, and that after seizing the towns and villages in the Ngasint region across the north, he would have Khin-U-sa Let-ya-pyanchi surround it from the northern front, and would have Aenarae and Aekankaung seize the Kyaukmyaung-taing towns and villages and march up to surround it from the eastern front.
A33: First 5% | B33: vol1 | C33: 77 | D33: vol1_s000476 | E33: vol1_s000476_t04_fd98cf6593fe | F33: Musopo King | G33: APPOINTED_COMMANDER | H33: Aenarae and Aekankaung | I33: hard | J33: The speaking commander is the Ava Mon commander Ngwekhunwun, introduced by အဝဗိုလ်မှူး ငွေခွန်ဝန်က. The Moksobo ruler is the target of the encirclement, not the issuer of these assignments. | K33: Ngwekhunwun | ASSIGNED_EASTERN_ENCIRCLEMENT_TO | Aenarae and Aekankaung | L33: ယင်းသောအခါ အဝဗိုလ်မှူး ငွေခွန်ဝန်က မူဆိုးပိုမင်းသည် ထန်းလုံးတပ်ကို သံမြို့မှတ်၍ လူနှစ်ထောင် သုံးထောင်နှင့် အခိုင်နေလေသည်မှာ မြောက်ဘက်တစ်လွှား ငါးစို့တစ်ခွင်၊ မြို့ကျေးရွာများကို သိမ်းရုံးပြီးလျှင် ခင်ဦးစား လက်ယာပျံချီကို မြောက်ဘက် မျက်နှာက ရံစေမည်၊ အဲနရဲ၊ အဲကန်ကောင်းတို့ကိုလည်း ကျောက်မြောင်းတိုင် မြို့ ရွာများကို သိမ်းယူဆန်တက်၍ အရှေ့မျက်နှာက ရံစေမည်။ | M33: At that time, the Ava commander, the Ngwekwanwun, stated that the Musopo King [the Mon King] had designated the Thanlon fort as a fortified city and was holding it firmly with two or three thousand men, and that after seizing the towns and villages in the Ngasint region across the north, he would have Khin-U-sa Let-ya-pyanchi surround it from the northern front, and would have Aenarae and Aekankaung seize the Kyaukmyaung-taing towns and villages and march up to surround it from the eastern front.
A34: First 5% | B34: vol1 | C34: 77 | D34: vol1_s000477 | E34: vol1_s000477_t01_9bc0ee6b5563 | F34: Musopo King | G34: APPOINTED_COMMANDER | H34: Samainzeipbyae, Samainlut, Samainthanlaik, Ye-khaung-san-kyaw | I34: hard | J34: The speaking commander is the Ava Mon commander Ngwekhunwun, introduced by အဝဗိုလ်မှူး ငွေခွန်ဝန်က. The Moksobo ruler is the target of the encirclement, not the issuer of these assignments. | K34: Ngwekhunwun | ASSIGNED_WESTERN_ENCIRCLEMENT_TO | the four Mon commanders | L34: သမိန်ဇိပ်ဗြဲ၊ သမိန်လွတ်၊ သမိန်သံလိုက်၊ ရဲခေါင်စံကျော်တို့ကိုလည်း မူးမြစ်ကြောင်း အနောက်တစ်ပြင် မြို့ရွာများကို သိမ်းယူ၍ အနောက် မျက်နှာက ရံစေမည်၊ ငါလည်း ပိုက်သီဟ၊ ပိုက်ကမြင်းတို့နှင့် စစ်ကိုင်းကြောင်း ချီတက်၍ တောင်မျက်နှာက ရံမည်၊ သည်ကဲ့သို့ လေးကြောင်း လေးမျက်နှာ တက်၍ စစ်အားကြီး လုပ်ကြံရလျှင် မုဆိုးပိုတပ်သည် ငှက်မူ၍ ပျံထွက်နိုင်မည်လောဟု ကြုံးဝါးပြီးလျှင် သက္ကရာဇ် (၁၁၁၄) တစ်ထောင့်တစ်ရာ တစ်ဆယ့်လေးခု၊ သီတင်းကျွတ်လ တွင် သမိန်ဇိပ်ဗြဲ တစ်တပ်၊ သမိန်လွတ် တစ်တပ်၊ သမိန်သံလိုက် တစ်တပ်၊ ရဲခေါင်စံကျော် တစ်တပ်၊ သည် လေးတပ်တွင် မြင်းသုံးရာ၊ စစ်သည်သူရဲနှစ်ထောင့်ငါးရာ၊ မူးမြစ်ကြောင်း ချီနှင့်ရလေ၏။ | M34: He also stated that he would have Samainzeipbyae, Samainlut, Samainthanlaik, and Ye-khaung-san-kyaw seize the towns and villages on the western side of the Mu River and surround it from the western front, and that he himself would march along the Sagaing route with Paik-thiha and Paik-kamyin and surround it from the southern front; after boasting, 'If we attack with such great military force, advancing from four directions and four fronts, will the Musopo fort be able to fly away like a bird?', in the month of Thadingyut, in the year 1114, he sent one unit of Samainzeipbyae, one unit of Samainlut, one unit of Samainthanlaik, and one unit of Ye-khaung-san-kyaw—these four units, consisting of three hundred horses and two thousand five hundred soldiers—to march along the Mu River.
A35: First 5% | B35: vol1 | C35: 77 | D35: vol1_s000477 | E35: vol1_s000477_t02_8a4279ee1476 | F35: Musopo King | G35: PLANNED_ENCIRCLEMENT | H35: Nyaung-hla | I35: hard | J35: The Mon commander plans to surround Moksobo. This triple substitutes the Moksobo king as planner and Nyaunghla as the intended target. Nyaunghla is the later Mon staging camp, not the target named in this plan. | K35: Ngwekhunwun | PLANNED_ENCIRCLEMENT_OF | Moksobo | L35: သမိန်ဇိပ်ဗြဲ၊ သမိန်လွတ်၊ သမိန်သံလိုက်၊ ရဲခေါင်စံကျော်တို့ကိုလည်း မူးမြစ်ကြောင်း အနောက်တစ်ပြင် မြို့ရွာများကို သိမ်းယူ၍ အနောက် မျက်နှာက ရံစေမည်၊ ငါလည်း ပိုက်သီဟ၊ ပိုက်ကမြင်းတို့နှင့် စစ်ကိုင်းကြောင်း ချီတက်၍ တောင်မျက်နှာက ရံမည်၊ သည်ကဲ့သို့ လေးကြောင်း လေးမျက်နှာ တက်၍ စစ်အားကြီး လုပ်ကြံရလျှင် မုဆိုးပိုတပ်သည် ငှက်မူ၍ ပျံထွက်နိုင်မည်လောဟု ကြုံးဝါးပြီးလျှင် သက္ကရာဇ် (၁၁၁၄) တစ်ထောင့်တစ်ရာ တစ်ဆယ့်လေးခု၊ သီတင်းကျွတ်လ တွင် သမိန်ဇိပ်ဗြဲ တစ်တပ်၊ သမိန်လွတ် တစ်တပ်၊ သမိန်သံလိုက် တစ်တပ်၊ ရဲခေါင်စံကျော် တစ်တပ်၊ သည် လေးတပ်တွင် မြင်းသုံးရာ၊ စစ်သည်သူရဲနှစ်ထောင့်ငါးရာ၊ မူးမြစ်ကြောင်း ချီနှင့်ရလေ၏။ | M35: He also stated that he would have Samainzeipbyae, Samainlut, Samainthanlaik, and Ye-khaung-san-kyaw seize the towns and villages on the western side of the Mu River and surround it from the western front, and that he himself would march along the Sagaing route with Paik-thiha and Paik-kamyin and surround it from the southern front; after boasting, 'If we attack with such great military force, advancing from four directions and four fronts, will the Musopo fort be able to fly away like a bird?', in the month of Thadingyut, in the year 1114, he sent one unit of Samainzeipbyae, one unit of Samainlut, one unit of Samainthanlaik, and one unit of Ye-khaung-san-kyaw—these four units, consisting of three hundred horses and two thousand five hundred soldiers—to march along the Mu River.
A36: First 5% | B36: vol1 | C36: 77 | D36: vol1_s000477 | E36: vol1_s000477_t03_25771c827e6a | F36: Musopo King | G36: MOBILIZED_MILITARY_FORCE | H36: 300 horses and 2500 soldiers | I36: hard | J36: The 300 horses and 2,500 soldiers belong to the four advancing Mon battalions, not to the Moksobo king’s force. | K36: Ngwekhunwun / four Mon commanders | DISPATCHED | 300 horses and 2500 soldiers | L36: သမိန်ဇိပ်ဗြဲ၊ သမိန်လွတ်၊ သမိန်သံလိုက်၊ ရဲခေါင်စံကျော်တို့ကိုလည်း မူးမြစ်ကြောင်း အနောက်တစ်ပြင် မြို့ရွာများကို သိမ်းယူ၍ အနောက် မျက်နှာက ရံစေမည်၊ ငါလည်း ပိုက်သီဟ၊ ပိုက်ကမြင်းတို့နှင့် စစ်ကိုင်းကြောင်း ချီတက်၍ တောင်မျက်နှာက ရံမည်၊ သည်ကဲ့သို့ လေးကြောင်း လေးမျက်နှာ တက်၍ စစ်အားကြီး လုပ်ကြံရလျှင် မုဆိုးပိုတပ်သည် ငှက်မူ၍ ပျံထွက်နိုင်မည်လောဟု ကြုံးဝါးပြီးလျှင် သက္ကရာဇ် (၁၁၁၄) တစ်ထောင့်တစ်ရာ တစ်ဆယ့်လေးခု၊ သီတင်းကျွတ်လ တွင် သမိန်ဇိပ်ဗြဲ တစ်တပ်၊ သမိန်လွတ် တစ်တပ်၊ သမိန်သံလိုက် တစ်တပ်၊ ရဲခေါင်စံကျော် တစ်တပ်၊ သည် လေးတပ်တွင် မြင်းသုံးရာ၊ စစ်သည်သူရဲနှစ်ထောင့်ငါးရာ၊ မူးမြစ်ကြောင်း ချီနှင့်ရလေ၏။ | M36: He also stated that he would have Samainzeipbyae, Samainlut, Samainthanlaik, and Ye-khaung-san-kyaw seize the towns and villages on the western side of the Mu River and surround it from the western front, and that he himself would march along the Sagaing route with Paik-thiha and Paik-kamyin and surround it from the southern front; after boasting, 'If we attack with such great military force, advancing from four directions and four fronts, will the Musopo fort be able to fly away like a bird?', in the month of Thadingyut, in the year 1114, he sent one unit of Samainzeipbyae, one unit of Samainlut, one unit of Samainthanlaik, and one unit of Ye-khaung-san-kyaw—these four units, consisting of three hundred horses and two thousand five hundred soldiers—to march along the Mu River.
A37: First 5% | B37: vol1 | C37: 77 | D37: vol1_s000478 | E37: vol1_s000478_t01_5ee6ca8a38c6 | F37: Aenarae and Aekankaung | G37: MARCHED_TO | H37: Kyaukmyaung | I37: supported | J37: Supported by the Burmese sentence and allowed narrative context; grouping and contextually inferred participants accepted. | L37: အဲနရဲ၊ အဲကန်ကောင်းတို့ လည်း ဧရာဝတီမြစ်ကြောင်း ကျောက်မြောင်းရောက် ချီရလေသည်။ | M37: Aenarae and Aekankaung also marched along the Irrawaddy River route to reach Kyaukmyaung.
A38: First 5% | B38: vol1 | C38: 77 | D38: vol1_s000479 | E38: vol1_s000479_t01_94ee31f83371 | F38: Musopo King | G38: APPOINTED_COMMANDER | H38: Khin-U-sa Let-ya-pyanchi | I38: hard | J38: The speaking commander is the Ava Mon commander Ngwekhunwun, introduced by အဝဗိုလ်မှူး ငွေခွန်ဝန်က. The Moksobo ruler is the target of the encirclement, not the issuer of these assignments. The ongoing passage describes Mon deployments. | K38: Ngwekhunwun | DISPATCHED_MON_COMMANDERS_TO | Khin-U-sa Let-ya-pyanchi | L38: ခင်ဦးစား လက်ယာပျံချီသို့လည်း မြောက်ဘက် တစ်လွှား ငါးစို့တစ်ခွင် သိမ်းရုံးစည်းကြပ်ရမည်ဟု မွန်တပ်မှူးတို့ကို ခန့်ထားစေလွှတ်သည်။ | M38: He also appointed and sent Mon commanders to Khin-U-sa Let-ya-pyanchi to seize and organize the Ngasint region across the north.
A39: First 5% | B39: vol1 | C39: 77 | D39: vol1_s000479 | E39: vol1_s000479_t02_1407a7ea8054 | F39: Khin-U-sa Let-ya-pyanchi | G39: TASKED_WITH_CONTROLLING | H39: Ngasint region | I39: supported | J39: Supported by the Burmese sentence and allowed narrative context; grouping and contextually inferred participants accepted. | L39: ခင်ဦးစား လက်ယာပျံချီသို့လည်း မြောက်ဘက် တစ်လွှား ငါးစို့တစ်ခွင် သိမ်းရုံးစည်းကြပ်ရမည်ဟု မွန်တပ်မှူးတို့ကို ခန့်ထားစေလွှတ်သည်။ | M39: He also appointed and sent Mon commanders to Khin-U-sa Let-ya-pyanchi to seize and organize the Ngasint region across the north.
A40: First 5% | B40: vol1 | C40: 77 | D40: vol1_s000480 | E40: vol1_s000480_t01_70af7dca3c1d | F40: Alaungpaya | G40: RECEIVED_INTELLIGENCE_ON | H40: Mon progress at Nyaung-hla | I40: supported | J40: Supported by the Burmese sentence and allowed narrative context; grouping and contextually inferred participants accepted. | L40: ယင်းသောအခါ အနောက်ဘက် မူးကြောင်း အလျင်ချီနှင့်ရသည့် လေးဗိုလ်လေးတပ်တို့ ညောင်လှအရပ်သို့ ရောက်ကြောင်းကို အလောင်းမင်းတရားကြီးဘုရား ကြားတော်မူသော်လည်း ရွာသစ်ကြီးသို့ သေနတ်ဝန် မင်းကျော် ပျံချီ, မင်းလှရွှေတောင်တို့ ချီလေရာ သူရဲသူခက် လက်နက်ပါ ချေသောကြောင့် ခပ်မဆိတ် နေတော်မူ၏။ | M40: At that time, although the Alaungmintayagyi Phaya heard that the four commanders and four units that had marched ahead along the western Mu route had reached the Nyaunghla area, because the Thanatwun Minkyawpyanchi and Minhlashwetaung had marched to Ywathitgyi with soldiers and weapons, he remained silent.
A41: First 5% | B41: vol1 | C41: 77 | D41: vol1_s000480 | E41: vol1_s000480_t02_8b3494957d0f | F41: Alaungpaya | G41: EXERCISED_STRATEGIC_PATIENCE | H41: Military operations | I41: supported | J41: Supported by the Burmese sentence and allowed narrative context; grouping and contextually inferred participants accepted. | L41: ယင်းသောအခါ အနောက်ဘက် မူးကြောင်း အလျင်ချီနှင့်ရသည့် လေးဗိုလ်လေးတပ်တို့ ညောင်လှအရပ်သို့ ရောက်ကြောင်းကို အလောင်းမင်းတရားကြီးဘုရား ကြားတော်မူသော်လည်း ရွာသစ်ကြီးသို့ သေနတ်ဝန် မင်းကျော် ပျံချီ, မင်းလှရွှေတောင်တို့ ချီလေရာ သူရဲသူခက် လက်နက်ပါ ချေသောကြောင့် ခပ်မဆိတ် နေတော်မူ၏။ | M41: At that time, although the Alaungmintayagyi Phaya heard that the four commanders and four units that had marched ahead along the western Mu route had reached the Nyaunghla area, because the Thanatwun Minkyawpyanchi and Minhlashwetaung had marched to Ywathitgyi with soldiers and weapons, he remained silent.
A42: First 5% | B42: vol1 | C42: 77 | D42: vol1_s000481 | E42: vol1_s000481_t01_86b135767614 | F42: Royal commanders | G42: PROPOSED_ATTACK | H42: Nyaung-hla | I42: supported | J42: Supported by the Burmese sentence and allowed narrative context; grouping and contextually inferred participants accepted. | L42: ထိုအခါ သားတော် ညီတော် ဗိုလ်မှူး တပ်မှူးတို့က ယခု မွန်တို့ လေးတပ်ချီလာ၍ ညောင်လှအရပ်တွင် တပ်ကြီးတပ်ခိုင် တည်လုပ်လာသည်ကို တပ်မပြီးခင် အလျင်အမြန် ချီတက်၍ ဖျက်ဆီးသိမ်းယူပါမည်ဟု လျှောက်ကြသော်လည်း ဘဝရှင် အလောင်းမင်းတၱရားကြီးဘုရားသည် ရာဇမာယာ၌ လိမ္မာတော်မူသည်နှင့်အညီ ယခု တပ်မပြီးခင် ချီချေသော် မွန်တို့က ငါတို့ တပ်မပြီးခင်သောကြောင့်သာ ရှုံးရလေသည်ဟု ဆိုပြန်လေတော့မည်၊ တပ်ပြီးစေဦးဟု အမိန့်တော် ရှိ၍ ရပ်ဆိုင်းသည့်အတွင်း သေနတ်ဝန် မင်းကျော်ပျံချီ, မင်းလှရွှေတောင်တို့ ရွာသစ်ကြီးတပ်ကို ဖျက်သိမ်း ပြန်ရောက်၍ ယခု မွန်တို့က စစ်လေးမျက်နှာ ခန့်ရန် စည်းကြပ်ကြောင်းနှင့် အဝက ထွက်လာသူတို့ စစ်ချက်တွင် ကြားသိရသည့် အတိုင်း မွန်တို့က ညောင်လှတွင် တပ်တည်သည်ကို ချီ၍ တိုက်ပါမည်ဟု လျှောက်သည်တွင် မွန်တို့ တပ်တည်၍ ပြီးစေဦးတော့ဟု ငါ့အမိန့်တော် ရှိနှင့်သည်၊ ယခုမှာ မွန်တို့တပ်လည်း ပြီးတန်လေပြီ၊ ချီလေတော့ဟူ၍ အမိန့်တော် ရှိလျှင် သေနတ်ဝန် မင်းကျော်ပျံချီ, မင်းလှရွှေတောင်တို့ လက်နက်ကိုင် လူတစ်ထောင့်ငါးရာနှင့် ချက်တစ်ဖြုတ် ချီသွား၍ ညောင်လှတပ်သို့ ရောက်လျှင် တပ်မချဘဲ သမိန်သံလိုက်တပ်ကို တိုက်သည်။ | M42: At that time, although the royal sons, younger brothers, commanders, and unit leaders submitted that they would march quickly to destroy and seize the large, fortified fort that the four Mon units had come and built in the Nyaunghla area before it was completed, the Bawa-shin Alaungmintayagyi Phaya, being skilled in royal strategy, said, 'If we march before it is completed, the Mons will say they only lost because their fort was not finished; let them finish the fort,' and ordered a halt; while they were waiting, the Thanatwun Minkyawpyanchi and Minhlashwetaung destroyed the Ywathitgyi fort and returned, and upon hearing from the reports of those who came out from Ava that the Mons were organizing to attack from four directions, they submitted that they would march and attack the fort the Mons were building at Nyaunghla, to which [the King] replied, 'I have already given the order to let the Mons finish building their fort; now that the Mon fort must be finished, march,' and upon that order, the Thanatwun Minkyawpyanchi and Minhlashwetaung marched immediately with one thousand five hundred armed men, and upon reaching the Nyaunghla fort, they did not set up a camp but attacked the Samainthanlaik unit.
A43: First 5% | B43: vol1 | C43: 77 | D43: vol1_s000481 | E43: vol1_s000481_t02_e12d797c9038 | F43: Alaungpaya | G43: EXERCISED_ROYAL_STRATAGEM | H43: Military timing | I43: supported | J43: Supported by the Burmese sentence and allowed narrative context; grouping and contextually inferred participants accepted. | L43: ထိုအခါ သားတော် ညီတော် ဗိုလ်မှူး တပ်မှူးတို့က ယခု မွန်တို့ လေးတပ်ချီလာ၍ ညောင်လှအရပ်တွင် တပ်ကြီးတပ်ခိုင် တည်လုပ်လာသည်ကို တပ်မပြီးခင် အလျင်အမြန် ချီတက်၍ ဖျက်ဆီးသိမ်းယူပါမည်ဟု လျှောက်ကြသော်လည်း ဘဝရှင် အလောင်းမင်းတၱရားကြီးဘုရားသည် ရာဇမာယာ၌ လိမ္မာတော်မူသည်နှင့်အညီ ယခု တပ်မပြီးခင် ချီချေသော် မွန်တို့က ငါတို့ တပ်မပြီးခင်သောကြောင့်သာ ရှုံးရလေသည်ဟု ဆိုပြန်လေတော့မည်၊ တပ်ပြီးစေဦးဟု အမိန့်တော် ရှိ၍ ရပ်ဆိုင်းသည့်အတွင်း သေနတ်ဝန် မင်းကျော်ပျံချီ, မင်းလှရွှေတောင်တို့ ရွာသစ်ကြီးတပ်ကို ဖျက်သိမ်း ပြန်ရောက်၍ ယခု မွန်တို့က စစ်လေးမျက်နှာ ခန့်ရန် စည်းကြပ်ကြောင်းနှင့် အဝက ထွက်လာသူတို့ စစ်ချက်တွင် ကြားသိရသည့် အတိုင်း မွန်တို့က ညောင်လှတွင် တပ်တည်သည်ကို ချီ၍ တိုက်ပါမည်ဟု လျှောက်သည်တွင် မွန်တို့ တပ်တည်၍ ပြီးစေဦးတော့ဟု ငါ့အမိန့်တော် ရှိနှင့်သည်၊ ယခုမှာ မွန်တို့တပ်လည်း ပြီးတန်လေပြီ၊ ချီလေတော့ဟူ၍ အမိန့်တော် ရှိလျှင် သေနတ်ဝန် မင်းကျော်ပျံချီ, မင်းလှရွှေတောင်တို့ လက်နက်ကိုင် လူတစ်ထောင့်ငါးရာနှင့် ချက်တစ်ဖြုတ် ချီသွား၍ ညောင်လှတပ်သို့ ရောက်လျှင် တပ်မချဘဲ သမိန်သံလိုက်တပ်ကို တိုက်သည်။ | M43: At that time, although the royal sons, younger brothers, commanders, and unit leaders submitted that they would march quickly to destroy and seize the large, fortified fort that the four Mon units had come and built in the Nyaunghla area before it was completed, the Bawa-shin Alaungmintayagyi Phaya, being skilled in royal strategy, said, 'If we march before it is completed, the Mons will say they only lost because their fort was not finished; let them finish the fort,' and ordered a halt; while they were waiting, the Thanatwun Minkyawpyanchi and Minhlashwetaung destroyed the Ywathitgyi fort and returned, and upon hearing from the reports of those who came out from Ava that the Mons were organizing to attack from four directions, they submitted that they would march and attack the fort the Mons were building at Nyaunghla, to which [the King] replied, 'I have already given the order to let the Mons finish building their fort; now that the Mon fort must be finished, march,' and upon that order, the Thanatwun Minkyawpyanchi and Minhlashwetaung marched immediately with one thousand five hundred armed men, and upon reaching the Nyaunghla fort, they did not set up a camp but attacked the Samainthanlaik unit.
A44: First 5% | B44: vol1 | C44: 77 | D44: vol1_s000481 | E44: vol1_s000481_t03_44cf9924cffe | F44: Alaungpaya | G44: ORDERED_DELAY | H44: Attack on Nyaung-hla | I44: supported | J44: Supported by the Burmese sentence and allowed narrative context; grouping and contextually inferred participants accepted. | L44: ထိုအခါ သားတော် ညီတော် ဗိုလ်မှူး တပ်မှူးတို့က ယခု မွန်တို့ လေးတပ်ချီလာ၍ ညောင်လှအရပ်တွင် တပ်ကြီးတပ်ခိုင် တည်လုပ်လာသည်ကို တပ်မပြီးခင် အလျင်အမြန် ချီတက်၍ ဖျက်ဆီးသိမ်းယူပါမည်ဟု လျှောက်ကြသော်လည်း ဘဝရှင် အလောင်းမင်းတၱရားကြီးဘုရားသည် ရာဇမာယာ၌ လိမ္မာတော်မူသည်နှင့်အညီ ယခု တပ်မပြီးခင် ချီချေသော် မွန်တို့က ငါတို့ တပ်မပြီးခင်သောကြောင့်သာ ရှုံးရလေသည်ဟု ဆိုပြန်လေတော့မည်၊ တပ်ပြီးစေဦးဟု အမိန့်တော် ရှိ၍ ရပ်ဆိုင်းသည့်အတွင်း သေနတ်ဝန် မင်းကျော်ပျံချီ, မင်းလှရွှေတောင်တို့ ရွာသစ်ကြီးတပ်ကို ဖျက်သိမ်း ပြန်ရောက်၍ ယခု မွန်တို့က စစ်လေးမျက်နှာ ခန့်ရန် စည်းကြပ်ကြောင်းနှင့် အဝက ထွက်လာသူတို့ စစ်ချက်တွင် ကြားသိရသည့် အတိုင်း မွန်တို့က ညောင်လှတွင် တပ်တည်သည်ကို ချီ၍ တိုက်ပါမည်ဟု လျှောက်သည်တွင် မွန်တို့ တပ်တည်၍ ပြီးစေဦးတော့ဟု ငါ့အမိန့်တော် ရှိနှင့်သည်၊ ယခုမှာ မွန်တို့တပ်လည်း ပြီးတန်လေပြီ၊ ချီလေတော့ဟူ၍ အမိန့်တော် ရှိလျှင် သေနတ်ဝန် မင်းကျော်ပျံချီ, မင်းလှရွှေတောင်တို့ လက်နက်ကိုင် လူတစ်ထောင့်ငါးရာနှင့် ချက်တစ်ဖြုတ် ချီသွား၍ ညောင်လှတပ်သို့ ရောက်လျှင် တပ်မချဘဲ သမိန်သံလိုက်တပ်ကို တိုက်သည်။ | M44: At that time, although the royal sons, younger brothers, commanders, and unit leaders submitted that they would march quickly to destroy and seize the large, fortified fort that the four Mon units had come and built in the Nyaunghla area before it was completed, the Bawa-shin Alaungmintayagyi Phaya, being skilled in royal strategy, said, 'If we march before it is completed, the Mons will say they only lost because their fort was not finished; let them finish the fort,' and ordered a halt; while they were waiting, the Thanatwun Minkyawpyanchi and Minhlashwetaung destroyed the Ywathitgyi fort and returned, and upon hearing from the reports of those who came out from Ava that the Mons were organizing to attack from four directions, they submitted that they would march and attack the fort the Mons were building at Nyaunghla, to which [the King] replied, 'I have already given the order to let the Mons finish building their fort; now that the Mon fort must be finished, march,' and upon that order, the Thanatwun Minkyawpyanchi and Minhlashwetaung marched immediately with one thousand five hundred armed men, and upon reaching the Nyaunghla fort, they did not set up a camp but attacked the Samainthanlaik unit.
A45: First 5% | B45: vol1 | C45: 77 | D45: vol1_s000481 | E45: vol1_s000481_t04_ee4b249cb475 | F45: Alaungpaya | G45: ORDERED_ATTACK | H45: Thanatwun Minkyawpyanchi and Minhlashwetaung | I45: supported | J45: Supported by the Burmese sentence and allowed narrative context; grouping and contextually inferred participants accepted. | L45: ထိုအခါ သားတော် ညီတော် ဗိုလ်မှူး တပ်မှူးတို့က ယခု မွန်တို့ လေးတပ်ချီလာ၍ ညောင်လှအရပ်တွင် တပ်ကြီးတပ်ခိုင် တည်လုပ်လာသည်ကို တပ်မပြီးခင် အလျင်အမြန် ချီတက်၍ ဖျက်ဆီးသိမ်းယူပါမည်ဟု လျှောက်ကြသော်လည်း ဘဝရှင် အလောင်းမင်းတၱရားကြီးဘုရားသည် ရာဇမာယာ၌ လိမ္မာတော်မူသည်နှင့်အညီ ယခု တပ်မပြီးခင် ချီချေသော် မွန်တို့က ငါတို့ တပ်မပြီးခင်သောကြောင့်သာ ရှုံးရလေသည်ဟု ဆိုပြန်လေတော့မည်၊ တပ်ပြီးစေဦးဟု အမိန့်တော် ရှိ၍ ရပ်ဆိုင်းသည့်အတွင်း သေနတ်ဝန် မင်းကျော်ပျံချီ, မင်းလှရွှေတောင်တို့ ရွာသစ်ကြီးတပ်ကို ဖျက်သိမ်း ပြန်ရောက်၍ ယခု မွန်တို့က စစ်လေးမျက်နှာ ခန့်ရန် စည်းကြပ်ကြောင်းနှင့် အဝက ထွက်လာသူတို့ စစ်ချက်တွင် ကြားသိရသည့် အတိုင်း မွန်တို့က ညောင်လှတွင် တပ်တည်သည်ကို ချီ၍ တိုက်ပါမည်ဟု လျှောက်သည်တွင် မွန်တို့ တပ်တည်၍ ပြီးစေဦးတော့ဟု ငါ့အမိန့်တော် ရှိနှင့်သည်၊ ယခုမှာ မွန်တို့တပ်လည်း ပြီးတန်လေပြီ၊ ချီလေတော့ဟူ၍ အမိန့်တော် ရှိလျှင် သေနတ်ဝန် မင်းကျော်ပျံချီ, မင်းလှရွှေတောင်တို့ လက်နက်ကိုင် လူတစ်ထောင့်ငါးရာနှင့် ချက်တစ်ဖြုတ် ချီသွား၍ ညောင်လှတပ်သို့ ရောက်လျှင် တပ်မချဘဲ သမိန်သံလိုက်တပ်ကို တိုက်သည်။ | M45: At that time, although the royal sons, younger brothers, commanders, and unit leaders submitted that they would march quickly to destroy and seize the large, fortified fort that the four Mon units had come and built in the Nyaunghla area before it was completed, the Bawa-shin Alaungmintayagyi Phaya, being skilled in royal strategy, said, 'If we march before it is completed, the Mons will say they only lost because their fort was not finished; let them finish the fort,' and ordered a halt; while they were waiting, the Thanatwun Minkyawpyanchi and Minhlashwetaung destroyed the Ywathitgyi fort and returned, and upon hearing from the reports of those who came out from Ava that the Mons were organizing to attack from four directions, they submitted that they would march and attack the fort the Mons were building at Nyaunghla, to which [the King] replied, 'I have already given the order to let the Mons finish building their fort; now that the Mon fort must be finished, march,' and upon that order, the Thanatwun Minkyawpyanchi and Minhlashwetaung marched immediately with one thousand five hundred armed men, and upon reaching the Nyaunghla fort, they did not set up a camp but attacked the Samainthanlaik unit.
A46: First 5% | B46: vol1 | C46: 77 | D46: vol1_s000481 | E46: vol1_s000481_t05_9cb62cd963f0 | F46: Thanatwun Minkyawpyanchi and Minhlashwetaung | G46: ATTACKED | H46: Samainthanlaik unit | I46: supported | J46: Supported by the Burmese sentence and allowed narrative context; grouping and contextually inferred participants accepted. | L46: ထိုအခါ သားတော် ညီတော် ဗိုလ်မှူး တပ်မှူးတို့က ယခု မွန်တို့ လေးတပ်ချီလာ၍ ညောင်လှအရပ်တွင် တပ်ကြီးတပ်ခိုင် တည်လုပ်လာသည်ကို တပ်မပြီးခင် အလျင်အမြန် ချီတက်၍ ဖျက်ဆီးသိမ်းယူပါမည်ဟု လျှောက်ကြသော်လည်း ဘဝရှင် အလောင်းမင်းတၱရားကြီးဘုရားသည် ရာဇမာယာ၌ လိမ္မာတော်မူသည်နှင့်အညီ ယခု တပ်မပြီးခင် ချီချေသော် မွန်တို့က ငါတို့ တပ်မပြီးခင်သောကြောင့်သာ ရှုံးရလေသည်ဟု ဆိုပြန်လေတော့မည်၊ တပ်ပြီးစေဦးဟု အမိန့်တော် ရှိ၍ ရပ်ဆိုင်းသည့်အတွင်း သေနတ်ဝန် မင်းကျော်ပျံချီ, မင်းလှရွှေတောင်တို့ ရွာသစ်ကြီးတပ်ကို ဖျက်သိမ်း ပြန်ရောက်၍ ယခု မွန်တို့က စစ်လေးမျက်နှာ ခန့်ရန် စည်းကြပ်ကြောင်းနှင့် အဝက ထွက်လာသူတို့ စစ်ချက်တွင် ကြားသိရသည့် အတိုင်း မွန်တို့က ညောင်လှတွင် တပ်တည်သည်ကို ချီ၍ တိုက်ပါမည်ဟု လျှောက်သည်တွင် မွန်တို့ တပ်တည်၍ ပြီးစေဦးတော့ဟု ငါ့အမိန့်တော် ရှိနှင့်သည်၊ ယခုမှာ မွန်တို့တပ်လည်း ပြီးတန်လေပြီ၊ ချီလေတော့ဟူ၍ အမိန့်တော် ရှိလျှင် သေနတ်ဝန် မင်းကျော်ပျံချီ, မင်းလှရွှေတောင်တို့ လက်နက်ကိုင် လူတစ်ထောင့်ငါးရာနှင့် ချက်တစ်ဖြုတ် ချီသွား၍ ညောင်လှတပ်သို့ ရောက်လျှင် တပ်မချဘဲ သမိန်သံလိုက်တပ်ကို တိုက်သည်။ | M46: At that time, although the royal sons, younger brothers, commanders, and unit leaders submitted that they would march quickly to destroy and seize the large, fortified fort that the four Mon units had come and built in the Nyaunghla area before it was completed, the Bawa-shin Alaungmintayagyi Phaya, being skilled in royal strategy, said, 'If we march before it is completed, the Mons will say they only lost because their fort was not finished; let them finish the fort,' and ordered a halt; while they were waiting, the Thanatwun Minkyawpyanchi and Minhlashwetaung destroyed the Ywathitgyi fort and returned, and upon hearing from the reports of those who came out from Ava that the Mons were organizing to attack from four directions, they submitted that they would march and attack the fort the Mons were building at Nyaunghla, to which [the King] replied, 'I have already given the order to let the Mons finish building their fort; now that the Mon fort must be finished, march,' and upon that order, the Thanatwun Minkyawpyanchi and Minhlashwetaung marched immediately with one thousand five hundred armed men, and upon reaching the Nyaunghla fort, they did not set up a camp but attacked the Samainthanlaik unit.
A47: First 5% | B47: vol1 | C47: 77 | D47: vol1_s000482 | E47: vol1_s000482_t01_d615f46458fd | F47: Thanatwun Minkyawpyanchi and Minhlashwetaung | G47: DEFEATED | H47: Samainthanlaik unit | I47: supported | J47: Supported by the Burmese sentence and allowed narrative context; grouping and contextually inferred participants accepted. | L47: သမိန်သံလိုက် တပ်ပျက် လေ၏၊ သမိန်သံလိုက်လည်း မြင်းဦးတွင်ပင် သေလေ၏။ | M47: The Samainthanlaik unit was defeated, and Samainthanlaik died right on his horse.
A48: First 5% | B48: vol1 | C48: 77 | D48: vol1_s000482 | E48: vol1_s000482_t02_134d4cf7955a | F48: Samainthanlaik | G48: DIED_IN_BATTLE | H48: Nyaung-hla | I48: supported | J48: Supported by the Burmese sentence and allowed narrative context; grouping and contextually inferred participants accepted. | L48: သမိန်သံလိုက် တပ်ပျက် လေ၏၊ သမိန်သံလိုက်လည်း မြင်းဦးတွင်ပင် သေလေ၏။ | M48: The Samainthanlaik unit was defeated, and Samainthanlaik died right on his horse.
A49: First 5% | B49: vol1 | C49: 77 | D49: vol1_s000483 | E49: vol1_s000483_t01_b5161a85d7a7 | F49: Thanatwun Minkyawpyanchi and Minhlashwetaung | G49: DEFEATED | H49: Samainzeipbyae unit | I49: supported | J49: Supported by the Burmese sentence and allowed narrative context; grouping and contextually inferred participants accepted. | L49: သမိန်သံလိုက် တပ်ပျက်လျှင် သမိန်ဇိပ်ဗြဲတပ်ကို တိုက်သည်၊ ပျက်ပြန်လေ၏။ | M49: When the Samainthanlaik unit was defeated, they attacked the Samainzeipbyae unit, which was also defeated.
A50: First 5% | B50: vol1 | C50: 77 | D50: vol1_s000484 | E50: vol1_s000484_t01_572a80131d9e | F50: Thanatwun Minkyawpyanchi and Minhlashwetaung | G50: DEFEATED | H50: Samainlut unit | I50: supported | J50: Supported by the Burmese sentence and allowed narrative context; grouping and contextually inferred participants accepted. | L50: သမိန်ဇိပ်ဗြဲတပ် ပျက်လျှင် သမိန်လွတ် တပ်ကို တိုက်သည်၊ ပျက်ပြန်လေ၏။ | M50: When the Samainzeipbyae unit was defeated, they attacked the Samainlut unit, which was also defeated.
... A77: First 5% | B77: vol1 | C77: 108 | D77: vol1_s000799 | E77: vol1_s000799_t01_85fdff8bcd04 | F77: Mon leadership | G77: EXECUTED_RAPID_RETREAT | H77: Hanthawaddy | I77: supported | J77: Supported by the Burmese sentence and allowed narrative context; grouping and contextually inferred participants accepted. | L77: ဥပရာဇာ စသော မွန်တို့လည်း နေ့ညဉ့် မရပ်မဆိုင်း အပြင်း ခွာလေ၏။ | M77: The Mon, including the Uparaja, also retreated rapidly without stopping day or night.
A78: First 5% | B78: vol1 | C78: 108 | D78: vol1_s000800 | E78: vol1_s000800_t01_748d393bfd9e | F78: Mon leadership | G78: ABANDONED_SYMBOLIC_LEGITIMACY_OBJECT | H78: Mon royal umbrella | I78: soft | J78: The abandoned umbrella is the Mon hti intended for installation on Shwezigon pagoda, not simply a royal parasol. Abandonment and symbolic significance are supported; the object is imprecisely typed. | K78: Mon leadership | ABANDONED | Mon pagoda umbrella intended for Shwezigon | L78: ဆင်ဖြူကျွန်း ရေကြည်ဝတွင် အလျင်ထားခဲ့သည့် ရွှေစည်းခုံဘုရားမှာ တင်ရန် မွန်ထီးကို ပစ်ထားခဲ့ပြီးလျှင် ရဟန်း သံဃာတော်များကိုသာ တင်ယူ၍ ပြည်မြို့တွင် စစ်သူကြီး ဒလပန်းတို့ကို အစောင့်အနေ ခန့်ထားခဲ့ပြီးမှ ဟံသာဝတီရောက် စုန်လေ၏။ | M78: They abandoned the Mon umbrella that was to be placed on the Shwezigon Pagoda, which had been left earlier at Sinphyukyun Yekyiwa, took only the Buddhist monks on board, appointed the general Dalaban and others to guard Prome, and then sailed down to Hanthawaddy.
A79: First 5% | B79: vol1 | C79: 108 | D79: vol1_s000800 | E79: vol1_s000800_t02_f502f5541dda | F79: Dalaban | G79: APPOINTED_AS_GUARD_OF | H79: Prome | I79: supported | J79: Supported by the Burmese sentence and allowed narrative context; grouping and contextually inferred participants accepted. | L79: ဆင်ဖြူကျွန်း ရေကြည်ဝတွင် အလျင်ထားခဲ့သည့် ရွှေစည်းခုံဘုရားမှာ တင်ရန် မွန်ထီးကို ပစ်ထားခဲ့ပြီးလျှင် ရဟန်း သံဃာတော်များကိုသာ တင်ယူ၍ ပြည်မြို့တွင် စစ်သူကြီး ဒလပန်းတို့ကို အစောင့်အနေ ခန့်ထားခဲ့ပြီးမှ ဟံသာဝတီရောက် စုန်လေ၏။ | M79: They abandoned the Mon umbrella that was to be placed on the Shwezigon Pagoda, which had been left earlier at Sinphyukyun Yekyiwa, took only the Buddhist monks on board, appointed the general Dalaban and others to guard Prome, and then sailed down to Hanthawaddy.
A80: First 5% | B80: vol1 | C80: 108 | D80: vol1_s000801 | E80: vol1_s000801_t01_a5228c8dd625 | F80: Alaungmintaya | G80: ADMINISTERED_OATHS_OF_ALLEGIANCE_AT | H80: Pinmahti | I80: supported | J80: Supported by the Burmese sentence and allowed narrative context; grouping and contextually inferred participants accepted. | L80: အလောင်းမင်းတရားကြီး ပင်းမဲထီးရောက် ချီတော်မူ၍ သစ္စာပေးပြီး ရတနာသိင်္ဃမြို့သို့ ပြန်၍ နန်းတော် ဆက်လက် တည်လုပ်ခြင်း 6 ဘဝရှင် အလောင်းမင်းတရားကြီး ဘုရားလည်း တာဝတိံသာသို့ ရောက်လာကုန်သော အသူရာစစ်သည်အား သိကြား အောင်မြင်သောအခါကဲ့သို့ မကြားဘူးမြဲ အံ့ဘွယ်သရဲသော အောင်ခြင်းဖြင့် မွန်စစ်သည်ကို အောင်တော် မူလိုက်သည့် ပွဲတွင် သားတော် ညီတော် ဗိုလ်မှူး တပ်မှူး သူရဲသူခက် ရဲမက်တော်အပေါင်း ပွဲလမ်းရသသူတို့ကို အထိုက်အလျောက် ဆုပေးတော်မူပြီးမှ အဝသို့ ကူး၍ အဝမြို့နန်းတော်ရာ မြောက်နန်းမြို့ တော်တွင် သက်ကယ်နန်း နှင့် စံတော်မူသည်။ | M80: Alaungmintaya Gyi marched to Pinmahti, administered oaths of allegiance, returned to Ratanasingha City, and continued the construction of the palace. 6 The Lord of Life, Alaungmintaya Gyi, after having defeated the Mon soldiers with a victory so wondrous and unheard of, like when Sakra defeated the Asura soldiers who had reached Tavatimsa, gave appropriate rewards to his sons, younger brothers, commanders, battalion leaders, warriors, and all the soldiers who had participated in the victory, then crossed to Ava and resided in a temporary palace in the northern palace city at the site of the Ava royal palace.
A81: First 5% | B81: vol1 | C81: 108 | D81: vol1_s000801 | E81: vol1_s000801_t02_5571b3c9b3e5 | F81: Alaungmintaya | G81: DISTRIBUTED_REWARDS_TO | H81: Konbaung military elite | I81: supported | J81: Supported by the Burmese sentence and allowed narrative context; grouping and contextually inferred participants accepted. | L81: အလောင်းမင်းတရားကြီး ပင်းမဲထီးရောက် ချီတော်မူ၍ သစ္စာပေးပြီး ရတနာသိင်္ဃမြို့သို့ ပြန်၍ နန်းတော် ဆက်လက် တည်လုပ်ခြင်း 6 ဘဝရှင် အလောင်းမင်းတရားကြီး ဘုရားလည်း တာဝတိံသာသို့ ရောက်လာကုန်သော အသူရာစစ်သည်အား သိကြား အောင်မြင်သောအခါကဲ့သို့ မကြားဘူးမြဲ အံ့ဘွယ်သရဲသော အောင်ခြင်းဖြင့် မွန်စစ်သည်ကို အောင်တော် မူလိုက်သည့် ပွဲတွင် သားတော် ညီတော် ဗိုလ်မှူး တပ်မှူး သူရဲသူခက် ရဲမက်တော်အပေါင်း ပွဲလမ်းရသသူတို့ကို အထိုက်အလျောက် ဆုပေးတော်မူပြီးမှ အဝသို့ ကူး၍ အဝမြို့နန်းတော်ရာ မြောက်နန်းမြို့ တော်တွင် သက်ကယ်နန်း နှင့် စံတော်မူသည်။ | M81: Alaungmintaya Gyi marched to Pinmahti, administered oaths of allegiance, returned to Ratanasingha City, and continued the construction of the palace. 6 The Lord of Life, Alaungmintaya Gyi, after having defeated the Mon soldiers with a victory so wondrous and unheard of, like when Sakra defeated the Asura soldiers who had reached Tavatimsa, gave appropriate rewards to his sons, younger brothers, commanders, battalion leaders, warriors, and all the soldiers who had participated in the victory, then crossed to Ava and resided in a temporary palace in the northern palace city at the site of the Ava royal palace.
A82: First 5% | B82: vol1 | C82: 108 | D82: vol1_s000801 | E82: vol1_s000801_t03_fbb64dbbf13c | F82: Alaungmintaya | G82: ESTABLISHED_TEMPORARY_ROYAL_CENTER_AT | H82: Ava | I82: supported | J82: Supported by the Burmese sentence and allowed narrative context; grouping and contextually inferred participants accepted. | L82: အလောင်းမင်းတရားကြီး ပင်းမဲထီးရောက် ချီတော်မူ၍ သစ္စာပေးပြီး ရတနာသိင်္ဃမြို့သို့ ပြန်၍ နန်းတော် ဆက်လက် တည်လုပ်ခြင်း 6 ဘဝရှင် အလောင်းမင်းတရားကြီး ဘုရားလည်း တာဝတိံသာသို့ ရောက်လာကုန်သော အသူရာစစ်သည်အား သိကြား အောင်မြင်သောအခါကဲ့သို့ မကြားဘူးမြဲ အံ့ဘွယ်သရဲသော အောင်ခြင်းဖြင့် မွန်စစ်သည်ကို အောင်တော် မူလိုက်သည့် ပွဲတွင် သားတော် ညီတော် ဗိုလ်မှူး တပ်မှူး သူရဲသူခက် ရဲမက်တော်အပေါင်း ပွဲလမ်းရသသူတို့ကို အထိုက်အလျောက် ဆုပေးတော်မူပြီးမှ အဝသို့ ကူး၍ အဝမြို့နန်းတော်ရာ မြောက်နန်းမြို့ တော်တွင် သက်ကယ်နန်း နှင့် စံတော်မူသည်။ | M82: Alaungmintaya Gyi marched to Pinmahti, administered oaths of allegiance, returned to Ratanasingha City, and continued the construction of the palace. 6 The Lord of Life, Alaungmintaya Gyi, after having defeated the Mon soldiers with a victory so wondrous and unheard of, like when Sakra defeated the Asura soldiers who had reached Tavatimsa, gave appropriate rewards to his sons, younger brothers, commanders, battalion leaders, warriors, and all the soldiers who had participated in the victory, then crossed to Ava and resided in a temporary palace in the northern palace city at the site of the Ava royal palace.
A83: First 5% | B83: vol1 | C83: 132 | D83: vol1_s001034 | E83: vol1_s001034_t01_ab5eea88a94a | F83: King of Hanthawaddy | G83: REINFORCED_GARRISONS | H83: Syriam outpost | I83: supported | J83: Supported by the Burmese sentence and allowed narrative context; grouping and contextually inferred participants accepted. | L83: ဟံသာဝတီဘုရင်လည်း ပြည်မြို့မှာ စစ်ကြီးတွေ့ကြ၍ မွန်ဆိုသမျှ အကုန်ပျက်ကြောင်းကို ကြားလျှင် မြန်မာမင်းကား ငါတို့မြို့ ရင်းတိုင်အောင် ချီလာချိမ့်မည်၊ သံလျင်ကင်းဝတွင် ခြောက်တပ်နှင့်သာ မလုံလေသေးဟု ဈေးငယ်ဗိုလ်၊ ကုလားဗိုလ်၊ တုတ်တလုပ်ဗိုလ်၊ သေနစက်တို့ကို တိုက်လှေကြီး နှစ်ရာကျော်နှင့် ထပ်ဖြည့်ချီစေ၍ ပန်းလှိုင်ဝ ချောင်းနှစ်ဘက်တွင် တပ်ကြီးနှစ်တပ် တည်ပြီးလျှင် ရေခလုတ် အပြည့်စီဆင်၍ ခံစေ၏၊ ညီ ဗညားဒလ ကိုလည်း စစ်သည်တစ်သောင်းကျော်နှင့် သံလျင်မြို့ ကို ကျုံး မြောင်း မြို့ပြ, ပစ္စင် ရင်လျှောက် ဆင်ခလုတ် မြင်းခလုတ် ခိုင်ခန့်လုံခြုံအောင် ပြင်ဆင်၍ နေစေ၏။ | M83: When the King of Hanthawaddy heard that they had encountered a great battle in Prome and that everything the Mon had said was completely ruined, he thought, 'The Burmese King will surely march as far as our capital; six garrisons at the Thanlyin outpost are not enough,' and he ordered the Zay-Nge Bo, Kalar Bo, Tot-Ta-Lot Bo, and The-Ne-Set to reinforce them with over two hundred large war boats, established two large garrisons on both sides of the Panhlaing creek, and had them fully prepare water-traps to defend it; he also had his younger brother, Banya Dala, prepare the city of Thanlyin with moats, ditches, city walls, fortifications, breastworks, elephant-traps, and horse-traps to be strong and secure, and stay there.
A84: First 5% | B84: vol1 | C84: 132 | D84: vol1_s001034 | E84: vol1_s001034_t02_20f49d3eb183 | F84: King of Hanthawaddy | G84: ESTABLISHED_DEFENSIVE_POSITIONS | H84: Panhlaing creek | I84: supported | J84: Supported by the Burmese sentence and allowed narrative context; grouping and contextually inferred participants accepted. | L84: ဟံသာဝတီဘုရင်လည်း ပြည်မြို့မှာ စစ်ကြီးတွေ့ကြ၍ မွန်ဆိုသမျှ အကုန်ပျက်ကြောင်းကို ကြားလျှင် မြန်မာမင်းကား ငါတို့မြို့ ရင်းတိုင်အောင် ချီလာချိမ့်မည်၊ သံလျင်ကင်းဝတွင် ခြောက်တပ်နှင့်သာ မလုံလေသေးဟု ဈေးငယ်ဗိုလ်၊ ကုလားဗိုလ်၊ တုတ်တလုပ်ဗိုလ်၊ သေနစက်တို့ကို တိုက်လှေကြီး နှစ်ရာကျော်နှင့် ထပ်ဖြည့်ချီစေ၍ ပန်းလှိုင်ဝ ချောင်းနှစ်ဘက်တွင် တပ်ကြီးနှစ်တပ် တည်ပြီးလျှင် ရေခလုတ် အပြည့်စီဆင်၍ ခံစေ၏၊ ညီ ဗညားဒလ ကိုလည်း စစ်သည်တစ်သောင်းကျော်နှင့် သံလျင်မြို့ ကို ကျုံး မြောင်း မြို့ပြ, ပစ္စင် ရင်လျှောက် ဆင်ခလုတ် မြင်းခလုတ် ခိုင်ခန့်လုံခြုံအောင် ပြင်ဆင်၍ နေစေ၏။ | M84: When the King of Hanthawaddy heard that they had encountered a great battle in Prome and that everything the Mon had said was completely ruined, he thought, 'The Burmese King will surely march as far as our capital; six garrisons at the Thanlyin outpost are not enough,' and he ordered the Zay-Nge Bo, Kalar Bo, Tot-Ta-Lot Bo, and The-Ne-Set to reinforce them with over two hundred large war boats, established two large garrisons on both sides of the Panhlaing creek, and had them fully prepare water-traps to defend it; he also had his younger brother, Banya Dala, prepare the city of Thanlyin with moats, ditches, city walls, fortifications, breastworks, elephant-traps, and horse-traps to be strong and secure, and stay there.
A85: First 5% | B85: vol1 | C85: 132 | D85: vol1_s001034 | E85: vol1_s001034_t03_d4ad5b1b1631 | F85: King of Hanthawaddy | G85: APPOINTED_COMMANDER | H85: Banya Dala | I85: supported | J85: Supported by the Burmese sentence and allowed narrative context; grouping and contextually inferred participants accepted. | L85: ဟံသာဝတီဘုရင်လည်း ပြည်မြို့မှာ စစ်ကြီးတွေ့ကြ၍ မွန်ဆိုသမျှ အကုန်ပျက်ကြောင်းကို ကြားလျှင် မြန်မာမင်းကား ငါတို့မြို့ ရင်းတိုင်အောင် ချီလာချိမ့်မည်၊ သံလျင်ကင်းဝတွင် ခြောက်တပ်နှင့်သာ မလုံလေသေးဟု ဈေးငယ်ဗိုလ်၊ ကုလားဗိုလ်၊ တုတ်တလုပ်ဗိုလ်၊ သေနစက်တို့ကို တိုက်လှေကြီး နှစ်ရာကျော်နှင့် ထပ်ဖြည့်ချီစေ၍ ပန်းလှိုင်ဝ ချောင်းနှစ်ဘက်တွင် တပ်ကြီးနှစ်တပ် တည်ပြီးလျှင် ရေခလုတ် အပြည့်စီဆင်၍ ခံစေ၏၊ ညီ ဗညားဒလ ကိုလည်း စစ်သည်တစ်သောင်းကျော်နှင့် သံလျင်မြို့ ကို ကျုံး မြောင်း မြို့ပြ, ပစ္စင် ရင်လျှောက် ဆင်ခလုတ် မြင်းခလုတ် ခိုင်ခန့်လုံခြုံအောင် ပြင်ဆင်၍ နေစေ၏။ | M85: When the King of Hanthawaddy heard that they had encountered a great battle in Prome and that everything the Mon had said was completely ruined, he thought, 'The Burmese King will surely march as far as our capital; six garrisons at the Thanlyin outpost are not enough,' and he ordered the Zay-Nge Bo, Kalar Bo, Tot-Ta-Lot Bo, and The-Ne-Set to reinforce them with over two hundred large war boats, established two large garrisons on both sides of the Panhlaing creek, and had them fully prepare water-traps to defend it; he also had his younger brother, Banya Dala, prepare the city of Thanlyin with moats, ditches, city walls, fortifications, breastworks, elephant-traps, and horse-traps to be strong and secure, and stay there.
A86: First 5% | B86: vol1 | C86: 132 | D86: vol1_s001034 | E86: vol1_s001034_t04_ff4f571497fe | F86: Banya Dala | G86: FORTIFIED_CITY | H86: Thanlyin | I86: supported | J86: Supported by the Burmese sentence and allowed narrative context; grouping and contextually inferred participants accepted. | L86: ဟံသာဝတီဘုရင်လည်း ပြည်မြို့မှာ စစ်ကြီးတွေ့ကြ၍ မွန်ဆိုသမျှ အကုန်ပျက်ကြောင်းကို ကြားလျှင် မြန်မာမင်းကား ငါတို့မြို့ ရင်းတိုင်အောင် ချီလာချိမ့်မည်၊ သံလျင်ကင်းဝတွင် ခြောက်တပ်နှင့်သာ မလုံလေသေးဟု ဈေးငယ်ဗိုလ်၊ ကုလားဗိုလ်၊ တုတ်တလုပ်ဗိုလ်၊ သေနစက်တို့ကို တိုက်လှေကြီး နှစ်ရာကျော်နှင့် ထပ်ဖြည့်ချီစေ၍ ပန်းလှိုင်ဝ ချောင်းနှစ်ဘက်တွင် တပ်ကြီးနှစ်တပ် တည်ပြီးလျှင် ရေခလုတ် အပြည့်စီဆင်၍ ခံစေ၏၊ ညီ ဗညားဒလ ကိုလည်း စစ်သည်တစ်သောင်းကျော်နှင့် သံလျင်မြို့ ကို ကျုံး မြောင်း မြို့ပြ, ပစ္စင် ရင်လျှောက် ဆင်ခလုတ် မြင်းခလုတ် ခိုင်ခန့်လုံခြုံအောင် ပြင်ဆင်၍ နေစေ၏။ | M86: When the King of Hanthawaddy heard that they had encountered a great battle in Prome and that everything the Mon had said was completely ruined, he thought, 'The Burmese King will surely march as far as our capital; six garrisons at the Thanlyin outpost are not enough,' and he ordered the Zay-Nge Bo, Kalar Bo, Tot-Ta-Lot Bo, and The-Ne-Set to reinforce them with over two hundred large war boats, established two large garrisons on both sides of the Panhlaing creek, and had them fully prepare water-traps to defend it; he also had his younger brother, Banya Dala, prepare the city of Thanlyin with moats, ditches, city walls, fortifications, breastworks, elephant-traps, and horse-traps to be strong and secure, and stay there.
A87: First 5% | B87: vol1 | C87: 132 | D87: vol1_s001035 | E87: vol1_s001035_t01_8d5407ed282a | F87: Mon naval force | G87: ESTABLISHED_OUTPOST | H87: Zayon | I87: supported | J87: Supported by the Burmese sentence and allowed narrative context; grouping and contextually inferred participants accepted. | L87: ယင်းသို့မှ ရေတပ်ချီသည့် မွန်ဗိုလ်မှူးတို့က လှေနှစ်ရာကျော် ရှေ့လွန်၍ ဇရွံကင်းတွင် အစောင့်အနေ ထားလာ၏။ | M87: Following this, the Mon commanders leading the naval force advanced more than two hundred boats ahead and placed guards at the Zayon outpost.
A88: First 5% | B88: vol1 | C88: 132 | D88: vol1_s001036 | E88: vol1_s001036_t01_5aee7bece095 | F88: Alaungmintaya | G88: APPOINTED_COMMANDER | H88: Ne Myo Shwe Taung | I88: supported | J88: Supported by the Burmese sentence and allowed narrative context; grouping and contextually inferred participants accepted. | L88: ထိုအကြောင်းကို ဘဝရှင်အလောင်းမင်းတရားကြီးဘုရား ကြားတော်မူလျှင် ကျွန်တော်ရင်း နေမျိုးရွှေတောင်ကို ဗိုလ်မှူးခန့်၍ ဟင်းသာတ ကျောင်းဆိပ်တွင် ရှိနှင့်သည့် လှေတပ် ခုနစ်ဆယ့်ငါးစင်းနှင့် တိုက်စေလျှင် မွန်တို့လှေ တပ် ပျက်လေ၍ အပြင်း ဆုတ်ပြေးလေ၏၊ ထိုတပ်တွင် လှေနီ တစ်စင်း၊ ဝန်လှေ ငါးစင်း၊ အမြောက် တစ်ဆယ်၊ သေနတ် နှစ်ဆယ်၊ သုံ့လူ တစ်ရာကျော် ရလိုက်၏။ | M88: When the Lord of Life, the Great Alaungmintaya, heard of this, he appointed his loyal servant Ne Myo Shwe Taung as commander and ordered him to attack with the seventy-five boats already at the Hinthada monastery landing; the Mon boat force was destroyed and retreated rapidly, and in that force, one red boat, five supply boats, ten cannons, twenty muskets, and over one hundred prisoners were captured.
A89: First 5% | B89: vol1 | C89: 132 | D89: vol1_s001036 | E89: vol1_s001036_t02_22fd01c65862 | F89: Ne Myo Shwe Taung | G89: CAPTURED_RESOURCES | H89: Mon naval force | I89: supported | J89: Supported by the Burmese sentence and allowed narrative context; grouping and contextually inferred participants accepted. | L89: ထိုအကြောင်းကို ဘဝရှင်အလောင်းမင်းတရားကြီးဘုရား ကြားတော်မူလျှင် ကျွန်တော်ရင်း နေမျိုးရွှေတောင်ကို ဗိုလ်မှူးခန့်၍ ဟင်းသာတ ကျောင်းဆိပ်တွင် ရှိနှင့်သည့် လှေတပ် ခုနစ်ဆယ့်ငါးစင်းနှင့် တိုက်စေလျှင် မွန်တို့လှေ တပ် ပျက်လေ၍ အပြင်း ဆုတ်ပြေးလေ၏၊ ထိုတပ်တွင် လှေနီ တစ်စင်း၊ ဝန်လှေ ငါးစင်း၊ အမြောက် တစ်ဆယ်၊ သေနတ် နှစ်ဆယ်၊ သုံ့လူ တစ်ရာကျော် ရလိုက်၏။ | M89: When the Lord of Life, the Great Alaungmintaya, heard of this, he appointed his loyal servant Ne Myo Shwe Taung as commander and ordered him to attack with the seventy-five boats already at the Hinthada monastery landing; the Mon boat force was destroyed and retreated rapidly, and in that force, one red boat, five supply boats, ten cannons, twenty muskets, and over one hundred prisoners were captured.
A90: First 5% | B90: vol1 | C90: 132 | D90: vol1_s001036 | E90: vol1_s001036_t03_cd37c644c65c | F90: Ne Myo Shwe Taung | G90: CAPTURED_PRISONERS | H90: 100 prisoners | I90: supported | J90: Supported by the Burmese sentence and allowed narrative context; grouping and contextually inferred participants accepted. | L90: ထိုအကြောင်းကို ဘဝရှင်အလောင်းမင်းတရားကြီးဘုရား ကြားတော်မူလျှင် ကျွန်တော်ရင်း နေမျိုးရွှေတောင်ကို ဗိုလ်မှူးခန့်၍ ဟင်းသာတ ကျောင်းဆိပ်တွင် ရှိနှင့်သည့် လှေတပ် ခုနစ်ဆယ့်ငါးစင်းနှင့် တိုက်စေလျှင် မွန်တို့လှေ တပ် ပျက်လေ၍ အပြင်း ဆုတ်ပြေးလေ၏၊ ထိုတပ်တွင် လှေနီ တစ်စင်း၊ ဝန်လှေ ငါးစင်း၊ အမြောက် တစ်ဆယ်၊ သေနတ် နှစ်ဆယ်၊ သုံ့လူ တစ်ရာကျော် ရလိုက်၏။ | M90: When the Lord of Life, the Great Alaungmintaya, heard of this, he appointed his loyal servant Ne Myo Shwe Taung as commander and ordered him to attack with the seventy-five boats already at the Hinthada monastery landing; the Mon boat force was destroyed and retreated rapidly, and in that force, one red boat, five supply boats, ten cannons, twenty muskets, and over one hundred prisoners were captured.
... A111: First 5% | B111: vol1 | C111: 167 | D111: vol1_s001397 | E111: vol1_s001397_t05_6050d2f5ed97 | F111: Alaungmintayagyi | G111: ASSIGNED_COMMANDER_TO_NAVAL_UNIT | H111: Turinthurein | I111: supported | J111: Supported by the Burmese sentence and allowed narrative context; grouping and contextually inferred participants accepted. | L111: ဘဝရှင် အလောင်းမင်းတရားကြီးဘုရားလည်း မွန်မင်းသမက် စောဗြ ပိုင်, ကမာပီတွင် တပ်ခိုင်တည်၍ ရေတပ်, ကြည်းတပ် အခိုင်နေကြောင်းကို ကြားတော်မူလျှင် ရွှေတောင်ရာဇာ တိုက်လှေကြီး ငါးဆယ်ကျော်နှင့်လက်ဝဲ ကြောင်း၊ ဒေဝဒိဗ္ဗ တိုက်လှေကြီး ငါးဆယ်ကျော်နှင့် လက်ယာကြောင်း၊ တုရင်သူရိန် တိုက်လှေကြီး ငါးဆယ်ကျော်, သမ္ဗန် တစ်ဆယ်ကျော်နှင့် အလယ်ကြောင်း၊ တုရင်သူရိန် လှေတပ်တွင် ဗညားဒလ ခံသော ဒေါဖွယ်ယစက်ကို ထည့်တော်မူ၍ လိုက်ရ၏။ | M111: When the Lord of Life, Alaungmintayagyi, heard that the Mon son-in-law Saw Bya had established a fortified camp at Kamapi and was holding it firmly with naval and land forces, he ordered Shwetaung Raza with over fifty large war boats to take the left route, Dewadibba with over fifty large war boats to take the right route, and Turinthurein with over fifty large war boats and over ten sampans to take the center route; he also had the 'Dau-phwai-ya-set' [a type of weapon or device] commanded by Banyadala placed in Turinthurein's boat fleet to follow.
A112: First 5% | B112: vol1 | C112: 167 | D112: vol1_s001397 | E112: vol1_s001397_t06_7b08dfb4863e | F112: Alaungmintayagyi | G112: DEPLOYED_SPECIALIZED_WEAPON_UNDER | H112: Banyadala | I112: hard | J112: The Burmese attaches the person Daw Phwe Ya Set, who bears the title Binnya Dala, to Turinthurin’s fleet. No specialized weapon is stated. The triple invents a weapon and makes Binnya Dala its supervising officer. | K112: Alaungmintayagyi | ATTACHED_TO_TURINTHURIN_FLEET | Daw Phwe Ya Set (Binnya Dala) | L112: ဘဝရှင် အလောင်းမင်းတရားကြီးဘုရားလည်း မွန်မင်းသမက် စောဗြ ပိုင်, ကမာပီတွင် တပ်ခိုင်တည်၍ ရေတပ်, ကြည်းတပ် အခိုင်နေကြောင်းကို ကြားတော်မူလျှင် ရွှေတောင်ရာဇာ တိုက်လှေကြီး ငါးဆယ်ကျော်နှင့်လက်ဝဲ ကြောင်း၊ ဒေဝဒိဗ္ဗ တိုက်လှေကြီး ငါးဆယ်ကျော်နှင့် လက်ယာကြောင်း၊ တုရင်သူရိန် တိုက်လှေကြီး ငါးဆယ်ကျော်, သမ္ဗန် တစ်ဆယ်ကျော်နှင့် အလယ်ကြောင်း၊ တုရင်သူရိန် လှေတပ်တွင် ဗညားဒလ ခံသော ဒေါဖွယ်ယစက်ကို ထည့်တော်မူ၍ လိုက်ရ၏။ | M112: When the Lord of Life, Alaungmintayagyi, heard that the Mon son-in-law Saw Bya had established a fortified camp at Kamapi and was holding it firmly with naval and land forces, he ordered Shwetaung Raza with over fifty large war boats to take the left route, Dewadibba with over fifty large war boats to take the right route, and Turinthurein with over fifty large war boats and over ten sampans to take the center route; he also had the 'Dau-phwai-ya-set' [a type of weapon or device] commanded by Banyadala placed in Turinthurein's boat fleet to follow.
A113: First 5% | B113: vol1 | C113: 167 | D113: vol1_s001398 | E113: vol1_s001398_t01_1a8c1e2b6fb9 | F113: Royal naval force | G113: COMPRISED_MILITARY_PERSONNEL | H113: 6000 soldiers | I113: supported | J113: Supported by the Burmese sentence and allowed narrative context; grouping and contextually inferred participants accepted. | L113: သည်လှေတပ် သုံးတပ်၊ စစ်သည်သူရဲ ခြောက်ထောင်ကျော်နှင့် ရေကြောင်းချီရ၏။ | M113: They set out by water with these three boat fleets and over six thousand soldiers.
A114: First 5% | B114: vol1 | C114: 167 | D114: vol1_s001399 | E114: vol1_s001399_t01_c5b5fa8859f4 | F114: Alaungmintayagyi | G114: APPOINTED_AS_COMMANDER | H114: Minhtin Nawrahta | I114: supported | J114: Supported by the Burmese sentence and allowed narrative context; grouping and contextually inferred participants accepted. | L114: မင်းရွာဗိုလ် ဘယဂါမဏိ တစ်တပ်, လက်ဝဲကြံသိုင်း တစ်တပ်, မင်းလှသီရိ တစ်တပ်, သိဒ္ဓိသူရိန် တစ်တပ်, ကျော်ထင်ရာဇာ တစ်တပ်, ယောစော်ဘွားတစ်တပ်, ထီးလင်းစော်ဘွား တစ်တပ်, ပင်းဗိုလ်မှူး တစ်တပ်, သည်တပ် ပေါင်း ရှစ်တပ်တွင် မြင်းတစ်ထောင်, သေနတ်တစ်ထောင်, စစ်သည်သူရဲ တစ်သောင်းငါးထောင်ကို မင်းထင် နော်ရထာကို ဗိုလ်မှူး၊ ကျော်ထင်သက်တော်ရှည်ကို စစ်ကဲခန့်တော်မူ၍ ကြည်းကြောင်းချီရ၏။ | M114: He appointed Minhtin Nawrahta as commander and Kyawhtin Thettawshay as military strategist for the eight combined units—the Minywa Bo Bayagamani unit, the Left Kyansine unit, the Minhla Thiri unit, the Siddhi Thurein unit, the Kyawhtin Raza unit, the Yaw Sawbwa unit, the Htilin Sawbwa unit, and the Pin Bo Hmu unit—comprising one thousand cavalry, one thousand musketeers, and fifteen thousand soldiers, and they set out by land.
A115: First 5% | B115: vol1 | C115: 167 | D115: vol1_s001399 | E115: vol1_s001399_t02_2f27a4d9f19b | F115: Alaungmintayagyi | G115: APPOINTED_AS_STRATEGIST | H115: Kyawhtin Thettawshay | I115: supported | J115: Supported by the Burmese sentence and allowed narrative context; grouping and contextually inferred participants accepted. | L115: မင်းရွာဗိုလ် ဘယဂါမဏိ တစ်တပ်, လက်ဝဲကြံသိုင်း တစ်တပ်, မင်းလှသီရိ တစ်တပ်, သိဒ္ဓိသူရိန် တစ်တပ်, ကျော်ထင်ရာဇာ တစ်တပ်, ယောစော်ဘွားတစ်တပ်, ထီးလင်းစော်ဘွား တစ်တပ်, ပင်းဗိုလ်မှူး တစ်တပ်, သည်တပ် ပေါင်း ရှစ်တပ်တွင် မြင်းတစ်ထောင်, သေနတ်တစ်ထောင်, စစ်သည်သူရဲ တစ်သောင်းငါးထောင်ကို မင်းထင် နော်ရထာကို ဗိုလ်မှူး၊ ကျော်ထင်သက်တော်ရှည်ကို စစ်ကဲခန့်တော်မူ၍ ကြည်းကြောင်းချီရ၏။ | M115: He appointed Minhtin Nawrahta as commander and Kyawhtin Thettawshay as military strategist for the eight combined units—the Minywa Bo Bayagamani unit, the Left Kyansine unit, the Minhla Thiri unit, the Siddhi Thurein unit, the Kyawhtin Raza unit, the Yaw Sawbwa unit, the Htilin Sawbwa unit, and the Pin Bo Hmu unit—comprising one thousand cavalry, one thousand musketeers, and fifteen thousand soldiers, and they set out by land.
A116: First 5% | B116: vol1 | C116: 167 | D116: vol1_s001399 | E116: vol1_s001399_t03_6690ed245107 | F116: Royal land force | G116: COMPRISED_MILITARY_RESOURCES | H116: 1000 cavalry, 1000 musketeers, 15000 soldiers | I116: supported | J116: Supported by the Burmese sentence and allowed narrative context; grouping and contextually inferred participants accepted. | L116: မင်းရွာဗိုလ် ဘယဂါမဏိ တစ်တပ်, လက်ဝဲကြံသိုင်း တစ်တပ်, မင်းလှသီရိ တစ်တပ်, သိဒ္ဓိသူရိန် တစ်တပ်, ကျော်ထင်ရာဇာ တစ်တပ်, ယောစော်ဘွားတစ်တပ်, ထီးလင်းစော်ဘွား တစ်တပ်, ပင်းဗိုလ်မှူး တစ်တပ်, သည်တပ် ပေါင်း ရှစ်တပ်တွင် မြင်းတစ်ထောင်, သေနတ်တစ်ထောင်, စစ်သည်သူရဲ တစ်သောင်းငါးထောင်ကို မင်းထင် နော်ရထာကို ဗိုလ်မှူး၊ ကျော်ထင်သက်တော်ရှည်ကို စစ်ကဲခန့်တော်မူ၍ ကြည်းကြောင်းချီရ၏။ | M116: He appointed Minhtin Nawrahta as commander and Kyawhtin Thettawshay as military strategist for the eight combined units—the Minywa Bo Bayagamani unit, the Left Kyansine unit, the Minhla Thiri unit, the Siddhi Thurein unit, the Kyawhtin Raza unit, the Yaw Sawbwa unit, the Htilin Sawbwa unit, and the Pin Bo Hmu unit—comprising one thousand cavalry, one thousand musketeers, and fifteen thousand soldiers, and they set out by land.
A117: First 5% | B117: vol1 | C117: 167 | D117: vol1_s001400 | E117: vol1_s001400_t01_2707a29370ff | F117: Royal rear guard | G117: COMPRISED_MILITARY_RESOURCES | H117: 600 cavalry, 500 musketeers, 2000 soldiers | I117: supported | J117: Supported by the Burmese sentence and allowed narrative context; grouping and contextually inferred participants accepted. | L117: မင်းကျော်ရဲထွတ် တစ်တပ်, လက်ယာပျံချီ တစ်တပ်, ကျော်ထင်ရွှေတောင် တစ်တပ်, သီရိကျော်ထင် တစ်တပ်, ဗလသီရိ တစ်တပ်, ဗလကျော်သူ တစ်တပ်, သည်ခြောက်တပ်မှာ မြင်းခြောက်ရာကျော်, သေနတ်ငါးရာ, စစ်သည်သူရဲ နှစ်ထောင်ကျော်လည်း ကြည်းကြောင်း နောက်ထောက် ကျောခံ ချီရ၏။ | M117: The six units—the Min Kyaw Ye Htut unit, the Right Pyan Chi unit, the Kyawhtin Shwetaung unit, the Thiri Kyawhtin unit, the Bala Thiri unit, and the Bala Kyawthu unit—comprising over six hundred cavalry, five hundred musketeers, and over two thousand soldiers, also set out by land as a rear guard.
A118: First 5% | B118: vol1 | C118: 167 | D118: vol1_s001401 | E118: vol1_s001401_t01_ed67d5ed1d38 | F118: Alaungmintayagyi | G118: ORGANIZED_MILITARY_CAMPAIGN_FROM | H118: Yangon | I118: supported | J118: Supported by the Burmese sentence and allowed narrative context; grouping and contextually inferred participants accepted. | L118: ယင်းသို့ ရေကြောင်း, ကြည်းကြောင်း ခန့်ရန်စည်းကြပ်တော်မူပြီးလျှင် သက္ကရာဇ် (၁၁၁၈) တစ်ထောင့်တစ်ရာ တစ်ဆယ့်ရှစ်ခု သီတင်းကျွတ်လဆန်း ငါးရက် နေ့ ရန်ကုန်မြို့ တော်က ချီထွက်စေ၏။ | M118: Having thus organized and commanded the naval and land forces, he had them set out from the royal city of Yangon on the fifth day of the waxing moon of Thadingyut in the year 1118.
A119: First 5% | B119: vol1 | C119: 167 | D119: vol1_s001402 | E119: vol1_s001402_t01_1094b434c145 | F119: Royal naval force | G119: ENGAGED_IN_COMBAT_WITH | H119: Mattara Bo Pal Kyaw | I119: supported | J119: Supported by the Burmese sentence and allowed narrative context; grouping and contextually inferred participants accepted. | L119: ရေကြောင်း ချီလေသည့် ရွှေတောင်ရာဇာ, ဒေဝဒိဗ္ဗ, တုရင်သူရိန်, ဗညားဒလတို့နှင့် လှေတပ် တစ်ရာကျော်သားတို့ ပိုင်ကြုံဝအောက်တွင် မတ္တရာ ဗိုလ်ပယ်ကျော် လှေတပ်နှင့် နေသည်ကို တွေ့ လေလျှင် ချဉ်း၍ တိုက်သည်။ | M119: When the naval forces—Shwetaung Raza, Dewadibba, Turinthurein, and Banyadala—and the fleet of over one hundred boats encountered the Mattara Bo Pal Kyaw's boat fleet stationed below Paingkyonwa, they approached and attacked.
A120: First 5% | B120: vol1 | C120: 167 | D120: vol1_s001403 | E120: vol1_s001403_t01_a2a0499a0a0a | F120: Mon forces | G120: RESISTED_ROYAL_FORCES_WITH | H120: firearms and melee weapons | I120: supported | J120: Supported by the Burmese sentence and allowed narrative context; grouping and contextually inferred participants accepted. | L120: မွန်တို့ကလည်း ဆီးကြို၍ ပစ်ခတ်ထိုးခုတ်နှင့်သည်။ | M120: The Mons also met them, firing and thrusting with weapons.
A121: First 5% | B121: vol1 | C121: 167 | D121: vol1_s001404 | E121: vol1_s001404_t01_4f63d269e4f2 | F121: Royal soldiers | G121: EXECUTED_BOARDING_TACTIC_AGAINST | H121: Mon boats | I121: supported | J121: Supported by the Burmese sentence and allowed narrative context; grouping and contextually inferred participants accepted. | L121: ရဲမက်တော်တို့လည်း မွန်တို့က ပစ်ခတ်ထိုးခုတ်သည်ကို မကြောက်မရွံ့ အထိအပါး အရှအနခံ၍ မွန်တို့လှေကို ယှဉ်၍ ချင်းနင်း ထိုးခုတ်သည်။ | M121: The royal soldiers, without fear of the Mons' firing and thrusting, and disregarding their own wounds and injuries, drew alongside the Mon boats and boarded them to thrust and strike.
A122: First 5% | B122: vol1 | C122: 167 | D122: vol1_s001405 | E122: vol1_s001405_t01_5bc3820236f3 | F122: Mon forces | G122: SUFFERED_CASUALTIES_AND | H122: fled to shore | I122: soft | J122: The statement is true, but the triple splits a compound clause after a dangling “AND”: the object is the verb phrase “fled to shore” rather than a coherent argument of the predicate. | K122: Mon forces | FLED_TO | shore after heavy casualties | L122: မနည်းကြာလျှင် မွန်တို့ အထိအပါး များလှသည်နှင့် လှေက ကုန်းသို့ချည်း တက်ပြေးကြလေ၏။ | M122: Before long, because the Mons had suffered many casualties, they fled from their boats toward the shore.
A123: First 5% | B123: vol1 | C123: 167 | D123: vol1_s001406 | E123: vol1_s001406_t01_55dda08569d2 | F123: Mattara Bo Pal Kyaw | G123: REORGANIZED_FORCES_WITH | H123: rear boat fleet | I123: supported | J123: Supported by the Burmese sentence and allowed narrative context; grouping and contextually inferred participants accepted. | L123: မတ္တရာဗိုလ်ပယ်ကျော်လည်း မစည်းမကြပ်နိုင်လေလျှင် ရုံးမိသမျှ လူတို့နှင့် နောက်လှေတပ်သို့ ပေါင်း၍ ခံပြန်၏။ | M123: When Mattara Bo Pal Kyaw could not maintain order, he gathered the men he could and joined the rear boat fleet to resist again.
A124: First 5% | B124: vol1 | C124: 167 | D124: vol1_s001407 | E124: vol1_s001407_t01_3f983fb9106e | F124: Mon forces | G124: DEPLOYED_DEFENSIVE_RAFT_FORTIFICATION_WITH | H124: heavy artillery | I124: supported | J124: Supported by the Burmese sentence and allowed narrative context; grouping and contextually inferred participants accepted. | L124: ရဲမက်တော်တို့လည်း မတ္တရာဗိုလ်ပယ်ကျော်နှင့် တိုက်လှေကြီးသုံးရာကျော်ကို နိုင်လိုက်လျှင် အရပ်အဆိုင်းမရှိ လိုက်ထပ်သည်တွင် မွန်တို့ မြစ်တစ်ဘက်နှင့်တစ်ဘက်သို့ ခတ်အောင် အထပ်ထပ် စီရင်၍ထားသော နှစ်စင်းတွဲ, သုံးစင်းတွဲ ဖောင်တပ်ပစ္စင်က အမြောက်ကြီးနှင့် ဆီးခံပစ်လွှတ်သောကြောင့် လှေတက်အများ နစ်ချေ၏။ | M124: When the royal soldiers defeated Mattara Bo Pal Kyaw and his over three hundred large war boats, they pursued them without pause; however, because the Mons fired with large cannons from a raft-fortification of double and triple-linked rafts that had been repeatedly arranged to span from one side of the river to the other, many of the royal boats sank.
A125: First 5% | B125: vol1 | C125: 167 | D125: vol1_s001407 | E125: vol1_s001407_t02_43cbee640a6f | F125: Mon artillery | G125: DAMAGED_ROYAL_FLEET_BY | H125: sinking boats | I125: supported | J125: Supported by the Burmese sentence and allowed narrative context; grouping and contextually inferred participants accepted. | L125: ရဲမက်တော်တို့လည်း မတ္တရာဗိုလ်ပယ်ကျော်နှင့် တိုက်လှေကြီးသုံးရာကျော်ကို နိုင်လိုက်လျှင် အရပ်အဆိုင်းမရှိ လိုက်ထပ်သည်တွင် မွန်တို့ မြစ်တစ်ဘက်နှင့်တစ်ဘက်သို့ ခတ်အောင် အထပ်ထပ် စီရင်၍ထားသော နှစ်စင်းတွဲ, သုံးစင်းတွဲ ဖောင်တပ်ပစ္စင်က အမြောက်ကြီးနှင့် ဆီးခံပစ်လွှတ်သောကြောင့် လှေတက်အများ နစ်ချေ၏။ | M125: When the royal soldiers defeated Mattara Bo Pal Kyaw and his over three hundred large war boats, they pursued them without pause; however, because the Mons fired with large cannons from a raft-fortification of double and triple-linked rafts that had been repeatedly arranged to span from one side of the river to the other, many of the royal boats sank.
A126: First 5% | B126: vol1 | C126: 167 | D126: vol1_s001408 | E126: vol1_s001408_t01_c0a86ee11d2d | F126: Royal soldiers | G126: BREACHED_DEFENSES_OF | H126: Mon raft-fortification | I126: supported | J126: Supported by the Burmese sentence and allowed narrative context; grouping and contextually inferred participants accepted. | L126: ရဲမက်တော် တို့လည်း ထိခိုက် ဆုံးပါးသည်ကို လေးစားမမူဘဲ ချွံချွံဝင်သည်၊ မွန်တို့ ဖောင်တပ်ကို ကပ်မိလေ၍ ဖောင်ထက်သို့ ခုန်တက်ကာ တွေ့ရာမြင်တိုင်း လိုက်လံထိုးခုတ်သည်၊ ရဲမက်တော်အလုံး ဖောင်ထက်သို့ချည်း တက်မိလျှင် မွန်တို့ မရပ်မခံနိုင် ခုန်ဆင်း၍ ကြည်းသို့ချည်း တက်ပြေးကြလေ၏။ | M126: The royal soldiers, disregarding their own injuries and losses, charged forward bravely; they drew close to the Mon raft-fortification, leaped onto the rafts, and pursued and struck at everything they saw, and once the entire royal force had boarded the rafts, the Mons could not stand their ground, so they jumped off and fled toward the shore.
A127: First 5% | B127: vol1 | C127: 167 | D127: vol1_s001408 | E127: vol1_s001408_t02_39a253d64fd2 | F127: Mon forces | G127: ABANDONED_DEFENSIVE_POSITION_DUE_TO | H127: royal boarding assault | I127: supported | J127: Supported by the Burmese sentence and allowed narrative context; grouping and contextually inferred participants accepted. | L127: ရဲမက်တော် တို့လည်း ထိခိုက် ဆုံးပါးသည်ကို လေးစားမမူဘဲ ချွံချွံဝင်သည်၊ မွန်တို့ ဖောင်တပ်ကို ကပ်မိလေ၍ ဖောင်ထက်သို့ ခုန်တက်ကာ တွေ့ရာမြင်တိုင်း လိုက်လံထိုးခုတ်သည်၊ ရဲမက်တော်အလုံး ဖောင်ထက်သို့ချည်း တက်မိလျှင် မွန်တို့ မရပ်မခံနိုင် ခုန်ဆင်း၍ ကြည်းသို့ချည်း တက်ပြေးကြလေ၏။ | M127: The royal soldiers, disregarding their own injuries and losses, charged forward bravely; they drew close to the Mon raft-fortification, leaped onto the rafts, and pursued and struck at everything they saw, and once the entire royal force had boarded the rafts, the Mons could not stand their ground, so they jumped off and fled toward the shore.
A128: First 5% | B128: vol1 | C128: 167 | D128: vol1_s001409 | E128: vol1_s001409_t01_15de2b604191 | F128: Mattara Bo Pal Kyaw | G128: RETREATED_FROM | H128: royal naval forces | I128: supported | J128: Supported by the Burmese sentence and allowed narrative context; grouping and contextually inferred participants accepted. | L128: မတ္တရာဗိုလ်ပယ်ကျော်လည်း မနှိပ်မကွပ်နိုင်၊ ရုံးမိသမျှ တိုက်လှေများနှင့် အပြင်းဆုတ်ခွာလေသည်။ | M128: Mattara Bo Pal Kyaw could not suppress them and retreated rapidly with the war boats he could gather.
A129: First 5% | B129: vol1 | C129: 167 | D129: vol1_s001410 | E129: vol1_s001410_t01_d058834d0608 | F129: Royal forces | G129: SEIZED_ENEMY_RESOURCES | H129: cannons, muskets, prisoners, boats, men | I129: supported | J129: Supported by the Burmese sentence and allowed narrative context; grouping and contextually inferred participants accepted. | L129: အမြောက်, သေနတ်, သုံ့ပန်း, လှေ, လူအများ ရလိုက်၏။ | M129: They captured many cannons, muskets, prisoners, boats, and men.
A130: First 5% | B130: vol1 | C130: 167 | D130: vol1_s001411 | E130: vol1_s001411_t01_009f6b449ed9 | F130: Minhtin Nawrahta | G130: ESTABLISHED_CAMP_AT | H130: Kamapi | I130: supported | J130: Supported by the Burmese sentence and allowed narrative context; grouping and contextually inferred participants accepted. | L130: ကြည်းကြောင်းချီလေသည့် ဗိုလ်မှူးမင်းထင်နော်ရထာတို့ ရှစ်တပ်လည်း ကမာပီသို့ ရောက်၍ တပ်ချရပ်နေ သည့်အခိုက် နောက်ချီလာသည့် မင်းကျော်ရဲထွတ်, ကျော်ထင်ရွှေတောင်တို့ ခြောက်တပ်က အောင်တံခွန်များ ကိုလည်း မြင်သည်နှင့် ရေကြောင်းက အမြောက်, စိန်ပြောင်းသံကိုလည်း ကြား၍ ဆင်မြင်းကပြီးလျှင် မင်းထင် နော်ရထာ, ကျော်ထင်သက်တော်ရှည်တို့ စောဗြ နေသည့် ကမာပီတပ်ကြီးသို့ ချဉ်းသည်။ | M130: While the eight units led by Commander Minhtin Nawrahta, who had marched by land, had reached Kamapi and were stationed in camp, the six units led by Min Kyaw Ye Htut and Kyawhtin Shwetaung, who were marching behind, saw the victory banners and heard the sound of cannons and mortars from the river; they then mounted their elephants and horses and approached the large Kamapi camp where Saw Bya was staying.
A131: First 5% | B131: vol1 | C131: 167 | D131: vol1_s001411 | E131: vol1_s001411_t02_792b812859e8 | F131: Min Kyaw Ye Htut and Kyawhtin Shwetaung | G131: COORDINATED_LAND_ASSAULT_WITH | H131: naval artillery signals | I131: supported | J131: Supported by the Burmese sentence and allowed narrative context; grouping and contextually inferred participants accepted. | L131: ကြည်းကြောင်းချီလေသည့် ဗိုလ်မှူးမင်းထင်နော်ရထာတို့ ရှစ်တပ်လည်း ကမာပီသို့ ရောက်၍ တပ်ချရပ်နေ သည့်အခိုက် နောက်ချီလာသည့် မင်းကျော်ရဲထွတ်, ကျော်ထင်ရွှေတောင်တို့ ခြောက်တပ်က အောင်တံခွန်များ ကိုလည်း မြင်သည်နှင့် ရေကြောင်းက အမြောက်, စိန်ပြောင်းသံကိုလည်း ကြား၍ ဆင်မြင်းကပြီးလျှင် မင်းထင် နော်ရထာ, ကျော်ထင်သက်တော်ရှည်တို့ စောဗြ နေသည့် ကမာပီတပ်ကြီးသို့ ချဉ်းသည်။ | M131: While the eight units led by Commander Minhtin Nawrahta, who had marched by land, had reached Kamapi and were stationed in camp, the six units led by Min Kyaw Ye Htut and Kyawhtin Shwetaung, who were marching behind, saw the victory banners and heard the sound of cannons and mortars from the river; they then mounted their elephants and horses and approached the large Kamapi camp where Saw Bya was staying.
A132: First 5% | B132: vol1 | C132: 167 | D132: vol1_s001412 | E132: vol1_s001412_t01_67c783a17ef0 | F132: Mon_forces | G132: UTILIZED_DEFENSIVE_TECHNOLOGY | H132: cannons_mortars_muskets | I132: supported | J132: Supported by the Burmese sentence and allowed narrative context; grouping and contextually inferred participants accepted. | L132: တပ်ပေါ်က အမြောက်, စိန်ပြောင်း သေနတ် ထူထပ်လှသောကြောင့် မကပ်တည့်နိုင်၊ အမ်း၍ရှိနေစဉ် မင်းထင်နော်ရထာတို့ ရှစ်တပ် မွန်တို့တပ်သို့ ချဉ်းသည်ကို နောက်ချီလာသည့် မင်းကျော်ရဲထွတ်, ကျော်ထင်ရွှေတောင်တို့ ခြောက်တပ်က မြင်လေလျှင် မင်းကျော်ရဲထွတ်, ကျော်ထင်ရွှေတောင်တို့လည်း ဆင်မြင်း မချ၊ တစ်ဟုန်တည်း စောဗြတပ်ကို ချဉ်းကြသည်။ | M132: Because the cannons, mortars, and muskets from the camp were so dense, they could not approach; while they were hesitating, the six units led by Min Kyaw Ye Htut and Kyawhtin Shwetaung, seeing that the eight units led by Minhtin Nawrahta were approaching the Mon camp, did not wait to mount their elephants and horses but charged toward Saw Bya's camp in a single rush.
A133: First 5% | B133: vol1 | C133: 167 | D133: vol1_s001412 | E133: vol1_s001412_t02_44d01b648b8c | F133: Min_Kyaw_Ye_Htut_and_Kyawhtin_Shwetaung | G133: COMMANDED_MILITARY_UNITS | H133: six_units | I133: supported | J133: Supported by the Burmese sentence and allowed narrative context; grouping and contextually inferred participants accepted. | L133: တပ်ပေါ်က အမြောက်, စိန်ပြောင်း သေနတ် ထူထပ်လှသောကြောင့် မကပ်တည့်နိုင်၊ အမ်း၍ရှိနေစဉ် မင်းထင်နော်ရထာတို့ ရှစ်တပ် မွန်တို့တပ်သို့ ချဉ်းသည်ကို နောက်ချီလာသည့် မင်းကျော်ရဲထွတ်, ကျော်ထင်ရွှေတောင်တို့ ခြောက်တပ်က မြင်လေလျှင် မင်းကျော်ရဲထွတ်, ကျော်ထင်ရွှေတောင်တို့လည်း ဆင်မြင်း မချ၊ တစ်ဟုန်တည်း စောဗြတပ်ကို ချဉ်းကြသည်။ | M133: Because the cannons, mortars, and muskets from the camp were so dense, they could not approach; while they were hesitating, the six units led by Min Kyaw Ye Htut and Kyawhtin Shwetaung, seeing that the eight units led by Minhtin Nawrahta were approaching the Mon camp, did not wait to mount their elephants and horses but charged toward Saw Bya's camp in a single rush.
A134: First 5% | B134: vol1 | C134: 167 | D134: vol1_s001412 | E134: vol1_s001412_t03_a0544e9f363c | F134: Minhtin_Nawrahta | G134: COMMANDED_MILITARY_UNITS | H134: eight_units | I134: supported | J134: Supported by the Burmese sentence and allowed narrative context; grouping and contextually inferred participants accepted. | L134: တပ်ပေါ်က အမြောက်, စိန်ပြောင်း သေနတ် ထူထပ်လှသောကြောင့် မကပ်တည့်နိုင်၊ အမ်း၍ရှိနေစဉ် မင်းထင်နော်ရထာတို့ ရှစ်တပ် မွန်တို့တပ်သို့ ချဉ်းသည်ကို နောက်ချီလာသည့် မင်းကျော်ရဲထွတ်, ကျော်ထင်ရွှေတောင်တို့ ခြောက်တပ်က မြင်လေလျှင် မင်းကျော်ရဲထွတ်, ကျော်ထင်ရွှေတောင်တို့လည်း ဆင်မြင်း မချ၊ တစ်ဟုန်တည်း စောဗြတပ်ကို ချဉ်းကြသည်။ | M134: Because the cannons, mortars, and muskets from the camp were so dense, they could not approach; while they were hesitating, the six units led by Min Kyaw Ye Htut and Kyawhtin Shwetaung, seeing that the eight units led by Minhtin Nawrahta were approaching the Mon camp, did not wait to mount their elephants and horses but charged toward Saw Bya's camp in a single rush.
... A184: First 5% | B184: vol1 | C184: 186 | D184: vol1_s001721 | E184: vol1_s001721_t02_73e6495fd253 | F184: Mon King | G184: BESTOWED_SYMBOLIC_GIFT_UPON | H184: One-Pillar Princess | I184: supported | J184: Supported by the Burmese sentence and allowed narrative context; grouping and contextually inferred participants accepted. | L184: ဆရာတော်နှင့် မင်းရာဇာတို့လည်း အမိန့်တော်ရှိသမျှ စကားမျိုးကို စေ့စုံစွာ မွန်မင်းအား ပြန်လေလျှင် မွန်မင်းလည်း ပေးတော်မူလိုက်သည့် သဇင်ပန်းတော် နှစ်ခြင်းကို မှာတော်မူလိုက်သည့် အမိန့် တော်သံကို ထောက် ၍ တစ်ခြင်းကို ရွှေမော်ဓောဘုရားမှာ တင်ရ၏၊ တစ်ခြင်းကို သမီးတော် တစ်ပင်တိုင် မင်းသမီးသို့ ပို့၍ ဆင်ရ၏။ | M184: When the Sayadaw and Min Raza fully reported all the words that had been ordered to the Mon King, the Mon King, relying on the royal command that accompanied the two baskets of Thazin flowers that had been given, had one basket offered at the Shwemawdaw Pagoda and sent the other basket to his daughter, the One-Pillar Princess, to wear.
A185: First 5% | B185: vol1 | C185: 186 | D185: vol1_s001722 | E185: vol1_s001722_t01_7370fbe88f18 | F185: Alaungpaya | G185: ORDERED_OFFICIALS_TO_MANAGE_DIPLOMATIC_PRESENTATION | H185: Banya U, Banya Arinda, Raza Aindra | I185: hard | J185: The issuing ruler here is the Mon king, the continuing subject of the preceding sentence, who orders his own ministers to arrange presentation of his daughter to Alaungmintaya. The triple incorrectly makes Alaungpaya the issuer. | K185: Mon king | ORDERED_DAUGHTER_PRESENTATION_ARRANGEMENTS | Banya U, Banya Arinda, Raza Aindra | L185: ယင်းသို့မှ သမီးတော်ကို အခါနေ့ရက် တွက်ချက်ရွေးချယ်ပြီးလျှင် အလောင်းမင်းတရားကြီးမှာ လျှောက်ထား၍ စီရင်ရန်ရှိသည်များကို ပြီးပြေအောင် စီစဉ်ဆက်သကြရမည်ဟု ယောက်ဖတော်စစ်သူကြီး ဗညားဦး, ဗညားအရိန္ဒမ, အတွင်းဝန် ရာဇအိန္ဒတို့ကို အမိန့်တော်ရှိ၍ သက္ကရာဇ် (၁၁၁၈) တစ်ထောင့်တစ်ရာ့တစ်ဆယ့် ရှစ်ခု နတ်တော် လပြည့်ကျော် တစ်ဆယ့်လေးရက် နေ့တွင် စစ်သူကြီး ဗညားဦး, ဗညားအရိန္ဒမ, အတွင်းဝန် ရာဇအိန္ဒတို့နှင့် အမတ်တစ်ဆယ့်လေး၊ ပုဏ္ဏား အဓိပတိ ဗြဟ္မာ, မူလဗြဟ္မာ, အဂ္ဂဗြဟ္မာတို့နှင့် နောက်ပါ တစ်ဆယ့်လေး၊ စန္ဒရပ် ကျော်နှင့် နောက်ပါ တစ်ဆယ့်နှစ်၊ နန်းစာရေး လွှတ်စာရေး ငကွန်းတေ, ငထော်ဦး, ငထွန်း, ကုလားပျိုတို့နှင့် အစုစုလူပေါင်း ခြောက်ဆယ်၊ ပဲကူးမြို့ တွင်းက ထွက်လာ၍ လက်ယာထိမ်းမှတ်တပ်သို့ ရောက်လာ၏။ | M185: Only then, after calculating and selecting the auspicious day and date for the daughter, he ordered his brother-in-law, the General Banya U, Banya Arinda, and the Interior Minister Raza Aindra, saying that they must arrange and present the matters to be carried out by reporting to Alaungmintaya Gyi, and on the 14th day of the waning moon of Natdaw, 1118, the General Banya U, Banya Arinda, and Interior Minister Raza Aindra, along with fourteen ministers, the Brahmin Adipati Brahma, Mula Brahma, and Agga Brahma with fourteen followers, Sandaryat Kyaw with twelve followers, and the palace scribes and royal secretaries Nga Kun Te, Nga Htaw U, Nga Htun, and Kular Pyo, totaling sixty people, left the city of Pegu and arrived at the right-flank guard camp.
A186: First 5% | B186: vol1 | C186: 186 | D186: vol1_s001722 | E186: vol1_s001722_t02_4dc3330cece6 | F186: Banya U, Banya Arinda, Raza Aindra | G186: LED_DIPLOMATIC_MISSION_TO | H186: Konbaung military camp | I186: supported | J186: Supported by the Burmese sentence and allowed narrative context; grouping and contextually inferred participants accepted. | L186: ယင်းသို့မှ သမီးတော်ကို အခါနေ့ရက် တွက်ချက်ရွေးချယ်ပြီးလျှင် အလောင်းမင်းတရားကြီးမှာ လျှောက်ထား၍ စီရင်ရန်ရှိသည်များကို ပြီးပြေအောင် စီစဉ်ဆက်သကြရမည်ဟု ယောက်ဖတော်စစ်သူကြီး ဗညားဦး, ဗညားအရိန္ဒမ, အတွင်းဝန် ရာဇအိန္ဒတို့ကို အမိန့်တော်ရှိ၍ သက္ကရာဇ် (၁၁၁၈) တစ်ထောင့်တစ်ရာ့တစ်ဆယ့် ရှစ်ခု နတ်တော် လပြည့်ကျော် တစ်ဆယ့်လေးရက် နေ့တွင် စစ်သူကြီး ဗညားဦး, ဗညားအရိန္ဒမ, အတွင်းဝန် ရာဇအိန္ဒတို့နှင့် အမတ်တစ်ဆယ့်လေး၊ ပုဏ္ဏား အဓိပတိ ဗြဟ္မာ, မူလဗြဟ္မာ, အဂ္ဂဗြဟ္မာတို့နှင့် နောက်ပါ တစ်ဆယ့်လေး၊ စန္ဒရပ် ကျော်နှင့် နောက်ပါ တစ်ဆယ့်နှစ်၊ နန်းစာရေး လွှတ်စာရေး ငကွန်းတေ, ငထော်ဦး, ငထွန်း, ကုလားပျိုတို့နှင့် အစုစုလူပေါင်း ခြောက်ဆယ်၊ ပဲကူးမြို့ တွင်းက ထွက်လာ၍ လက်ယာထိမ်းမှတ်တပ်သို့ ရောက်လာ၏။ | M186: Only then, after calculating and selecting the auspicious day and date for the daughter, he ordered his brother-in-law, the General Banya U, Banya Arinda, and the Interior Minister Raza Aindra, saying that they must arrange and present the matters to be carried out by reporting to Alaungmintaya Gyi, and on the 14th day of the waning moon of Natdaw, 1118, the General Banya U, Banya Arinda, and Interior Minister Raza Aindra, along with fourteen ministers, the Brahmin Adipati Brahma, Mula Brahma, and Agga Brahma with fourteen followers, Sandaryat Kyaw with twelve followers, and the palace scribes and royal secretaries Nga Kun Te, Nga Htaw U, Nga Htun, and Kular Pyo, totaling sixty people, left the city of Pegu and arrived at the right-flank guard camp.
A187: First 5% | B187: vol1 | C187: 186 | D187: vol1_s001722 | E187: vol1_s001722_t03_d87e8aa50d49 | F187: Diplomatic mission | G187: INCLUDED_REPRESENTATIVES_OF | H187: Pegu administration and religious hierarchy | I187: supported | J187: Supported by the Burmese sentence and allowed narrative context; grouping and contextually inferred participants accepted. | L187: ယင်းသို့မှ သမီးတော်ကို အခါနေ့ရက် တွက်ချက်ရွေးချယ်ပြီးလျှင် အလောင်းမင်းတရားကြီးမှာ လျှောက်ထား၍ စီရင်ရန်ရှိသည်များကို ပြီးပြေအောင် စီစဉ်ဆက်သကြရမည်ဟု ယောက်ဖတော်စစ်သူကြီး ဗညားဦး, ဗညားအရိန္ဒမ, အတွင်းဝန် ရာဇအိန္ဒတို့ကို အမိန့်တော်ရှိ၍ သက္ကရာဇ် (၁၁၁၈) တစ်ထောင့်တစ်ရာ့တစ်ဆယ့် ရှစ်ခု နတ်တော် လပြည့်ကျော် တစ်ဆယ့်လေးရက် နေ့တွင် စစ်သူကြီး ဗညားဦး, ဗညားအရိန္ဒမ, အတွင်းဝန် ရာဇအိန္ဒတို့နှင့် အမတ်တစ်ဆယ့်လေး၊ ပုဏ္ဏား အဓိပတိ ဗြဟ္မာ, မူလဗြဟ္မာ, အဂ္ဂဗြဟ္မာတို့နှင့် နောက်ပါ တစ်ဆယ့်လေး၊ စန္ဒရပ် ကျော်နှင့် နောက်ပါ တစ်ဆယ့်နှစ်၊ နန်းစာရေး လွှတ်စာရေး ငကွန်းတေ, ငထော်ဦး, ငထွန်း, ကုလားပျိုတို့နှင့် အစုစုလူပေါင်း ခြောက်ဆယ်၊ ပဲကူးမြို့ တွင်းက ထွက်လာ၍ လက်ယာထိမ်းမှတ်တပ်သို့ ရောက်လာ၏။ | M187: Only then, after calculating and selecting the auspicious day and date for the daughter, he ordered his brother-in-law, the General Banya U, Banya Arinda, and the Interior Minister Raza Aindra, saying that they must arrange and present the matters to be carried out by reporting to Alaungmintaya Gyi, and on the 14th day of the waning moon of Natdaw, 1118, the General Banya U, Banya Arinda, and Interior Minister Raza Aindra, along with fourteen ministers, the Brahmin Adipati Brahma, Mula Brahma, and Agga Brahma with fourteen followers, Sandaryat Kyaw with twelve followers, and the palace scribes and royal secretaries Nga Kun Te, Nga Htaw U, Nga Htun, and Kular Pyo, totaling sixty people, left the city of Pegu and arrived at the right-flank guard camp.
A188: First 5% | B188: vol1 | C188: 267 | D188: vol1_s002390 | E188: vol1_s002390_t01_c3e0c682ac8d | F188: Royal musketeers | G188: EXECUTED_REBEL | H188: Minkhaung Nawrahta | I188: supported | J188: Supported by the Burmese sentence and allowed narrative context; grouping and contextually inferred participants accepted. | L188: ငချစ်ကောင်းလည်း အသက်မလွတ်ချေပြီ အမှတ်ရှိ၍ ကြောက်လန့်တကြား ကယ်ပါ, ကယ်ပါ ဟစ်အော် သည်တွင် သေနတ်လုလင်တော်တို့ ဖြဖြဝန်းရံပြီးလျှင် အထက်က နှိပ်၍ မင်းခေါင်နော်ရထာကို သေနတ်နှင့် ပစ်သည်၊ ငချစ်ကောင်းလည်း မင်းခေါင်နော်ရထာ ဦးခေါင်းကို ဖြတ်သည်၊ ယင်းတွင်မှ မင်းခေါင်နော်ရထာကို ရချေ၏။ | M188: Nga Chit Kaung also realized his life would not be spared, and being mindful of this, he cried out in fear, 'Save me, save me!' At that moment, the royal musketeers surrounded him closely, pressed down from above, and shot Minkhaung Nawrahta with a musket; Nga Chit Kaung then cut off Minkhaung Nawrahta's head, and only then was Minkhaung Nawrahta captured.
A189: First 5% | B189: vol1 | C189: 267 | D189: vol1_s002390 | E189: vol1_s002390_t02_ef315037ea02 | F189: Nga Chit Kaung | G189: BEHEADED_REBEL | H189: Minkhaung Nawrahta | I189: supported | J189: Supported by the Burmese sentence and allowed narrative context; grouping and contextually inferred participants accepted. | L189: ငချစ်ကောင်းလည်း အသက်မလွတ်ချေပြီ အမှတ်ရှိ၍ ကြောက်လန့်တကြား ကယ်ပါ, ကယ်ပါ ဟစ်အော် သည်တွင် သေနတ်လုလင်တော်တို့ ဖြဖြဝန်းရံပြီးလျှင် အထက်က နှိပ်၍ မင်းခေါင်နော်ရထာကို သေနတ်နှင့် ပစ်သည်၊ ငချစ်ကောင်းလည်း မင်းခေါင်နော်ရထာ ဦးခေါင်းကို ဖြတ်သည်၊ ယင်းတွင်မှ မင်းခေါင်နော်ရထာကို ရချေ၏။ | M189: Nga Chit Kaung also realized his life would not be spared, and being mindful of this, he cried out in fear, 'Save me, save me!' At that moment, the royal musketeers surrounded him closely, pressed down from above, and shot Minkhaung Nawrahta with a musket; Nga Chit Kaung then cut off Minkhaung Nawrahta's head, and only then was Minkhaung Nawrahta captured.
A190: First 5% | B190: vol1 | C190: 267 | D190: vol1_s002390 | E190: vol1_s002390_t03_2ffff18e8914 | F190: Royal forces | G190: CAPTURED_REBEL | H190: Minkhaung Nawrahta | I190: supported | J190: Supported by the Burmese sentence and allowed narrative context; grouping and contextually inferred participants accepted. | L190: ငချစ်ကောင်းလည်း အသက်မလွတ်ချေပြီ အမှတ်ရှိ၍ ကြောက်လန့်တကြား ကယ်ပါ, ကယ်ပါ ဟစ်အော် သည်တွင် သေနတ်လုလင်တော်တို့ ဖြဖြဝန်းရံပြီးလျှင် အထက်က နှိပ်၍ မင်းခေါင်နော်ရထာကို သေနတ်နှင့် ပစ်သည်၊ ငချစ်ကောင်းလည်း မင်းခေါင်နော်ရထာ ဦးခေါင်းကို ဖြတ်သည်၊ ယင်းတွင်မှ မင်းခေါင်နော်ရထာကို ရချေ၏။ | M190: Nga Chit Kaung also realized his life would not be spared, and being mindful of this, he cried out in fear, 'Save me, save me!' At that moment, the royal musketeers surrounded him closely, pressed down from above, and shot Minkhaung Nawrahta with a musket; Nga Chit Kaung then cut off Minkhaung Nawrahta's head, and only then was Minkhaung Nawrahta captured.
A191: First 5% | B191: vol1 | C191: 267 | D191: vol1_s002391 | E191: vol1_s002391_t01_112acb71128e | F191: Royal commanders and warriors | G191: PURSUED_AND_ARRESTED | H191: Rebel associates | I191: supported | J191: Supported by the Burmese sentence and allowed narrative context; grouping and contextually inferred participants accepted. | L191: ဗိုလ်မှူးတပ်မှူး သူရဲသူခက်တို့လည်း မင်းခေါင်နော်ရထာ အသင်းအပင်း လူတစ်စုတို့ကို လိုက်လံဖမ်း ဆီးပြီးလျှင် မင်းခေါင်နော်ရထာ ခေါင်းကို ယူ၍ ပြန်ခဲ့ကြသည်။ | M191: The commanders and warriors also pursued and arrested the group of Minkhaung Nawrahta's associates, then took Minkhaung Nawrahta's head and returned.
A192: First 5% | B192: vol1 | C192: 267 | D192: vol1_s002391 | E192: vol1_s002391_t02_401fec6a7ae8 | F192: Royal commanders and warriors | G192: SEIZED_REBEL_REMAINS | H192: Minkhaung Nawrahta's head | I192: supported | J192: Supported by the Burmese sentence and allowed narrative context; grouping and contextually inferred participants accepted. | L192: ဗိုလ်မှူးတပ်မှူး သူရဲသူခက်တို့လည်း မင်းခေါင်နော်ရထာ အသင်းအပင်း လူတစ်စုတို့ကို လိုက်လံဖမ်း ဆီးပြီးလျှင် မင်းခေါင်နော်ရထာ ခေါင်းကို ယူ၍ ပြန်ခဲ့ကြသည်။ | M192: The commanders and warriors also pursued and arrested the group of Minkhaung Nawrahta's associates, then took Minkhaung Nawrahta's head and returned.
A193: First 5% | B193: vol1 | C193: 267 | D193: vol1_s002392 | E193: vol1_s002392_t01_84f7e6700f4c | F193: King Alaungpaya | G193: REPRIMANDED_COMMANDERS_FOR | H193: Unauthorized execution of rebel | I193: hard | J193: The passage is under Alaungpaya’s successor, the Dipeyin prince (Naungdawgyi), not Alaungpaya. The contextual accession is explicit in vol1_s002339, owner page 260, following Alaungpaya’s death. This is an incorrect named-king resolution, not a fault in inferring an unstated king. | K193: Replace King Alaungpaya with the reigning Dipeyin king / Naungdawgyi; retain the stated action. | L193: ဘဝရှင် မင်းတရားကြီးဘုရားလည်း မင်းခေါင်နော်ရထာကို ရလျှင် မသေလေစေနှင့်ဟု ဗိုလ်မှူးတပ်မှူးတို့ကို မဆွကာလကပင် ငါအမိန့်တော်ရှိသည်ကို သေဆုံးရာသလောဟု နှုတ်ပြစ် တင်တော်မူသည်၊ မင်းခေါင်နော်ရထာ ခေါင်းကို ဆက်သူ ငချစ်ကောင်းကိုလည်း လမှူးရန္တ သူ ဘွဲ့ အမည်ကို တပ်တော်မူသည်၊ မင်းခေါင်နော်ရထာနှင့် ရိုးရင်းဘက် တုရင်သိပ္ပံ, တုရင်သစ်တို့မှာ အင်းဝပျက်လျှင် ထွက်ရှောင်၍ မမိမရ၊ ဖမ်းဆီးရမိသည့် ခေါင်းတည် အကြီး ပြုသူတို့ကိုမူကား ရွေးစစ်တော်မူ၍ အပြစ်အလျောက် စီရင်တော်မူသည်။ | M193: When the Lord of Life, the Great King, obtained Minkhaung Nawrahta, he reprimanded the commanders, saying, 'Did he die? I had already given orders long ago not to let him die.' He also bestowed the title of 'Lamu Ranta Thu' upon Nga Chit Kaung, who had presented Minkhaung Nawrahta's head. As for Minkhaung Nawrahta's close associates, Turin Thiphan and Turin Thit, they escaped when Inwa fell and were not captured; however, those who were arrested and had acted as ringleaders were interrogated and punished according to their crimes.
A194: First 5% | B194: vol1 | C194: 267 | D194: vol1_s002392 | E194: vol1_s002392_t02_784e67ffa6e1 | F194: Nga Chit Kaung | G194: RECEIVED_TITLE_FROM_KING | H194: Lamu Ranta Thu | I194: supported | J194: Supported by the Burmese sentence and allowed narrative context; grouping and contextually inferred participants accepted. | L194: ဘဝရှင် မင်းတရားကြီးဘုရားလည်း မင်းခေါင်နော်ရထာကို ရလျှင် မသေလေစေနှင့်ဟု ဗိုလ်မှူးတပ်မှူးတို့ကို မဆွကာလကပင် ငါအမိန့်တော်ရှိသည်ကို သေဆုံးရာသလောဟု နှုတ်ပြစ် တင်တော်မူသည်၊ မင်းခေါင်နော်ရထာ ခေါင်းကို ဆက်သူ ငချစ်ကောင်းကိုလည်း လမှူးရန္တ သူ ဘွဲ့ အမည်ကို တပ်တော်မူသည်၊ မင်းခေါင်နော်ရထာနှင့် ရိုးရင်းဘက် တုရင်သိပ္ပံ, တုရင်သစ်တို့မှာ အင်းဝပျက်လျှင် ထွက်ရှောင်၍ မမိမရ၊ ဖမ်းဆီးရမိသည့် ခေါင်းတည် အကြီး ပြုသူတို့ကိုမူကား ရွေးစစ်တော်မူ၍ အပြစ်အလျောက် စီရင်တော်မူသည်။ | M194: When the Lord of Life, the Great King, obtained Minkhaung Nawrahta, he reprimanded the commanders, saying, 'Did he die? I had already given orders long ago not to let him die.' He also bestowed the title of 'Lamu Ranta Thu' upon Nga Chit Kaung, who had presented Minkhaung Nawrahta's head. As for Minkhaung Nawrahta's close associates, Turin Thiphan and Turin Thit, they escaped when Inwa fell and were not captured; however, those who were arrested and had acted as ringleaders were interrogated and punished according to their crimes.
A195: First 5% | B195: vol1 | C195: 267 | D195: vol1_s002392 | E195: vol1_s002392_t03_d1424475afd0 | F195: King Alaungpaya | G195: PUNISHED_REBEL_RINGLEADERS | H195: Rebel ringleaders | I195: hard | J195: The passage is under Alaungpaya’s successor, the Dipeyin prince (Naungdawgyi), not Alaungpaya. The contextual accession is explicit in vol1_s002339, owner page 260, following Alaungpaya’s death. This is an incorrect named-king resolution, not a fault in inferring an unstated king. | K195: Replace King Alaungpaya with the reigning Dipeyin king / Naungdawgyi; retain the stated action. | L195: ဘဝရှင် မင်းတရားကြီးဘုရားလည်း မင်းခေါင်နော်ရထာကို ရလျှင် မသေလေစေနှင့်ဟု ဗိုလ်မှူးတပ်မှူးတို့ကို မဆွကာလကပင် ငါအမိန့်တော်ရှိသည်ကို သေဆုံးရာသလောဟု နှုတ်ပြစ် တင်တော်မူသည်၊ မင်းခေါင်နော်ရထာ ခေါင်းကို ဆက်သူ ငချစ်ကောင်းကိုလည်း လမှူးရန္တ သူ ဘွဲ့ အမည်ကို တပ်တော်မူသည်၊ မင်းခေါင်နော်ရထာနှင့် ရိုးရင်းဘက် တုရင်သိပ္ပံ, တုရင်သစ်တို့မှာ အင်းဝပျက်လျှင် ထွက်ရှောင်၍ မမိမရ၊ ဖမ်းဆီးရမိသည့် ခေါင်းတည် အကြီး ပြုသူတို့ကိုမူကား ရွေးစစ်တော်မူ၍ အပြစ်အလျောက် စီရင်တော်မူသည်။ | M195: When the Lord of Life, the Great King, obtained Minkhaung Nawrahta, he reprimanded the commanders, saying, 'Did he die? I had already given orders long ago not to let him die.' He also bestowed the title of 'Lamu Ranta Thu' upon Nga Chit Kaung, who had presented Minkhaung Nawrahta's head. As for Minkhaung Nawrahta's close associates, Turin Thiphan and Turin Thit, they escaped when Inwa fell and were not captured; however, those who were arrested and had acted as ringleaders were interrogated and punished according to their crimes.
A196: First 5% | B196: vol1 | C196: 267 | D196: vol1_s002393 | E196: vol1_s002393_t01_1e1eb7ceb5d3 | F196: King Alaungpaya | G196: RETURNED_TO_CAPITAL | H196: Ratanasingha | I196: hard | J196: The passage is under Alaungpaya’s successor, the Dipeyin prince (Naungdawgyi), not Alaungpaya. The contextual accession is explicit in vol1_s002339, owner page 260, following Alaungpaya’s death. This is an incorrect named-king resolution, not a fault in inferring an unstated king. | K196: Replace King Alaungpaya with the reigning Dipeyin king / Naungdawgyi; retain the stated action. | L196: ဘဝရှင် မင်းတရားကြီး သင်္ကြန်ခေါ်တော်မူခြင်းနှင့် ဥကင်္သ ဖွင့်တော်မူခြင်း စသည်များ ဘဝရှင် မင်းတရားကြီးဘုရားလည်း အရေးတော်ကုံလျှင် သက္ကရာဇ် (၁၁၂၂) တစ်ထောင့်တစ်ရာ့နှစ်ဆယ့်နှစ်ခု ပြာသိုလပြည့်ကျော် ဆယ်ရက်ခ ဗုဒ္ဓဟူးနေ့ ရတနာသိင်္ဃ ရွှေပြည်တော်သို့ ပြန်တော်မူ၏။ | M196: Regarding the Lord of Life, the Great King's holding of the Thingyan festival and the opening of the royal pavilion, etc., when the Lord of Life, the Great King, had finished his urgent affairs, he returned to the royal capital of Ratanasingha on Wednesday, the 10th day of the waning moon of Pyatho, 1122 Era.
A197: First 5% | B197: vol1 | C197: 267 | D197: vol1_s002394 | E197: vol1_s002394_t01_886b2fb76ee5 | F197: King Alaungpaya | G197: PERFORMED_RITUAL_OF | H197: Maha Thingyan | I197: hard | J197: The passage is under Alaungpaya’s successor, the Dipeyin prince (Naungdawgyi), not Alaungpaya. The contextual accession is explicit in vol1_s002339, owner page 260, following Alaungpaya’s death. This is an incorrect named-king resolution, not a fault in inferring an unstated king. | K197: Replace King Alaungpaya with the reigning Dipeyin king / Naungdawgyi; retain the stated action. | L197: သက္ကရာဇ် (၁၁၂၂) တစ်ထောင့်တစ်ရာ့နှစ်ဆယ့်နှစ်ခု တပေါင်းလဆန်း ခြောက်ရက်J တနင်္လာနေ့ ရွှေနန်းတော်၏ အနောက်မြောက်ယွန်း နံတော်၏ ဂဟပတိအရပ်ဖြစ်သော ထနောင်းဝန်း အရပ်တွင် မဟာသင်္ကြန် ခေါ်တော်မူပြီးလျှင် ထီးဆောင်းမင်္ဂလာ မဟာဥကင်္သ ဖွင့်တော်မူ၍ “သီရိပဝရ မဟာဓမ္မရာဇာ” ဟူသော တံဆိပ်နာမံတော်ကို ခံတော်မူ၏။ | M197: On Monday, the 6th day of the waxing moon of Tabaung, 1122 Era, in the Thanaungwun area, which is the Gahapati quarter of the northwest direction of the royal palace, he held the Great Thingyan festival, opened the royal pavilion for the coronation ceremony, and received the title 'Thiri Pawara Maha Dhamma Raja'.
A198: First 5% | B198: vol1 | C198: 267 | D198: vol1_s002394 | E198: vol1_s002394_t02_ef5fa0c4b8b7 | F198: King Alaungpaya | G198: PERFORMED_RITUAL_OF | H198: Royal consecration | I198: hard | J198: The passage is under Alaungpaya’s successor, the Dipeyin prince (Naungdawgyi), not Alaungpaya. The contextual accession is explicit in vol1_s002339, owner page 260, following Alaungpaya’s death. This is an incorrect named-king resolution, not a fault in inferring an unstated king. | K198: Replace King Alaungpaya with the reigning Dipeyin king / Naungdawgyi; retain the stated action. | L198: သက္ကရာဇ် (၁၁၂၂) တစ်ထောင့်တစ်ရာ့နှစ်ဆယ့်နှစ်ခု တပေါင်းလဆန်း ခြောက်ရက်J တနင်္လာနေ့ ရွှေနန်းတော်၏ အနောက်မြောက်ယွန်း နံတော်၏ ဂဟပတိအရပ်ဖြစ်သော ထနောင်းဝန်း အရပ်တွင် မဟာသင်္ကြန် ခေါ်တော်မူပြီးလျှင် ထီးဆောင်းမင်္ဂလာ မဟာဥကင်္သ ဖွင့်တော်မူ၍ “သီရိပဝရ မဟာဓမ္မရာဇာ” ဟူသော တံဆိပ်နာမံတော်ကို ခံတော်မူ၏။ | M198: On Monday, the 6th day of the waxing moon of Tabaung, 1122 Era, in the Thanaungwun area, which is the Gahapati quarter of the northwest direction of the royal palace, he held the Great Thingyan festival, opened the royal pavilion for the coronation ceremony, and received the title 'Thiri Pawara Maha Dhamma Raja'.
A199: First 5% | B199: vol1 | C199: 267 | D199: vol1_s002394 | E199: vol1_s002394_t03_cda942946177 | F199: King Alaungpaya | G199: ASSUMED_ROYAL_TITLE | H199: Thiri Pawara Maha Dhamma Raja | I199: hard | J199: The passage is under Alaungpaya’s successor, the Dipeyin prince (Naungdawgyi), not Alaungpaya. The contextual accession is explicit in vol1_s002339, owner page 260, following Alaungpaya’s death. This is an incorrect named-king resolution, not a fault in inferring an unstated king. | K199: Replace King Alaungpaya with the reigning Dipeyin king / Naungdawgyi; retain the stated action. | L199: သက္ကရာဇ် (၁၁၂၂) တစ်ထောင့်တစ်ရာ့နှစ်ဆယ့်နှစ်ခု တပေါင်းလဆန်း ခြောက်ရက်J တနင်္လာနေ့ ရွှေနန်းတော်၏ အနောက်မြောက်ယွန်း နံတော်၏ ဂဟပတိအရပ်ဖြစ်သော ထနောင်းဝန်း အရပ်တွင် မဟာသင်္ကြန် ခေါ်တော်မူပြီးလျှင် ထီးဆောင်းမင်္ဂလာ မဟာဥကင်္သ ဖွင့်တော်မူ၍ “သီရိပဝရ မဟာဓမ္မရာဇာ” ဟူသော တံဆိပ်နာမံတော်ကို ခံတော်မူ၏။ | M199: On Monday, the 6th day of the waxing moon of Tabaung, 1122 Era, in the Thanaungwun area, which is the Gahapati quarter of the northwest direction of the royal palace, he held the Great Thingyan festival, opened the royal pavilion for the coronation ceremony, and received the title 'Thiri Pawara Maha Dhamma Raja'.
A200: First 5% | B200: vol1 | C200: 267 | D200: vol1_s002395 | E200: vol1_s002395_t01_9287bd6eaec3 | F200: Chief Queen | G200: RECEIVED_TITLE_FROM_KING | H200: Maha Mingala Ratana Devi | I200: supported | J200: Supported by the Burmese sentence and allowed narrative context; grouping and contextually inferred participants accepted. | L200: ရှင်မိဖုရား ခေါင်ကြီးကိုလည်း “မဟာမင်္ဂလာ ရတနာဒေဝီ” ဟူသော တံဆိပ်နာမံတော်ကို ခံစေသည်။ | M200: He also had the Chief Queen receive the title 'Maha Mingala Ratana Devi'.
A201: First 5% | B201: vol1 | C201: 267 | D201: vol1_s002396 | E201: vol1_s002396_t01_7624a4562763 | F201: Queen | G201: RECEIVED_TITLE_FROM_KING | H201: Mingala Devi | I201: supported | J201: Supported by the Burmese sentence and allowed narrative context; grouping and contextually inferred participants accepted. | L201: မိဖုရား တစ်ပါးကိုလည်း မင်္ဂလာဒေဝီ၊ တစ်ပါးကိုလည်း သီရိရတနာဒေဝီ၊ တစ်ပါးကိုလည်း သီတာဒေဝီ၊ တစ်ပါးကိုလည်း သီရိရာဇဒေဝီ၊ တစ်ပါးကိုလည်း ရာဇဒေဝီ၊ တစ်ပါးကိုလည်း မလ္လာဒေဝီ၊ တစ်ပါးကိုလည်း မင်္ဂလာဒေဝီ ဘွဲ့ ပေးတော်မူသည်။ | M201: He also bestowed the titles of Mingala Devi upon one queen, Thiri Ratana Devi upon another, Thida Devi upon another, Thiri Raza Devi upon another, Raza Devi upon another, Malla Devi upon another, and Mingala Devi upon another.
...

Sheet Recall
A1: Tranche | B1: Volume | C1: Page | D1: Sentence ID | E1: Unit ID | F1: Source relationship (identified by the judge from the Burmese) | G1: Coverage | H1: Annotation available | I1: Matched triple IDs | J1: Note | K1: Burmese sentence | L1: English translation (auxiliary)
A2: First 5% | B2: vol1 | C2: 71 | D2: vol1_s000407 | E2: G01.01.01 | F2: Alaungmintaya makes a royal military sortie accompanied by princes, commanders and troops | G2: covered | H2: yes | I2: vol1_s000407_t02_97f3bf59b463; vol1_s000407_t03_0be63211651d; vol1_s000407_t04_d0b57d421653; vol1_s000407_t05_008bb89c30b3 | K2: ထိုအခါ အလောင်းမင်းတရားကြီး ဘုရားလည်း သက္ကရာဇ် တစ်ထောင့် တစ်ရာ့ လေးဆယ့် လေးခု၊ ကဆုန်လပြည့်ကျော်ရှစ်ရက် သောကြာနေ့၊ မွန်းယိမ်းနှစ်ချက်တီးကျော် နှစ်မောင်းတွင် အတန္တုအားဖြင့် တာဝတိံသာ မဟာသုဒဿနမြို့သို့ ချီတက်လာကုန်သော အသူရာစစ်သည်တို့ကို နှိပ်နင်းအံ့သောငှာ မင်္ဂလာရှိသော စိတ္တကုဋ် တံခါးမှ သိကြားထွက်စံသကဲ့သို့ အောင်တံခွန်ကို လွှားလွှားလွှင့်တော်မူ၍ သားတော်မြတ် နှစ်ပါးနှင့်တကွ ဆွေတော် မျိုးတော် ကျွန်တော်ရင်း မြင်းရည်တက် လေးဆယ့်ခြောက်ခေါင်း အစု အမှုထမ်း လက်နက်စွဲ သူရဲအပေါင်း ခြံရံလျက် မင်းတို့စံပယ်ခြင်းဖြင့် စည်တော်ရွမ်း၍ အရှေ့မျက်နှာ လက်ယာတံခါးမှ ရွှေထီးဖြန့်လျက် ထွက်တော် မူသည်ကို မွန်တို့တပ်က မြင်လျှင် သောသောထ၍ ကြည့်ကြစဉ် ကောင်းကင်အရပ်က သိမ်းငှက်တစ်ခုသည် စွန်ရဲကို တိုက်၍ ရှေ့တော်တူရူ ဦးခေါင်းငိုက်ဆိုက် ကျလာသည်ကို ရဲမက်တော်တို့ လှံနှင့်နှိပ်၍ ရလိုက်သည်။ | L2: At that time, Alaungmintayagyi Paya, in the year 1144, on the eighth day of the waning moon of Kason, a Friday, at the time just past two strokes of the afternoon, in order to suppress the Asura soldiers who were marching toward the Tavatimsa Mahasudassana city as if by analogy, raised the victory banner high as if Sakra were emerging from the auspicious Cittakuta gate, and surrounded by his two noble sons, his relatives, his kin, his loyal servants, forty-six cavalrymen, and all the armed soldiers and service personnel, with the royal drums beating in the royal manner, he emerged from the right gate on the eastern side with the golden umbrella spread; when the Mon army saw this, they rose up in a clamor to watch, and at that moment, a hawk from the sky attacked a kite, and it fell headlong directly in front of him, which the royal soldiers struck with spears and caught.
A3: First 5% | B3: vol1 | C3: 71 | D3: vol1_s000408 | E3: G01.02.01 | F3: The king asserts omen-backed and legitimate beneficent kingship | G3: covered | H3: yes | I3: vol1_s000408_t01_b0fbd1f80d6b; vol1_s000408_t04_53fd29578911 | K3: ထိုနိမိတ်ကို မြင်တော်မူလျှင် စွန်နံဖြစ်သော မွန်ကို သိမ်းနံဖြစ်သော ငါမင်းတရားသည် ယခုနေ့ အောင်မြင် တော်မူမည် မချွတ်ဟု ဘတ်တော်မူပြီးမှ ငါတည်း မင်းမျိုးမင်းမြစ် မှန်သည်ဖြစ်၍ ရဟန်းရှင်လူ ပြည်သူတကာ သာသနာတော်မြတ်၏ စီးပွား၊ မယ်တော်, ခမည်းတော်, ဆွေတော် မျိုးတော်တို့၏ စီးပွား၊ သားတော်အစဉ် မြေးတော်အဆက် မြစ်တော်အညွန့် တိုင်အောင် ဆောင်တော်မူထိုက်သည် မှန်လျှင် သိကြား၊ စတုလောကပါလာ၊ သာသနာတော်မြတ်ကို စောင့်ကုန်သော သမ္မာဒေဝ နတ်မြတ်အပေါင်း ကောင်းသော ကြည့်ရှုခြင်းဖြင့် ညီညာ ရွက်ဆောင်သည်ဖြစ်၍ အလွယ်တကူ ရန်သူတော်တို့ကို လှံထင်ဆောက်ကာ ပြီးမြောက် အောင်မြင်တော်မူစေ သောဟု ရွှေကရားဖြင့် ရေစက်သွန်းတော်မူပြီးလျှင် ရေ မြေသို့ရောက်သည်နှင့် တစ်ပြိုင်နက် “အောင်ခါ ရောက်ပြီ၊ အောင်ချိန်သင့်ပြီ၊ အောင်ခါတန်ပြီ”ဟု ညွှန်းသော စကားဖြင့် အောင်သံပေးတော်မူသည်ကို မြန်မာစစ်သည် မွန်စစ်သည် အပေါင်းတို့သည် နားရင်းကြပ်ကြပ်အပ်၍ ဟစ်ကြော်ဘိကဲ့သို့ တပ်လုံး ကြားလေ၏။ | L3: Upon seeing this omen, he declared, 'I, King Alaungmintaya, who am the hawk, will undoubtedly be victorious this day over the Mon, who are the kite,' and after declaring this, he poured water from a golden ewer, saying, 'Since I am truly of royal lineage, if it is true that I am worthy to carry out the welfare of the noble religion for all monks and laypeople, the welfare of my mother, father, relatives, and kin, and the welfare of my sons, grandsons, and great-grandsons, then may Sakra, the Four Heavenly Kings, and all the noble Samma-deva spirits who guard the noble religion look upon me with favor, act in unison, and cause me to easily pierce the enemies with spears and achieve complete victory,' and as soon as the water reached the earth, he gave the signal for victory with the words, 'The time for victory has arrived, the time for victory is appropriate, the time for victory is due,' which the Burmese soldiers and all the Mon soldiers heard throughout the entire camp as if they were shouting it right into their ears.
A4: First 5% | B4: vol1 | C4: 71 | D4: vol1_s000408 | E4: G01.02.02 | F4: The king performs a water-libation invocation seeking divine support for victory | G4: covered | H4: yes | I4: vol1_s000408_t02_c56a1c317678; vol1_s000408_t03_d6fdde6ee5ab | K4: ထိုနိမိတ်ကို မြင်တော်မူလျှင် စွန်နံဖြစ်သော မွန်ကို သိမ်းနံဖြစ်သော ငါမင်းတရားသည် ယခုနေ့ အောင်မြင် တော်မူမည် မချွတ်ဟု ဘတ်တော်မူပြီးမှ ငါတည်း မင်းမျိုးမင်းမြစ် မှန်သည်ဖြစ်၍ ရဟန်းရှင်လူ ပြည်သူတကာ သာသနာတော်မြတ်၏ စီးပွား၊ မယ်တော်, ခမည်းတော်, ဆွေတော် မျိုးတော်တို့၏ စီးပွား၊ သားတော်အစဉ် မြေးတော်အဆက် မြစ်တော်အညွန့် တိုင်အောင် ဆောင်တော်မူထိုက်သည် မှန်လျှင် သိကြား၊ စတုလောကပါလာ၊ သာသနာတော်မြတ်ကို စောင့်ကုန်သော သမ္မာဒေဝ နတ်မြတ်အပေါင်း ကောင်းသော ကြည့်ရှုခြင်းဖြင့် ညီညာ ရွက်ဆောင်သည်ဖြစ်၍ အလွယ်တကူ ရန်သူတော်တို့ကို လှံထင်ဆောက်ကာ ပြီးမြောက် အောင်မြင်တော်မူစေ သောဟု ရွှေကရားဖြင့် ရေစက်သွန်းတော်မူပြီးလျှင် ရေ မြေသို့ရောက်သည်နှင့် တစ်ပြိုင်နက် “အောင်ခါ ရောက်ပြီ၊ အောင်ချိန်သင့်ပြီ၊ အောင်ခါတန်ပြီ”ဟု ညွှန်းသော စကားဖြင့် အောင်သံပေးတော်မူသည်ကို မြန်မာစစ်သည် မွန်စစ်သည် အပေါင်းတို့သည် နားရင်းကြပ်ကြပ်အပ်၍ ဟစ်ကြော်ဘိကဲ့သို့ တပ်လုံး ကြားလေ၏။ | L4: Upon seeing this omen, he declared, 'I, King Alaungmintaya, who am the hawk, will undoubtedly be victorious this day over the Mon, who are the kite,' and after declaring this, he poured water from a golden ewer, saying, 'Since I am truly of royal lineage, if it is true that I am worthy to carry out the welfare of the noble religion for all monks and laypeople, the welfare of my mother, father, relatives, and kin, and the welfare of my sons, grandsons, and great-grandsons, then may Sakra, the Four Heavenly Kings, and all the noble Samma-deva spirits who guard the noble religion look upon me with favor, act in unison, and cause me to easily pierce the enemies with spears and achieve complete victory,' and as soon as the water reached the earth, he gave the signal for victory with the words, 'The time for victory has arrived, the time for victory is appropriate, the time for victory is due,' which the Burmese soldiers and all the Mon soldiers heard throughout the entire camp as if they were shouting it right into their ears.
A5: First 5% | B5: vol1 | C5: 71 | D5: vol1_s000408 | E5: G01.02.03 | F5: The king gives the victory signal heard by both armies | G5: covered | H5: yes | I5: vol1_s000408_t06_8c758f29b409 | K5: ထိုနိမိတ်ကို မြင်တော်မူလျှင် စွန်နံဖြစ်သော မွန်ကို သိမ်းနံဖြစ်သော ငါမင်းတရားသည် ယခုနေ့ အောင်မြင် တော်မူမည် မချွတ်ဟု ဘတ်တော်မူပြီးမှ ငါတည်း မင်းမျိုးမင်းမြစ် မှန်သည်ဖြစ်၍ ရဟန်းရှင်လူ ပြည်သူတကာ သာသနာတော်မြတ်၏ စီးပွား၊ မယ်တော်, ခမည်းတော်, ဆွေတော် မျိုးတော်တို့၏ စီးပွား၊ သားတော်အစဉ် မြေးတော်အဆက် မြစ်တော်အညွန့် တိုင်အောင် ဆောင်တော်မူထိုက်သည် မှန်လျှင် သိကြား၊ စတုလောကပါလာ၊ သာသနာတော်မြတ်ကို စောင့်ကုန်သော သမ္မာဒေဝ နတ်မြတ်အပေါင်း ကောင်းသော ကြည့်ရှုခြင်းဖြင့် ညီညာ ရွက်ဆောင်သည်ဖြစ်၍ အလွယ်တကူ ရန်သူတော်တို့ကို လှံထင်ဆောက်ကာ ပြီးမြောက် အောင်မြင်တော်မူစေ သောဟု ရွှေကရားဖြင့် ရေစက်သွန်းတော်မူပြီးလျှင် ရေ မြေသို့ရောက်သည်နှင့် တစ်ပြိုင်နက် “အောင်ခါ ရောက်ပြီ၊ အောင်ချိန်သင့်ပြီ၊ အောင်ခါတန်ပြီ”ဟု ညွှန်းသော စကားဖြင့် အောင်သံပေးတော်မူသည်ကို မြန်မာစစ်သည် မွန်စစ်သည် အပေါင်းတို့သည် နားရင်းကြပ်ကြပ်အပ်၍ ဟစ်ကြော်ဘိကဲ့သို့ တပ်လုံး ကြားလေ၏။ | L5: Upon seeing this omen, he declared, 'I, King Alaungmintaya, who am the hawk, will undoubtedly be victorious this day over the Mon, who are the kite,' and after declaring this, he poured water from a golden ewer, saying, 'Since I am truly of royal lineage, if it is true that I am worthy to carry out the welfare of the noble religion for all monks and laypeople, the welfare of my mother, father, relatives, and kin, and the welfare of my sons, grandsons, and great-grandsons, then may Sakra, the Four Heavenly Kings, and all the noble Samma-deva spirits who guard the noble religion look upon me with favor, act in unison, and cause me to easily pierce the enemies with spears and achieve complete victory,' and as soon as the water reached the earth, he gave the signal for victory with the words, 'The time for victory has arrived, the time for victory is appropriate, the time for victory is due,' which the Burmese soldiers and all the Mon soldiers heard throughout the entire camp as if they were shouting it right into their ears.
A6: First 5% | B6: vol1 | C6: 71 | D6: vol1_s000409 | E6: G01.03.01 | F6: The Mon troops are intimidated into dropping weapons by the king's voice and authority | G6: covered | H6: yes | I6: vol1_s000409_t01_7dd4a7d1314c; vol1_s000409_t02_02d08094e321; vol1_s000409_t03_60475c497770 | K6: ထိုအခါ ပမာအားဖြင့် ကေသရရာဇာ ခြင်္သေ့မင်းသည် ရွှေဂူဝမှ ခုန်ကြွစံပယ်လျက် ထွက်၍ ဟောက်မြူးသောအသံကို တောင်ယံကမ်းပါး ကျက်စားရှိကုန်သော သားအပေါင်းတို့သည် ကြောက်ခြင်းပြင်းရကား ကမ်းပါးချောက်သို့ ဦးစောက်ကျဘိ သကဲ့သို့ မွန်စစ်သည် အပေါင်းတို့သည် အလောင်းမင်းတရားကြီးဘုရား အသံတော်ကို ကြားလျှင် ဘုန်းအာဏာတော်အား သတိမတည်နိုင်၍ လက်နက်လွတ်ကျသော ဟူ၏။ | L6: At that time, it is said that just as when the lion king, the Kesararaja, leaps out from the mouth of a golden cave and roars, all the animals living on the mountain slopes are so terrified that they fall headlong into the ravines, so too, when the Mon soldiers heard the voice of Alaungmintayagyi Paya, they could not maintain their composure due to his royal power and authority, and they dropped their weapons.
A7: First 5% | B7: vol1 | C7: 71 | D7: vol1_s000410 | E7: G01.04.01 | F7: The king signals and personally directs the army's attack | G7: covered | H7: yes | I7: vol1_s000410_t01_6fb674c9e392; vol1_s000410_t02_ef2633dfdf11 | K7: " ယင်းသို့ စင်တွင် တပ်မတော်မှ အောင်စည် အောင်မောင်း သောင်းသောင်းသောသော တီးမှုတ်စေလျက် အမှတ်ပေးတော်မူလျှင် လေးဆယ့်ငါးတပ် စွဲမှတ်ရှိနေကုန်သော မြင်းစီးသူရဲ၊ သေနတ်စွဲသူရဲ၊ လေးစွဲသူရဲ၊ ရထားစွဲသူရဲ၊ တင်ကျည်းစွဲ သူရဲတို့လည်း တစ်ပြိုင်နက် ကြော်ငြာလျက် အဆုတ်အဆိုင်းမရှိ ချွံချွံရွပ်ရွပ် ထိုးခုတ်ပစ်ခတ်ကြသည်ကို မွန်တို့လည်း မဆုတ်မနစ် ကြိုး၍ခံသည်၊ မနည်းကြာ တစ်ဦးကိုတစ်ဦး မတိုးမဝှေ့ နိုင်၊ အထွေးထွေးရှိစဉ် အလောင်း မင်းတရားကြီးဘုရား ကိုယ်တော်တိုင် ကွပ်သည်ကို ရဲမက်တော်တို့မြင်လျှင် အသက်ကို ပန်းတစ်ပွင့် အနှိုင်းမမှတ် စွန့်စား ထိုးခုတ် ပစ်ခတ်ကြသောကြောင့် မွန်တို့ အရှအန အသေအပျောက် များသည်နှင့် မနည်းကြာအမ်း၍ ရှိနေစဉ် တပ်မတော်နှင့်တကွ တောင်ဘိ၏သို့ တစ်ဟုန်တည်း တိုက်တော်မူလျှင် မွန်တို့ မခံနိုင်၍ အဆီးအတားမရှိ ပျက်လေ၏။ | L7: In this way, when the royal army gave the signal by beating the victory drums and gongs loudly, the forty-five units of cavalrymen, musketeers, archers, charioteers, and spearmen all at once shouted and charged forward without hesitation, stabbing and shooting fiercely; the Mon also resisted with unyielding effort, and for a while, they could not push or shove one another, and while they were in this state of entanglement, the royal soldiers saw Alaungmintayagyi Paya himself directing the battle, and because they fought, stabbed, and shot with such abandon, regarding their lives as no more than a flower, the Mon suffered many casualties and deaths, and while they were wavering for a while, he attacked with the royal army in one swift rush toward the south, and the Mon could not withstand it and were defeated without obstruction.
A8: First 5% | B8: vol1 | C8: 71 | D8: vol1_s000410 | E8: G01.04.02 | F8: Burmese troops assault and eventually rout the Mon | G8: covered | H8: yes | I8: vol1_s000410_t04_3fe015232093; vol1_s000410_t05_0fefbe13d092 | K8: " ယင်းသို့ စင်တွင် တပ်မတော်မှ အောင်စည် အောင်မောင်း သောင်းသောင်းသောသော တီးမှုတ်စေလျက် အမှတ်ပေးတော်မူလျှင် လေးဆယ့်ငါးတပ် စွဲမှတ်ရှိနေကုန်သော မြင်းစီးသူရဲ၊ သေနတ်စွဲသူရဲ၊ လေးစွဲသူရဲ၊ ရထားစွဲသူရဲ၊ တင်ကျည်းစွဲ သူရဲတို့လည်း တစ်ပြိုင်နက် ကြော်ငြာလျက် အဆုတ်အဆိုင်းမရှိ ချွံချွံရွပ်ရွပ် ထိုးခုတ်ပစ်ခတ်ကြသည်ကို မွန်တို့လည်း မဆုတ်မနစ် ကြိုး၍ခံသည်၊ မနည်းကြာ တစ်ဦးကိုတစ်ဦး မတိုးမဝှေ့ နိုင်၊ အထွေးထွေးရှိစဉ် အလောင်း မင်းတရားကြီးဘုရား ကိုယ်တော်တိုင် ကွပ်သည်ကို ရဲမက်တော်တို့မြင်လျှင် အသက်ကို ပန်းတစ်ပွင့် အနှိုင်းမမှတ် စွန့်စား ထိုးခုတ် ပစ်ခတ်ကြသောကြောင့် မွန်တို့ အရှအန အသေအပျောက် များသည်နှင့် မနည်းကြာအမ်း၍ ရှိနေစဉ် တပ်မတော်နှင့်တကွ တောင်ဘိ၏သို့ တစ်ဟုန်တည်း တိုက်တော်မူလျှင် မွန်တို့ မခံနိုင်၍ အဆီးအတားမရှိ ပျက်လေ၏။ | L8: In this way, when the royal army gave the signal by beating the victory drums and gongs loudly, the forty-five units of cavalrymen, musketeers, archers, charioteers, and spearmen all at once shouted and charged forward without hesitation, stabbing and shooting fiercely; the Mon also resisted with unyielding effort, and for a while, they could not push or shove one another, and while they were in this state of entanglement, the royal soldiers saw Alaungmintayagyi Paya himself directing the battle, and because they fought, stabbed, and shot with such abandon, regarding their lives as no more than a flower, the Mon suffered many casualties and deaths, and while they were wavering for a while, he attacked with the royal army in one swift rush toward the south, and the Mon could not withstand it and were defeated without obstruction.
A9: First 5% | B9: vol1 | C9: 71 | D9: vol1_s000410 | E9: G01.04.03 | F9: Mon troops initially resist the Burmese attack | G9: covered | H9: yes | I9: vol1_s000410_t03_46bb5d1bcdce | K9: " ယင်းသို့ စင်တွင် တပ်မတော်မှ အောင်စည် အောင်မောင်း သောင်းသောင်းသောသော တီးမှုတ်စေလျက် အမှတ်ပေးတော်မူလျှင် လေးဆယ့်ငါးတပ် စွဲမှတ်ရှိနေကုန်သော မြင်းစီးသူရဲ၊ သေနတ်စွဲသူရဲ၊ လေးစွဲသူရဲ၊ ရထားစွဲသူရဲ၊ တင်ကျည်းစွဲ သူရဲတို့လည်း တစ်ပြိုင်နက် ကြော်ငြာလျက် အဆုတ်အဆိုင်းမရှိ ချွံချွံရွပ်ရွပ် ထိုးခုတ်ပစ်ခတ်ကြသည်ကို မွန်တို့လည်း မဆုတ်မနစ် ကြိုး၍ခံသည်၊ မနည်းကြာ တစ်ဦးကိုတစ်ဦး မတိုးမဝှေ့ နိုင်၊ အထွေးထွေးရှိစဉ် အလောင်း မင်းတရားကြီးဘုရား ကိုယ်တော်တိုင် ကွပ်သည်ကို ရဲမက်တော်တို့မြင်လျှင် အသက်ကို ပန်းတစ်ပွင့် အနှိုင်းမမှတ် စွန့်စား ထိုးခုတ် ပစ်ခတ်ကြသောကြောင့် မွန်တို့ အရှအန အသေအပျောက် များသည်နှင့် မနည်းကြာအမ်း၍ ရှိနေစဉ် တပ်မတော်နှင့်တကွ တောင်ဘိ၏သို့ တစ်ဟုန်တည်း တိုက်တော်မူလျှင် မွန်တို့ မခံနိုင်၍ အဆီးအတားမရှိ ပျက်လေ၏။ | L9: In this way, when the royal army gave the signal by beating the victory drums and gongs loudly, the forty-five units of cavalrymen, musketeers, archers, charioteers, and spearmen all at once shouted and charged forward without hesitation, stabbing and shooting fiercely; the Mon also resisted with unyielding effort, and for a while, they could not push or shove one another, and while they were in this state of entanglement, the royal soldiers saw Alaungmintayagyi Paya himself directing the battle, and because they fought, stabbed, and shot with such abandon, regarding their lives as no more than a flower, the Mon suffered many casualties and deaths, and while they were wavering for a while, he attacked with the royal army in one swift rush toward the south, and the Mon could not withstand it and were defeated without obstruction.
A10: First 5% | B10: vol1 | C10: 71 | D10: vol1_s000411 | E10: G01.05.01 | F10: The remaining Mon encircling formations collapse after the eastern army | G10: covered | H10: yes | I10: vol1_s000411_t01_7937cc94dec9; vol1_s000411_t02_d89bf0092878 | K10: အရှေ့မျက်နှာက မွန်တို့ တပ်မ ပျက်လျှင် တောင်မျက်နှာ၊ အနောက်မျက်နှာ၊ မြောက်မျက်နှာ၊ ရံတပ်အလုံးလည်း ပျက်ပြန်လေ၏။ | L10: When the Mon main army on the eastern side was defeated, the southern, western, and northern sides, and all the supporting units, were also defeated.
A11: First 5% | B11: vol1 | C11: 71 | D11: vol1_s000412 | E11: G01.06.01 | F11: Royal troops pursue and attack the retreating Mon, putting them to flight | G11: covered | H11: yes | I11: vol1_s000412_t02_109353c6190e; vol1_s000412_t03_9e474c2e606c | K11: ယင်းသောအခါ ကဆုန် နွေလ ဖြစ်လျက် မြောက်လေ ပြင်းစွာလာလတ်၍ မြူမှုန်ခြောင်းခြောင်း တောင်သို့ဘိကာ မွန်တို့ ဆုတ်ခွာသည်ကို ရဲမက်တော်တို့ လိုက်ထပ်ထိုးခုတ် ပစ်ခတ်လျှင် မွန်စစ်သည်တို့ ခါးဝတ်မဆည်း စစ်ကြီး ထောင်းထောင်းပျက်၍ ကိုယ်လွတ် ဆုတ်ခွာရလေ၏။ | L11: At that time, it being the summer month of Kason, a strong north wind blew, and as the Mon retreated toward the south amidst clouds of dust, the royal soldiers pursued them, stabbing and shooting, so the Mon soldiers, unable to even fasten their waistcloths, suffered a total collapse of their great army and had to retreat to save their own lives.
A12: First 5% | B12: vol1 | C12: 77 | D12: vol1_s000475 | E12: G02.01.01 | F12: Alaungmintaya receives intelligence that the Mon are establishing a base at Ywathitgyi | G12: missing | H12: yes | K12: မွန်တပ်များကို ဆက်တိုက် အောင်တော်မူခြင်း ယင်းကမှ သေနတ်ဝန် မင်းကျော်ပျံချီ, မင်းလှရွှေတောင်တို့ကို ရွာသစ်ကြီး အရပ်သည် အထက်ကလည်း မွန်တို့ အခြေအမြစ် ပြုဘူးသည်၊ ယခုလည်း မွန်တို့ အရပ်အနေပြုကြောင်းနှင့် ကြားတော်မူရသည်၊ အခြေအမြစ် မဖြစ်ခင် ဖျက်ချေဟု စေခန့်တော်မူ၍ ချီရ၏။ | L12: Regarding the successive victories over the Mon forces, [the King] heard that the area of Ywathitgyi had previously been used as a base by the Mons and that they were currently using it as a base again; he ordered the Thanatwun [Minister of Musketeers] Minkyawpyanchi and Minhlashwetaung to march and destroy it before it could become established.
A13: First 5% | B13: vol1 | C13: 77 | D13: vol1_s000475 | E13: G02.01.02 | F13: Alaungmintaya orders Min Kyaw Pyanchi and Min Hla Shwetaung to destroy the base | G13: covered | H13: yes | I13: vol1_s000475_t01_9f4ce4ba91f5; vol1_s000475_t02_180ed2759ca7 | K13: မွန်တပ်များကို ဆက်တိုက် အောင်တော်မူခြင်း ယင်းကမှ သေနတ်ဝန် မင်းကျော်ပျံချီ, မင်းလှရွှေတောင်တို့ကို ရွာသစ်ကြီး အရပ်သည် အထက်ကလည်း မွန်တို့ အခြေအမြစ် ပြုဘူးသည်၊ ယခုလည်း မွန်တို့ အရပ်အနေပြုကြောင်းနှင့် ကြားတော်မူရသည်၊ အခြေအမြစ် မဖြစ်ခင် ဖျက်ချေဟု စေခန့်တော်မူ၍ ချီရ၏။ | L13: Regarding the successive victories over the Mon forces, [the King] heard that the area of Ywathitgyi had previously been used as a base by the Mons and that they were currently using it as a base again; he ordered the Thanatwun [Minister of Musketeers] Minkyawpyanchi and Minhlashwetaung to march and destroy it before it could become established.
A14: First 5% | B14: vol1 | C14: 77 | D14: vol1_s000476 | E14: G02.02.01 | F14: The ruler of Moksobo is entrenched with his troops | G14: covered | H14: yes | I14: vol1_s000476_t01_25e6f50e581c; vol1_s000476_t02_0709fa67e2f8 | K14: ယင်းသောအခါ အဝဗိုလ်မှူး ငွေခွန်ဝန်က မူဆိုးပိုမင်းသည် ထန်းလုံးတပ်ကို သံမြို့မှတ်၍ လူနှစ်ထောင် သုံးထောင်နှင့် အခိုင်နေလေသည်မှာ မြောက်ဘက်တစ်လွှား ငါးစို့တစ်ခွင်၊ မြို့ကျေးရွာများကို သိမ်းရုံးပြီးလျှင် ခင်ဦးစား လက်ယာပျံချီကို မြောက်ဘက် မျက်နှာက ရံစေမည်၊ အဲနရဲ၊ အဲကန်ကောင်းတို့ကိုလည်း ကျောက်မြောင်းတိုင် မြို့ ရွာများကို သိမ်းယူဆန်တက်၍ အရှေ့မျက်နှာက ရံစေမည်။ | L14: At that time, the Ava commander, the Ngwekwanwun, stated that the Musopo King [the Mon King] had designated the Thanlon fort as a fortified city and was holding it firmly with two or three thousand men, and that after seizing the towns and villages in the Ngasint region across the north, he would have Khin-U-sa Let-ya-pyanchi surround it from the northern front, and would have Aenarae and Aekankaung seize the Kyaukmyaung-taing towns and villages and march up to surround it from the eastern front.
A15: First 5% | B15: vol1 | C15: 77 | D15: vol1_s000476 | E15: G02.02.02 | F15: Ngwekhunwun plans territorial advance and assigns northern and eastern encirclement commands | G15: incorrect | H15: yes | I15: vol1_s000476_t03_e18c108df2bc; vol1_s000476_t04_fd98cf6593fe | J15: Commands are extracted, but assigned to the opposing ruler; this is an inaccurate match, not a wholly unextracted event. | K15: ယင်းသောအခါ အဝဗိုလ်မှူး ငွေခွန်ဝန်က မူဆိုးပိုမင်းသည် ထန်းလုံးတပ်ကို သံမြို့မှတ်၍ လူနှစ်ထောင် သုံးထောင်နှင့် အခိုင်နေလေသည်မှာ မြောက်ဘက်တစ်လွှား ငါးစို့တစ်ခွင်၊ မြို့ကျေးရွာများကို သိမ်းရုံးပြီးလျှင် ခင်ဦးစား လက်ယာပျံချီကို မြောက်ဘက် မျက်နှာက ရံစေမည်၊ အဲနရဲ၊ အဲကန်ကောင်းတို့ကိုလည်း ကျောက်မြောင်းတိုင် မြို့ ရွာများကို သိမ်းယူဆန်တက်၍ အရှေ့မျက်နှာက ရံစေမည်။ | L15: At that time, the Ava commander, the Ngwekwanwun, stated that the Musopo King [the Mon King] had designated the Thanlon fort as a fortified city and was holding it firmly with two or three thousand men, and that after seizing the towns and villages in the Ngasint region across the north, he would have Khin-U-sa Let-ya-pyanchi surround it from the northern front, and would have Aenarae and Aekankaung seize the Kyaukmyaung-taing towns and villages and march up to surround it from the eastern front.
A16: First 5% | B16: vol1 | C16: 77 | D16: vol1_s000477 | E16: G02.03.01 | F16: Ngwekhunwun assigns western and southern prongs of the encirclement | G16: incorrect | H16: yes | I16: vol1_s000477_t01_9bc0ee6b5563; vol1_s000477_t02_8a4279ee1476 | J16: The encirclement plan is extracted under the wrong side and target. | K16: သမိန်ဇိပ်ဗြဲ၊ သမိန်လွတ်၊ သမိန်သံလိုက်၊ ရဲခေါင်စံကျော်တို့ကိုလည်း မူးမြစ်ကြောင်း အနောက်တစ်ပြင် မြို့ရွာများကို သိမ်းယူ၍ အနောက် မျက်နှာက ရံစေမည်၊ ငါလည်း ပိုက်သီဟ၊ ပိုက်ကမြင်းတို့နှင့် စစ်ကိုင်းကြောင်း ချီတက်၍ တောင်မျက်နှာက ရံမည်၊ သည်ကဲ့သို့ လေးကြောင်း လေးမျက်နှာ တက်၍ စစ်အားကြီး လုပ်ကြံရလျှင် မုဆိုးပိုတပ်သည် ငှက်မူ၍ ပျံထွက်နိုင်မည်လောဟု ကြုံးဝါးပြီးလျှင် သက္ကရာဇ် (၁၁၁၄) တစ်ထောင့်တစ်ရာ တစ်ဆယ့်လေးခု၊ သီတင်းကျွတ်လ တွင် သမိန်ဇိပ်ဗြဲ တစ်တပ်၊ သမိန်လွတ် တစ်တပ်၊ သမိန်သံလိုက် တစ်တပ်၊ ရဲခေါင်စံကျော် တစ်တပ်၊ သည် လေးတပ်တွင် မြင်းသုံးရာ၊ စစ်သည်သူရဲနှစ်ထောင့်ငါးရာ၊ မူးမြစ်ကြောင်း ချီနှင့်ရလေ၏။ | L16: He also stated that he would have Samainzeipbyae, Samainlut, Samainthanlaik, and Ye-khaung-san-kyaw seize the towns and villages on the western side of the Mu River and surround it from the western front, and that he himself would march along the Sagaing route with Paik-thiha and Paik-kamyin and surround it from the southern front; after boasting, 'If we attack with such great military force, advancing from four directions and four fronts, will the Musopo fort be able to fly away like a bird?', in the month of Thadingyut, in the year 1114, he sent one unit of Samainzeipbyae, one unit of Samainlut, one unit of Samainthanlaik, and one unit of Ye-khaung-san-kyaw—these four units, consisting of three hundred horses and two thousand five hundred soldiers—to march along the Mu River.
A17: First 5% | B17: vol1 | C17: 77 | D17: vol1_s000477 | E17: G02.03.02 | F17: Four Mon battalions are dispatched along the Mu | G17: incorrect | H17: yes | I17: vol1_s000477_t03_25771c827e6a | J17: The mobilization is extracted under the wrong side. | K17: သမိန်ဇိပ်ဗြဲ၊ သမိန်လွတ်၊ သမိန်သံလိုက်၊ ရဲခေါင်စံကျော်တို့ကိုလည်း မူးမြစ်ကြောင်း အနောက်တစ်ပြင် မြို့ရွာများကို သိမ်းယူ၍ အနောက် မျက်နှာက ရံစေမည်၊ ငါလည်း ပိုက်သီဟ၊ ပိုက်ကမြင်းတို့နှင့် စစ်ကိုင်းကြောင်း ချီတက်၍ တောင်မျက်နှာက ရံမည်၊ သည်ကဲ့သို့ လေးကြောင်း လေးမျက်နှာ တက်၍ စစ်အားကြီး လုပ်ကြံရလျှင် မုဆိုးပိုတပ်သည် ငှက်မူ၍ ပျံထွက်နိုင်မည်လောဟု ကြုံးဝါးပြီးလျှင် သက္ကရာဇ် (၁၁၁၄) တစ်ထောင့်တစ်ရာ တစ်ဆယ့်လေးခု၊ သီတင်းကျွတ်လ တွင် သမိန်ဇိပ်ဗြဲ တစ်တပ်၊ သမိန်လွတ် တစ်တပ်၊ သမိန်သံလိုက် တစ်တပ်၊ ရဲခေါင်စံကျော် တစ်တပ်၊ သည် လေးတပ်တွင် မြင်းသုံးရာ၊ စစ်သည်သူရဲနှစ်ထောင့်ငါးရာ၊ မူးမြစ်ကြောင်း ချီနှင့်ရလေ၏။ | L17: He also stated that he would have Samainzeipbyae, Samainlut, Samainthanlaik, and Ye-khaung-san-kyaw seize the towns and villages on the western side of the Mu River and surround it from the western front, and that he himself would march along the Sagaing route with Paik-thiha and Paik-kamyin and surround it from the southern front; after boasting, 'If we attack with such great military force, advancing from four directions and four fronts, will the Musopo fort be able to fly away like a bird?', in the month of Thadingyut, in the year 1114, he sent one unit of Samainzeipbyae, one unit of Samainlut, one unit of Samainthanlaik, and one unit of Ye-khaung-san-kyaw—these four units, consisting of three hundred horses and two thousand five hundred soldiers—to march along the Mu River.
A18: First 5% | B18: vol1 | C18: 77 | D18: vol1_s000478 | E18: G02.04.01 | F18: E Na Ye and E Kan Kaung advance along the Irrawaddy to Kyaukmyaung | G18: covered | H18: yes | I18: vol1_s000478_t01_5ee6ca8a38c6 | K18: အဲနရဲ၊ အဲကန်ကောင်းတို့ လည်း ဧရာဝတီမြစ်ကြောင်း ကျောက်မြောင်းရောက် ချီရလေသည်။ | L18: Aenarae and Aekankaung also marched along the Irrawaddy River route to reach Kyaukmyaung.
A19: First 5% | B19: vol1 | C19: 77 | D19: vol1_s000479 | E19: G02.05.01 | F19: Mon commanders are dispatched to assist or direct Khin-U's control of the northern towns | G19: covered | H19: yes | I19: vol1_s000479_t02_1407a7ea8054 | K19: ခင်ဦးစား လက်ယာပျံချီသို့လည်း မြောက်ဘက် တစ်လွှား ငါးစို့တစ်ခွင် သိမ်းရုံးစည်းကြပ်ရမည်ဟု မွန်တပ်မှူးတို့ကို ခန့်ထားစေလွှတ်သည်။ | L19: He also appointed and sent Mon commanders to Khin-U-sa Let-ya-pyanchi to seize and organize the Ngasint region across the north.
A20: First 5% | B20: vol1 | C20: 77 | D20: vol1_s000480 | E20: G02.06.01 | F20: Alaungmintaya receives news of the four Mon battalions at Nyaunghla | G20: covered | H20: yes | I20: vol1_s000480_t01_70af7dca3c1d | K20: ယင်းသောအခါ အနောက်ဘက် မူးကြောင်း အလျင်ချီနှင့်ရသည့် လေးဗိုလ်လေးတပ်တို့ ညောင်လှအရပ်သို့ ရောက်ကြောင်းကို အလောင်းမင်းတရားကြီးဘုရား ကြားတော်မူသော်လည်း ရွာသစ်ကြီးသို့ သေနတ်ဝန် မင်းကျော် ပျံချီ, မင်းလှရွှေတောင်တို့ ချီလေရာ သူရဲသူခက် လက်နက်ပါ ချေသောကြောင့် ခပ်မဆိတ် နေတော်မူ၏။ | L20: At that time, although the Alaungmintayagyi Phaya heard that the four commanders and four units that had marched ahead along the western Mu route had reached the Nyaunghla area, because the Thanatwun Minkyawpyanchi and Minhlashwetaung had marched to Ywathitgyi with soldiers and weapons, he remained silent.
A21: First 5% | B21: vol1 | C21: 77 | D21: vol1_s000480 | E21: G02.06.02 | F21: The two royal commanders are away campaigning at Ywathitgyi | G21: covered | H21: yes | I21: vol1_s000475_t01_9f4ce4ba91f5; vol1_s000475_t02_180ed2759ca7 | J21: The Ywathitgyi mission repeats the deployment already represented in sentence 1; no extra omission charged. | K21: ယင်းသောအခါ အနောက်ဘက် မူးကြောင်း အလျင်ချီနှင့်ရသည့် လေးဗိုလ်လေးတပ်တို့ ညောင်လှအရပ်သို့ ရောက်ကြောင်းကို အလောင်းမင်းတရားကြီးဘုရား ကြားတော်မူသော်လည်း ရွာသစ်ကြီးသို့ သေနတ်ဝန် မင်းကျော် ပျံချီ, မင်းလှရွှေတောင်တို့ ချီလေရာ သူရဲသူခက် လက်နက်ပါ ချေသောကြောင့် ခပ်မဆိတ် နေတော်မူ၏။ | L21: At that time, although the Alaungmintayagyi Phaya heard that the four commanders and four units that had marched ahead along the western Mu route had reached the Nyaunghla area, because the Thanatwun Minkyawpyanchi and Minhlashwetaung had marched to Ywathitgyi with soldiers and weapons, he remained silent.
A22: First 5% | B22: vol1 | C22: 77 | D22: vol1_s000481 | E22: G02.07.01 | F22: Princes and commanders propose attacking the new Mon camp | G22: covered | H22: yes | I22: vol1_s000481_t01_86b135767614 | K22: ထိုအခါ သားတော် ညီတော် ဗိုလ်မှူး တပ်မှူးတို့က ယခု မွန်တို့ လေးတပ်ချီလာ၍ ညောင်လှအရပ်တွင် တပ်ကြီးတပ်ခိုင် တည်လုပ်လာသည်ကို တပ်မပြီးခင် အလျင်အမြန် ချီတက်၍ ဖျက်ဆီးသိမ်းယူပါမည်ဟု လျှောက်ကြသော်လည်း ဘဝရှင် အလောင်းမင်းတၱရားကြီးဘုရားသည် ရာဇမာယာ၌ လိမ္မာတော်မူသည်နှင့်အညီ ယခု တပ်မပြီးခင် ချီချေသော် မွန်တို့က ငါတို့ တပ်မပြီးခင်သောကြောင့်သာ ရှုံးရလေသည်ဟု ဆိုပြန်လေတော့မည်၊ တပ်ပြီးစေဦးဟု အမိန့်တော် ရှိ၍ ရပ်ဆိုင်းသည့်အတွင်း သေနတ်ဝန် မင်းကျော်ပျံချီ, မင်းလှရွှေတောင်တို့ ရွာသစ်ကြီးတပ်ကို ဖျက်သိမ်း ပြန်ရောက်၍ ယခု မွန်တို့က စစ်လေးမျက်နှာ ခန့်ရန် စည်းကြပ်ကြောင်းနှင့် အဝက ထွက်လာသူတို့ စစ်ချက်တွင် ကြားသိရသည့် အတိုင်း မွန်တို့က ညောင်လှတွင် တပ်တည်သည်ကို ချီ၍ တိုက်ပါမည်ဟု လျှောက်သည်တွင် မွန်တို့ တပ်တည်၍ ပြီးစေဦးတော့ဟု ငါ့အမိန့်တော် ရှိနှင့်သည်၊ ယခုမှာ မွန်တို့တပ်လည်း ပြီးတန်လေပြီ၊ ချီလေတော့ဟူ၍ အမိန့်တော် ရှိလျှင် သေနတ်ဝန် မင်းကျော်ပျံချီ, မင်းလှရွှေတောင်တို့ လက်နက်ကိုင် လူတစ်ထောင့်ငါးရာနှင့် ချက်တစ်ဖြုတ် ချီသွား၍ ညောင်လှတပ်သို့ ရောက်လျှင် တပ်မချဘဲ သမိန်သံလိုက်တပ်ကို တိုက်သည်။ | L22: At that time, although the royal sons, younger brothers, commanders, and unit leaders submitted that they would march quickly to destroy and seize the large, fortified fort that the four Mon units had come and built in the Nyaunghla area before it was completed, the Bawa-shin Alaungmintayagyi Phaya, being skilled in royal strategy, said, 'If we march before it is completed, the Mons will say they only lost because their fort was not finished; let them finish the fort,' and ordered a halt; while they were waiting, the Thanatwun Minkyawpyanchi and Minhlashwetaung destroyed the Ywathitgyi fort and returned, and upon hearing from the reports of those who came out from Ava that the Mons were organizing to attack from four directions, they submitted that they would march and attack the fort the Mons were building at Nyaunghla, to which [the King] replied, 'I have already given the order to let the Mons finish building their fort; now that the Mon fort must be finished, march,' and upon that order, the Thanatwun Minkyawpyanchi and Minhlashwetaung marched immediately with one thousand five hundred armed men, and upon reaching the Nyaunghla fort, they did not set up a camp but attacked the Samainthanlaik unit.
A23: First 5% | B23: vol1 | C23: 77 | D23: vol1_s000481 | E23: G02.07.02 | F23: The king initially orders a delay | G23: covered | H23: yes | I23: vol1_s000481_t02_e12d797c9038; vol1_s000481_t03_44cf9924cffe | K23: ထိုအခါ သားတော် ညီတော် ဗိုလ်မှူး တပ်မှူးတို့က ယခု မွန်တို့ လေးတပ်ချီလာ၍ ညောင်လှအရပ်တွင် တပ်ကြီးတပ်ခိုင် တည်လုပ်လာသည်ကို တပ်မပြီးခင် အလျင်အမြန် ချီတက်၍ ဖျက်ဆီးသိမ်းယူပါမည်ဟု လျှောက်ကြသော်လည်း ဘဝရှင် အလောင်းမင်းတၱရားကြီးဘုရားသည် ရာဇမာယာ၌ လိမ္မာတော်မူသည်နှင့်အညီ ယခု တပ်မပြီးခင် ချီချေသော် မွန်တို့က ငါတို့ တပ်မပြီးခင်သောကြောင့်သာ ရှုံးရလေသည်ဟု ဆိုပြန်လေတော့မည်၊ တပ်ပြီးစေဦးဟု အမိန့်တော် ရှိ၍ ရပ်ဆိုင်းသည့်အတွင်း သေနတ်ဝန် မင်းကျော်ပျံချီ, မင်းလှရွှေတောင်တို့ ရွာသစ်ကြီးတပ်ကို ဖျက်သိမ်း ပြန်ရောက်၍ ယခု မွန်တို့က စစ်လေးမျက်နှာ ခန့်ရန် စည်းကြပ်ကြောင်းနှင့် အဝက ထွက်လာသူတို့ စစ်ချက်တွင် ကြားသိရသည့် အတိုင်း မွန်တို့က ညောင်လှတွင် တပ်တည်သည်ကို ချီ၍ တိုက်ပါမည်ဟု လျှောက်သည်တွင် မွန်တို့ တပ်တည်၍ ပြီးစေဦးတော့ဟု ငါ့အမိန့်တော် ရှိနှင့်သည်၊ ယခုမှာ မွန်တို့တပ်လည်း ပြီးတန်လေပြီ၊ ချီလေတော့ဟူ၍ အမိန့်တော် ရှိလျှင် သေနတ်ဝန် မင်းကျော်ပျံချီ, မင်းလှရွှေတောင်တို့ လက်နက်ကိုင် လူတစ်ထောင့်ငါးရာနှင့် ချက်တစ်ဖြုတ် ချီသွား၍ ညောင်လှတပ်သို့ ရောက်လျှင် တပ်မချဘဲ သမိန်သံလိုက်တပ်ကို တိုက်သည်။ | L23: At that time, although the royal sons, younger brothers, commanders, and unit leaders submitted that they would march quickly to destroy and seize the large, fortified fort that the four Mon units had come and built in the Nyaunghla area before it was completed, the Bawa-shin Alaungmintayagyi Phaya, being skilled in royal strategy, said, 'If we march before it is completed, the Mons will say they only lost because their fort was not finished; let them finish the fort,' and ordered a halt; while they were waiting, the Thanatwun Minkyawpyanchi and Minhlashwetaung destroyed the Ywathitgyi fort and returned, and upon hearing from the reports of those who came out from Ava that the Mons were organizing to attack from four directions, they submitted that they would march and attack the fort the Mons were building at Nyaunghla, to which [the King] replied, 'I have already given the order to let the Mons finish building their fort; now that the Mon fort must be finished, march,' and upon that order, the Thanatwun Minkyawpyanchi and Minhlashwetaung marched immediately with one thousand five hundred armed men, and upon reaching the Nyaunghla fort, they did not set up a camp but attacked the Samainthanlaik unit.
A24: First 5% | B24: vol1 | C24: 77 | D24: vol1_s000481 | E24: G02.07.03 | F24: Min Kyaw Pyanchi and Min Hla Shwetaung destroy the Ywathitgyi camp and return | G24: missing | H24: yes | K24: ထိုအခါ သားတော် ညီတော် ဗိုလ်မှူး တပ်မှူးတို့က ယခု မွန်တို့ လေးတပ်ချီလာ၍ ညောင်လှအရပ်တွင် တပ်ကြီးတပ်ခိုင် တည်လုပ်လာသည်ကို တပ်မပြီးခင် အလျင်အမြန် ချီတက်၍ ဖျက်ဆီးသိမ်းယူပါမည်ဟု လျှောက်ကြသော်လည်း ဘဝရှင် အလောင်းမင်းတၱရားကြီးဘုရားသည် ရာဇမာယာ၌ လိမ္မာတော်မူသည်နှင့်အညီ ယခု တပ်မပြီးခင် ချီချေသော် မွန်တို့က ငါတို့ တပ်မပြီးခင်သောကြောင့်သာ ရှုံးရလေသည်ဟု ဆိုပြန်လေတော့မည်၊ တပ်ပြီးစေဦးဟု အမိန့်တော် ရှိ၍ ရပ်ဆိုင်းသည့်အတွင်း သေနတ်ဝန် မင်းကျော်ပျံချီ, မင်းလှရွှေတောင်တို့ ရွာသစ်ကြီးတပ်ကို ဖျက်သိမ်း ပြန်ရောက်၍ ယခု မွန်တို့က စစ်လေးမျက်နှာ ခန့်ရန် စည်းကြပ်ကြောင်းနှင့် အဝက ထွက်လာသူတို့ စစ်ချက်တွင် ကြားသိရသည့် အတိုင်း မွန်တို့က ညောင်လှတွင် တပ်တည်သည်ကို ချီ၍ တိုက်ပါမည်ဟု လျှောက်သည်တွင် မွန်တို့ တပ်တည်၍ ပြီးစေဦးတော့ဟု ငါ့အမိန့်တော် ရှိနှင့်သည်၊ ယခုမှာ မွန်တို့တပ်လည်း ပြီးတန်လေပြီ၊ ချီလေတော့ဟူ၍ အမိန့်တော် ရှိလျှင် သေနတ်ဝန် မင်းကျော်ပျံချီ, မင်းလှရွှေတောင်တို့ လက်နက်ကိုင် လူတစ်ထောင့်ငါးရာနှင့် ချက်တစ်ဖြုတ် ချီသွား၍ ညောင်လှတပ်သို့ ရောက်လျှင် တပ်မချဘဲ သမိန်သံလိုက်တပ်ကို တိုက်သည်။ | L24: At that time, although the royal sons, younger brothers, commanders, and unit leaders submitted that they would march quickly to destroy and seize the large, fortified fort that the four Mon units had come and built in the Nyaunghla area before it was completed, the Bawa-shin Alaungmintayagyi Phaya, being skilled in royal strategy, said, 'If we march before it is completed, the Mons will say they only lost because their fort was not finished; let them finish the fort,' and ordered a halt; while they were waiting, the Thanatwun Minkyawpyanchi and Minhlashwetaung destroyed the Ywathitgyi fort and returned, and upon hearing from the reports of those who came out from Ava that the Mons were organizing to attack from four directions, they submitted that they would march and attack the fort the Mons were building at Nyaunghla, to which [the King] replied, 'I have already given the order to let the Mons finish building their fort; now that the Mon fort must be finished, march,' and upon that order, the Thanatwun Minkyawpyanchi and Minhlashwetaung marched immediately with one thousand five hundred armed men, and upon reaching the Nyaunghla fort, they did not set up a camp but attacked the Samainthanlaik unit.
A25: First 5% | B25: vol1 | C25: 77 | D25: vol1_s000481 | E25: G02.07.04 | F25: Interrogation of arrivals from Ava supplies intelligence on the four-pronged Mon plan | G25: missing | H25: yes | K25: ထိုအခါ သားတော် ညီတော် ဗိုလ်မှူး တပ်မှူးတို့က ယခု မွန်တို့ လေးတပ်ချီလာ၍ ညောင်လှအရပ်တွင် တပ်ကြီးတပ်ခိုင် တည်လုပ်လာသည်ကို တပ်မပြီးခင် အလျင်အမြန် ချီတက်၍ ဖျက်ဆီးသိမ်းယူပါမည်ဟု လျှောက်ကြသော်လည်း ဘဝရှင် အလောင်းမင်းတၱရားကြီးဘုရားသည် ရာဇမာယာ၌ လိမ္မာတော်မူသည်နှင့်အညီ ယခု တပ်မပြီးခင် ချီချေသော် မွန်တို့က ငါတို့ တပ်မပြီးခင်သောကြောင့်သာ ရှုံးရလေသည်ဟု ဆိုပြန်လေတော့မည်၊ တပ်ပြီးစေဦးဟု အမိန့်တော် ရှိ၍ ရပ်ဆိုင်းသည့်အတွင်း သေနတ်ဝန် မင်းကျော်ပျံချီ, မင်းလှရွှေတောင်တို့ ရွာသစ်ကြီးတပ်ကို ဖျက်သိမ်း ပြန်ရောက်၍ ယခု မွန်တို့က စစ်လေးမျက်နှာ ခန့်ရန် စည်းကြပ်ကြောင်းနှင့် အဝက ထွက်လာသူတို့ စစ်ချက်တွင် ကြားသိရသည့် အတိုင်း မွန်တို့က ညောင်လှတွင် တပ်တည်သည်ကို ချီ၍ တိုက်ပါမည်ဟု လျှောက်သည်တွင် မွန်တို့ တပ်တည်၍ ပြီးစေဦးတော့ဟု ငါ့အမိန့်တော် ရှိနှင့်သည်၊ ယခုမှာ မွန်တို့တပ်လည်း ပြီးတန်လေပြီ၊ ချီလေတော့ဟူ၍ အမိန့်တော် ရှိလျှင် သေနတ်ဝန် မင်းကျော်ပျံချီ, မင်းလှရွှေတောင်တို့ လက်နက်ကိုင် လူတစ်ထောင့်ငါးရာနှင့် ချက်တစ်ဖြုတ် ချီသွား၍ ညောင်လှတပ်သို့ ရောက်လျှင် တပ်မချဘဲ သမိန်သံလိုက်တပ်ကို တိုက်သည်။ | L25: At that time, although the royal sons, younger brothers, commanders, and unit leaders submitted that they would march quickly to destroy and seize the large, fortified fort that the four Mon units had come and built in the Nyaunghla area before it was completed, the Bawa-shin Alaungmintayagyi Phaya, being skilled in royal strategy, said, 'If we march before it is completed, the Mons will say they only lost because their fort was not finished; let them finish the fort,' and ordered a halt; while they were waiting, the Thanatwun Minkyawpyanchi and Minhlashwetaung destroyed the Ywathitgyi fort and returned, and upon hearing from the reports of those who came out from Ava that the Mons were organizing to attack from four directions, they submitted that they would march and attack the fort the Mons were building at Nyaunghla, to which [the King] replied, 'I have already given the order to let the Mons finish building their fort; now that the Mon fort must be finished, march,' and upon that order, the Thanatwun Minkyawpyanchi and Minhlashwetaung marched immediately with one thousand five hundred armed men, and upon reaching the Nyaunghla fort, they did not set up a camp but attacked the Samainthanlaik unit.
A26: First 5% | B26: vol1 | C26: 77 | D26: vol1_s000481 | E26: G02.07.05 | F26: The commanders propose attacking Nyaunghla | G26: covered | H26: yes | I26: vol1_s000481_t01_86b135767614 | J26: The collective “Royal commanders proposed attack” is accepted for the proposals in this compound sentence. | K26: ထိုအခါ သားတော် ညီတော် ဗိုလ်မှူး တပ်မှူးတို့က ယခု မွန်တို့ လေးတပ်ချီလာ၍ ညောင်လှအရပ်တွင် တပ်ကြီးတပ်ခိုင် တည်လုပ်လာသည်ကို တပ်မပြီးခင် အလျင်အမြန် ချီတက်၍ ဖျက်ဆီးသိမ်းယူပါမည်ဟု လျှောက်ကြသော်လည်း ဘဝရှင် အလောင်းမင်းတၱရားကြီးဘုရားသည် ရာဇမာယာ၌ လိမ္မာတော်မူသည်နှင့်အညီ ယခု တပ်မပြီးခင် ချီချေသော် မွန်တို့က ငါတို့ တပ်မပြီးခင်သောကြောင့်သာ ရှုံးရလေသည်ဟု ဆိုပြန်လေတော့မည်၊ တပ်ပြီးစေဦးဟု အမိန့်တော် ရှိ၍ ရပ်ဆိုင်းသည့်အတွင်း သေနတ်ဝန် မင်းကျော်ပျံချီ, မင်းလှရွှေတောင်တို့ ရွာသစ်ကြီးတပ်ကို ဖျက်သိမ်း ပြန်ရောက်၍ ယခု မွန်တို့က စစ်လေးမျက်နှာ ခန့်ရန် စည်းကြပ်ကြောင်းနှင့် အဝက ထွက်လာသူတို့ စစ်ချက်တွင် ကြားသိရသည့် အတိုင်း မွန်တို့က ညောင်လှတွင် တပ်တည်သည်ကို ချီ၍ တိုက်ပါမည်ဟု လျှောက်သည်တွင် မွန်တို့ တပ်တည်၍ ပြီးစေဦးတော့ဟု ငါ့အမိန့်တော် ရှိနှင့်သည်၊ ယခုမှာ မွန်တို့တပ်လည်း ပြီးတန်လေပြီ၊ ချီလေတော့ဟူ၍ အမိန့်တော် ရှိလျှင် သေနတ်ဝန် မင်းကျော်ပျံချီ, မင်းလှရွှေတောင်တို့ လက်နက်ကိုင် လူတစ်ထောင့်ငါးရာနှင့် ချက်တစ်ဖြုတ် ချီသွား၍ ညောင်လှတပ်သို့ ရောက်လျှင် တပ်မချဘဲ သမိန်သံလိုက်တပ်ကို တိုက်သည်။ | L26: At that time, although the royal sons, younger brothers, commanders, and unit leaders submitted that they would march quickly to destroy and seize the large, fortified fort that the four Mon units had come and built in the Nyaunghla area before it was completed, the Bawa-shin Alaungmintayagyi Phaya, being skilled in royal strategy, said, 'If we march before it is completed, the Mons will say they only lost because their fort was not finished; let them finish the fort,' and ordered a halt; while they were waiting, the Thanatwun Minkyawpyanchi and Minhlashwetaung destroyed the Ywathitgyi fort and returned, and upon hearing from the reports of those who came out from Ava that the Mons were organizing to attack from four directions, they submitted that they would march and attack the fort the Mons were building at Nyaunghla, to which [the King] replied, 'I have already given the order to let the Mons finish building their fort; now that the Mon fort must be finished, march,' and upon that order, the Thanatwun Minkyawpyanchi and Minhlashwetaung marched immediately with one thousand five hundred armed men, and upon reaching the Nyaunghla fort, they did not set up a camp but attacked the Samainthanlaik unit.
A27: First 5% | B27: vol1 | C27: 77 | D27: vol1_s000481 | E27: G02.07.06 | F27: The king authorizes the advance | G27: covered | H27: yes | I27: vol1_s000481_t04_ee4b249cb475 | K27: ထိုအခါ သားတော် ညီတော် ဗိုလ်မှူး တပ်မှူးတို့က ယခု မွန်တို့ လေးတပ်ချီလာ၍ ညောင်လှအရပ်တွင် တပ်ကြီးတပ်ခိုင် တည်လုပ်လာသည်ကို တပ်မပြီးခင် အလျင်အမြန် ချီတက်၍ ဖျက်ဆီးသိမ်းယူပါမည်ဟု လျှောက်ကြသော်လည်း ဘဝရှင် အလောင်းမင်းတၱရားကြီးဘုရားသည် ရာဇမာယာ၌ လိမ္မာတော်မူသည်နှင့်အညီ ယခု တပ်မပြီးခင် ချီချေသော် မွန်တို့က ငါတို့ တပ်မပြီးခင်သောကြောင့်သာ ရှုံးရလေသည်ဟု ဆိုပြန်လေတော့မည်၊ တပ်ပြီးစေဦးဟု အမိန့်တော် ရှိ၍ ရပ်ဆိုင်းသည့်အတွင်း သေနတ်ဝန် မင်းကျော်ပျံချီ, မင်းလှရွှေတောင်တို့ ရွာသစ်ကြီးတပ်ကို ဖျက်သိမ်း ပြန်ရောက်၍ ယခု မွန်တို့က စစ်လေးမျက်နှာ ခန့်ရန် စည်းကြပ်ကြောင်းနှင့် အဝက ထွက်လာသူတို့ စစ်ချက်တွင် ကြားသိရသည့် အတိုင်း မွန်တို့က ညောင်လှတွင် တပ်တည်သည်ကို ချီ၍ တိုက်ပါမည်ဟု လျှောက်သည်တွင် မွန်တို့ တပ်တည်၍ ပြီးစေဦးတော့ဟု ငါ့အမိန့်တော် ရှိနှင့်သည်၊ ယခုမှာ မွန်တို့တပ်လည်း ပြီးတန်လေပြီ၊ ချီလေတော့ဟူ၍ အမိန့်တော် ရှိလျှင် သေနတ်ဝန် မင်းကျော်ပျံချီ, မင်းလှရွှေတောင်တို့ လက်နက်ကိုင် လူတစ်ထောင့်ငါးရာနှင့် ချက်တစ်ဖြုတ် ချီသွား၍ ညောင်လှတပ်သို့ ရောက်လျှင် တပ်မချဘဲ သမိန်သံလိုက်တပ်ကို တိုက်သည်။ | L27: At that time, although the royal sons, younger brothers, commanders, and unit leaders submitted that they would march quickly to destroy and seize the large, fortified fort that the four Mon units had come and built in the Nyaunghla area before it was completed, the Bawa-shin Alaungmintayagyi Phaya, being skilled in royal strategy, said, 'If we march before it is completed, the Mons will say they only lost because their fort was not finished; let them finish the fort,' and ordered a halt; while they were waiting, the Thanatwun Minkyawpyanchi and Minhlashwetaung destroyed the Ywathitgyi fort and returned, and upon hearing from the reports of those who came out from Ava that the Mons were organizing to attack from four directions, they submitted that they would march and attack the fort the Mons were building at Nyaunghla, to which [the King] replied, 'I have already given the order to let the Mons finish building their fort; now that the Mon fort must be finished, march,' and upon that order, the Thanatwun Minkyawpyanchi and Minhlashwetaung marched immediately with one thousand five hundred armed men, and upon reaching the Nyaunghla fort, they did not set up a camp but attacked the Samainthanlaik unit.
A28: First 5% | B28: vol1 | C28: 77 | D28: vol1_s000481 | E28: G02.07.07 | F28: The royal commanders attack Thamin Thanlite's camp with their troops | G28: covered | H28: yes | I28: vol1_s000481_t05_9cb62cd963f0 | K28: ထိုအခါ သားတော် ညီတော် ဗိုလ်မှူး တပ်မှူးတို့က ယခု မွန်တို့ လေးတပ်ချီလာ၍ ညောင်လှအရပ်တွင် တပ်ကြီးတပ်ခိုင် တည်လုပ်လာသည်ကို တပ်မပြီးခင် အလျင်အမြန် ချီတက်၍ ဖျက်ဆီးသိမ်းယူပါမည်ဟု လျှောက်ကြသော်လည်း ဘဝရှင် အလောင်းမင်းတၱရားကြီးဘုရားသည် ရာဇမာယာ၌ လိမ္မာတော်မူသည်နှင့်အညီ ယခု တပ်မပြီးခင် ချီချေသော် မွန်တို့က ငါတို့ တပ်မပြီးခင်သောကြောင့်သာ ရှုံးရလေသည်ဟု ဆိုပြန်လေတော့မည်၊ တပ်ပြီးစေဦးဟု အမိန့်တော် ရှိ၍ ရပ်ဆိုင်းသည့်အတွင်း သေနတ်ဝန် မင်းကျော်ပျံချီ, မင်းလှရွှေတောင်တို့ ရွာသစ်ကြီးတပ်ကို ဖျက်သိမ်း ပြန်ရောက်၍ ယခု မွန်တို့က စစ်လေးမျက်နှာ ခန့်ရန် စည်းကြပ်ကြောင်းနှင့် အဝက ထွက်လာသူတို့ စစ်ချက်တွင် ကြားသိရသည့် အတိုင်း မွန်တို့က ညောင်လှတွင် တပ်တည်သည်ကို ချီ၍ တိုက်ပါမည်ဟု လျှောက်သည်တွင် မွန်တို့ တပ်တည်၍ ပြီးစေဦးတော့ဟု ငါ့အမိန့်တော် ရှိနှင့်သည်၊ ယခုမှာ မွန်တို့တပ်လည်း ပြီးတန်လေပြီ၊ ချီလေတော့ဟူ၍ အမိန့်တော် ရှိလျှင် သေနတ်ဝန် မင်းကျော်ပျံချီ, မင်းလှရွှေတောင်တို့ လက်နက်ကိုင် လူတစ်ထောင့်ငါးရာနှင့် ချက်တစ်ဖြုတ် ချီသွား၍ ညောင်လှတပ်သို့ ရောက်လျှင် တပ်မချဘဲ သမိန်သံလိုက်တပ်ကို တိုက်သည်။ | L28: At that time, although the royal sons, younger brothers, commanders, and unit leaders submitted that they would march quickly to destroy and seize the large, fortified fort that the four Mon units had come and built in the Nyaunghla area before it was completed, the Bawa-shin Alaungmintayagyi Phaya, being skilled in royal strategy, said, 'If we march before it is completed, the Mons will say they only lost because their fort was not finished; let them finish the fort,' and ordered a halt; while they were waiting, the Thanatwun Minkyawpyanchi and Minhlashwetaung destroyed the Ywathitgyi fort and returned, and upon hearing from the reports of those who came out from Ava that the Mons were organizing to attack from four directions, they submitted that they would march and attack the fort the Mons were building at Nyaunghla, to which [the King] replied, 'I have already given the order to let the Mons finish building their fort; now that the Mon fort must be finished, march,' and upon that order, the Thanatwun Minkyawpyanchi and Minhlashwetaung marched immediately with one thousand five hundred armed men, and upon reaching the Nyaunghla fort, they did not set up a camp but attacked the Samainthanlaik unit.
A29: First 5% | B29: vol1 | C29: 77 | D29: vol1_s000482 | E29: G02.08.01 | F29: Thamin Thanlite's camp is defeated | G29: covered | H29: yes | I29: vol1_s000482_t01_d615f46458fd | K29: သမိန်သံလိုက် တပ်ပျက် လေ၏၊ သမိန်သံလိုက်လည်း မြင်းဦးတွင်ပင် သေလေ၏။ | L29: The Samainthanlaik unit was defeated, and Samainthanlaik died right on his horse.
A30: First 5% | B30: vol1 | C30: 77 | D30: vol1_s000482 | E30: G02.08.02 | F30: Thamin Thanlite is killed | G30: covered | H30: yes | I30: vol1_s000482_t02_134d4cf7955a | K30: သမိန်သံလိုက် တပ်ပျက် လေ၏၊ သမိန်သံလိုက်လည်း မြင်းဦးတွင်ပင် သေလေ၏။ | L30: The Samainthanlaik unit was defeated, and Samainthanlaik died right on his horse.
A31: First 5% | B31: vol1 | C31: 77 | D31: vol1_s000483 | E31: G02.09.01 | F31: The royal commanders attack and defeat Thamin Zeipbwe's camp | G31: covered | H31: yes | I31: vol1_s000483_t01_b5161a85d7a7 | K31: သမိန်သံလိုက် တပ်ပျက်လျှင် သမိန်ဇိပ်ဗြဲတပ်ကို တိုက်သည်၊ ပျက်ပြန်လေ၏။ | L31: When the Samainthanlaik unit was defeated, they attacked the Samainzeipbyae unit, which was also defeated.
A32: First 5% | B32: vol1 | C32: 77 | D32: vol1_s000484 | E32: G02.10.01 | F32: The royal commanders attack and defeat Thamin Lwat's camp | G32: covered | H32: yes | I32: vol1_s000484_t01_572a80131d9e | K32: သမိန်ဇိပ်ဗြဲတပ် ပျက်လျှင် သမိန်လွတ် တပ်ကို တိုက်သည်၊ ပျက်ပြန်လေ၏။ | L32: When the Samainzeipbyae unit was defeated, they attacked the Samainlut unit, which was also defeated.
A33: First 5% | B33: vol1 | C33: 77 | D33: vol1_s000485 | E33: G02.11.01 | F33: The royal commanders attack and defeat Ye Khaung San Kyaw's camp | G33: covered | H33: yes | I33: vol1_s000485_t01_87192a03f74e | K33: သမိန်လွတ်တပ် ပျက်လျှင် ရဲခေါင်စံကျော်တပ်ကို တိုက်သည်၊ ပျက်ပြန်လေ၏။ | L33: When the Samainlut unit was defeated, they attacked the Ye-khaung-san-kyaw unit, which was also defeated.
A34: First 5% | B34: vol1 | C34: 77 | D34: vol1_s000486 | E34: G02.12.01 | F34: The three surviving Mon commanders escape on horseback | G34: covered | H34: yes | I34: vol1_s000486_t01_be6731c34dcc | K34: သမိန်ဇိပ်ဗြဲ၊ သမိန်လွတ်၊ ရဲခေါင် စံကျော်တို့ သုံးဦးလည်း မြင်းနှင့် အပြင်းခွာသောကြောင့် လွတ်လေ၏။ | L34: Samainzeipbyae, Samainlut, and Ye-khaung-san-kyaw, the three of them, escaped because they fled rapidly on horseback.
A35: First 5% | B35: vol1 | C35: 77 | D35: vol1_s000487 | E35: G02.13.01 | F35: The royal commanders capture prisoners, horses and guns | G35: covered | H35: yes | I35: vol1_s000487_t01_a1b359e82e11; vol1_s000487_t02_e5ca1114f3ee | K35: သေနတ်ဝန် မင်းကျော်ပျံချီ၊ မင်းလှ ရွှေတောင်တို့လည်း ညောင်လှတပ်တွင် ရလိုက်သည့် လူသုံးရာကျော်၊ မြင်း နှစ်ဆယ်၊ သေနတ် တစ်ရာကျော်များကို သိမ်းယူ၍ ဆက်ရလေ၏။ | L35: The Thanatwun Minkyawpyanchi and Minhlashwetaung seized and continued on with over three hundred men, twenty horses, and over one hundred muskets captured at the Nyaunghla fort.
A36: First 5% | B36: vol1 | C36: 77 | D36: vol1_s000487 | E36: G02.13.02 | F36: The captured people and materiel are presented to the king | G36: missing | H36: yes | J36: Capture is represented, but ဆက်ရလေ၏, presentation of the booty to the king, is not. | K36: သေနတ်ဝန် မင်းကျော်ပျံချီ၊ မင်းလှ ရွှေတောင်တို့လည်း ညောင်လှတပ်တွင် ရလိုက်သည့် လူသုံးရာကျော်၊ မြင်း နှစ်ဆယ်၊ သေနတ် တစ်ရာကျော်များကို သိမ်းယူ၍ ဆက်ရလေ၏။ | L36: The Thanatwun Minkyawpyanchi and Minhlashwetaung seized and continued on with over three hundred men, twenty horses, and over one hundred muskets captured at the Nyaunghla fort.
A37: First 5% | B37: vol1 | C37: 85 | D37: vol1_s000558 | E37: G03.01.01 | F37: Alaungmintaya receives updated news of the fugitives | G37: missing | H37: yes | K37: ထိုအကြောင်းကို ဘဝရှင်အလောင်းမင်းတရားကြီးဘုရား ကြားတော်မူပြန်၍ ငကျန်နှင့်တကွ လူပြေးတို့ကို တွေ့ မိအောင် လိုက်လံဖမ်းဆီးရမည်ဟု သေနတ်ဝန် မင်းကျော်ပျံချီရှိရာ မင်းခင်းတပ်သို့ အမိန့်တော်ပြန်ရ၏။ | L37: The Lord of Life, Alaungmintaya Gyi, heard of this matter again and issued an order to the Minkhin camp, where the Minister of Musketeers, Min Kyaw Pyan Chi, was stationed, stating that he must pursue and capture the fugitives, including Nga Kyan.
A38: First 5% | B38: vol1 | C38: 85 | D38: vol1_s000558 | E38: G03.01.02 | F38: The king orders Min Kyaw Pyanchi to pursue and arrest Nga Kyan and the fugitives | G38: covered | H38: yes | I38: vol1_s000558_t01_cc04dd9b9ad7; vol1_s000558_t02_3fbdc8129d54 | K38: ထိုအကြောင်းကို ဘဝရှင်အလောင်းမင်းတရားကြီးဘုရား ကြားတော်မူပြန်၍ ငကျန်နှင့်တကွ လူပြေးတို့ကို တွေ့ မိအောင် လိုက်လံဖမ်းဆီးရမည်ဟု သေနတ်ဝန် မင်းကျော်ပျံချီရှိရာ မင်းခင်းတပ်သို့ အမိန့်တော်ပြန်ရ၏။ | L38: The Lord of Life, Alaungmintaya Gyi, heard of this matter again and issued an order to the Minkhin camp, where the Minister of Musketeers, Min Kyaw Pyan Chi, was stationed, stating that he must pursue and capture the fugitives, including Nga Kyan.
A39: First 5% | B39: vol1 | C39: 85 | D39: vol1_s000559 | E39: G03.02.01 | F39: Min Kyaw Pyanchi advances on Thitkhauk with his troops | G39: covered | H39: yes | I39: vol1_s000559_t01_e82adf250f44 | K39: သေနတ်ဝန် မင်းကျော်ပျံချီလည်း လက်နက်ကိုင် လူနှစ်ထောင်ကျော်နှင့် သစ်ခေါက်တပ်သို့ ချီသွားလေသော် ရာဇာဓိရာဇ်, ခင်ဦးစားတို့လည်း သစ်ခေါက်တပ်တွင် မနေဝံ့၍ တောင်ငူရာဇာ ရှိရာ ပိုနိမ့်ပိုမြင့်ကို အခိုအမှီပြုမှ ချမ်းသာမည် အမှတ်ရှိသဖြင့် ယောကျောက်ကာသို့ ပြေးလေ၏။ | L39: When the Minister of Musketeers, Min Kyaw Pyan Chi, marched to the Thitkhauk camp with over two thousand armed men, Razadarit and Khin U Sa, not daring to remain at the Thitkhauk camp and believing that they would only be safe if they sought refuge at Po-nim-po-myint where the Taungoo Raja was, fled to Yaw-kyauk-ka.
A40: First 5% | B40: vol1 | C40: 85 | D40: vol1_s000559 | E40: G03.02.02 | F40: Razadhiraj and the Khin-U lord flee seeking protection from Taungoo Yaza | G40: covered | H40: yes | I40: vol1_s000559_t02_695c0de17933; vol1_s000559_t03_0dfc62174135 | K40: သေနတ်ဝန် မင်းကျော်ပျံချီလည်း လက်နက်ကိုင် လူနှစ်ထောင်ကျော်နှင့် သစ်ခေါက်တပ်သို့ ချီသွားလေသော် ရာဇာဓိရာဇ်, ခင်ဦးစားတို့လည်း သစ်ခေါက်တပ်တွင် မနေဝံ့၍ တောင်ငူရာဇာ ရှိရာ ပိုနိမ့်ပိုမြင့်ကို အခိုအမှီပြုမှ ချမ်းသာမည် အမှတ်ရှိသဖြင့် ယောကျောက်ကာသို့ ပြေးလေ၏။ | L40: When the Minister of Musketeers, Min Kyaw Pyan Chi, marched to the Thitkhauk camp with over two thousand armed men, Razadarit and Khin U Sa, not daring to remain at the Thitkhauk camp and believing that they would only be safe if they sought refuge at Po-nim-po-myint where the Taungoo Raja was, fled to Yaw-kyauk-ka.
A41: First 5% | B41: vol1 | C41: 85 | D41: vol1_s000560 | E41: G03.03.01 | F41: Min Kyaw Pyanchi approaches and takes position away from the fortified camp | G41: covered | H41: yes | I41: vol1_s000560_t01_b8a420a1a6b1 | K41: ထိုအခါ သေနတ်ဝန် မင်းကျော်ပျံချီသည် သစ်ခေါက်တပ်သို့ ရောက်၍ ချဉ်းကပ် ကြည့်ရှုလျှင် သစ်လုံးပတ် တစ်ဖက်၊ အရပ်တစ်ဆယ့် ငါးတောင် မြဲမြံ ခိုင်ခန့်စွာ ဆောက်လုပ်သည့် တပ်ကိုမြင်လျှင် ဆုတ်၍ သေနတ်တစ်လှမ်း ခန့် ကွာက စွဲရပ်သည်တွင် နံနက် လေးချက်တီး အချိန်ကသည် နံနက်တစ်ချက်တီးတိုင်အောင် တပ်ထိပ်က မိုးရွာ၏သို့ ပစ်ဖောက်သည့် အမြောက် စိန်ပြောင်း လက်နက် ထူထပ်လှသောကြောင့် အထိအပါး များချေ၏။ | L41: At that time, when the Minister of Musketeers, Min Kyaw Pyan Chi, arrived at the Thitkhauk camp and approached to inspect it, he saw a camp built firmly and sturdily with a circumference of one log and a height of fifteen cubits; he retreated and stood at a distance of about one musket shot, and because the cannons, mortars, and firearms firing from the top of the camp like rain from four o'clock in the morning until one o'clock in the morning were so dense, there were many casualties.
A42: First 5% | B42: vol1 | C42: 85 | D42: vol1_s000560 | E42: G03.03.02 | F42: The camp defenders bombard his force and inflict casualties | G42: covered | H42: yes | I42: vol1_s000560_t02_390d5d83270b | K42: ထိုအခါ သေနတ်ဝန် မင်းကျော်ပျံချီသည် သစ်ခေါက်တပ်သို့ ရောက်၍ ချဉ်းကပ် ကြည့်ရှုလျှင် သစ်လုံးပတ် တစ်ဖက်၊ အရပ်တစ်ဆယ့် ငါးတောင် မြဲမြံ ခိုင်ခန့်စွာ ဆောက်လုပ်သည့် တပ်ကိုမြင်လျှင် ဆုတ်၍ သေနတ်တစ်လှမ်း ခန့် ကွာက စွဲရပ်သည်တွင် နံနက် လေးချက်တီး အချိန်ကသည် နံနက်တစ်ချက်တီးတိုင်အောင် တပ်ထိပ်က မိုးရွာ၏သို့ ပစ်ဖောက်သည့် အမြောက် စိန်ပြောင်း လက်နက် ထူထပ်လှသောကြောင့် အထိအပါး များချေ၏။ | L42: At that time, when the Minister of Musketeers, Min Kyaw Pyan Chi, arrived at the Thitkhauk camp and approached to inspect it, he saw a camp built firmly and sturdily with a circumference of one log and a height of fifteen cubits; he retreated and stood at a distance of about one musket shot, and because the cannons, mortars, and firearms firing from the top of the camp like rain from four o'clock in the morning until one o'clock in the morning were so dense, there were many casualties.
A43: First 5% | B43: vol1 | C43: 85 | D43: vol1_s000561 | E43: G03.04.01 | F43: Yinpa commander Min Hla Kyaw Khaung dies in the fighting | G43: covered | H43: yes | I43: vol1_s000561_t01_675b56585cfb | K43: ယင်းပါဗိုလ်မင်းလှကျော်ခေါင်လည်း ဆုံးချေ၏။ | L43: The commander accompanying him, Bo Min Hla Kyaw Khaung, also died.
A44: First 5% | B44: vol1 | C44: 85 | D44: vol1_s000562 | E44: G03.05.01 | F44: Min Kyaw Pyanchi orders infantry-first retreat and cavalry protection | G44: covered | H44: yes | I44: vol1_s000562_t01_df4a70c848d8 | K44: ထိုအခါ ဗိုလ်မှူး မင်းကျော်ပျံချီလည်း ယခု ငါတို့ ခွာချေသော် သူက လိုက်ထပ်ချိမ့်မည်ဟု အမှတ်ရှိ၍ သေနတ်လုလင် ခြေသည်သူရဲကို အလျင် ဆုတ်နှင့်စေ၊ ယင်းသို့မှ မြင်းတပ် နောက်က အုပ်၍ လိုက်လေ၊ ခြေသည်တစ်ယောက်မျှ သူကရသည် ကြားရလျှင် မြင်းတပ်သားတို့ကို စီရင်မည်၊ အကြီးအကြပ်တို့ကို ဆင့်ဆိုပြီးလျှင် ဗိုလ်မှူး မင်းကျော်ပျံချီနောက်အုပ်၍ စည်းစည်းကြပ်ကြပ် ဆုတ်ခွာခဲ့သည်နှင့် တပ်တွင်းသားတို့မြင်လျှင် ထွက်၍လိုက်သည်ကို ရဲခြင်းနှင့် ပြည့်စုံသော စစ်သည်တော်တို့လည်း ခြေလှမ်းမရွေ့ ပြကတေ့သာ ဆုတ်ခွာခဲ့၍ ဗိုလ်မှူးမင်းကျော်ပျံချီ နောက်က တလား, နှစ်လား လှည့်ကာ ပတ်ကာ မြင်းရေးကစား၍ လိုက်သည်ကို တပ်တွင်းသားတို့ မြင်လျှင် မလိုက်ဝံ့၍ ပြန်လေ၏။ | L44: At that time, the commander Min Kyaw Pyan Chi, thinking that if we withdraw now, they will pursue and attack us, ordered the musketeer youths and infantry soldiers to retreat first, and then he followed, covering the rear with the cavalry, and after ordering the commanders that if he heard that even one infantryman had been captured, he would punish the cavalrymen, he retreated in a disciplined and tight formation behind the commander Min Kyaw Pyan Chi; when those inside the camp saw this and came out to pursue, the soldiers, full of courage, retreated without quickening their pace, and when those inside the camp saw the commander Min Kyaw Pyan Chi following behind, turning and circling once or twice to perform cavalry maneuvers, they did not dare to pursue and returned.
A45: First 5% | B45: vol1 | C45: 85 | D45: vol1_s000562 | E45: G03.05.02 | F45: He threatens punishment if cavalry allow infantry to be captured | G45: covered | H45: yes | I45: vol1_s000562_t01_df4a70c848d8 | J45: “Enforced discipline during tactical retreat” is accepted as a broad representation of the explicit punitive threat, rather than demanding another triple. | K45: ထိုအခါ ဗိုလ်မှူး မင်းကျော်ပျံချီလည်း ယခု ငါတို့ ခွာချေသော် သူက လိုက်ထပ်ချိမ့်မည်ဟု အမှတ်ရှိ၍ သေနတ်လုလင် ခြေသည်သူရဲကို အလျင် ဆုတ်နှင့်စေ၊ ယင်းသို့မှ မြင်းတပ် နောက်က အုပ်၍ လိုက်လေ၊ ခြေသည်တစ်ယောက်မျှ သူကရသည် ကြားရလျှင် မြင်းတပ်သားတို့ကို စီရင်မည်၊ အကြီးအကြပ်တို့ကို ဆင့်ဆိုပြီးလျှင် ဗိုလ်မှူး မင်းကျော်ပျံချီနောက်အုပ်၍ စည်းစည်းကြပ်ကြပ် ဆုတ်ခွာခဲ့သည်နှင့် တပ်တွင်းသားတို့မြင်လျှင် ထွက်၍လိုက်သည်ကို ရဲခြင်းနှင့် ပြည့်စုံသော စစ်သည်တော်တို့လည်း ခြေလှမ်းမရွေ့ ပြကတေ့သာ ဆုတ်ခွာခဲ့၍ ဗိုလ်မှူးမင်းကျော်ပျံချီ နောက်က တလား, နှစ်လား လှည့်ကာ ပတ်ကာ မြင်းရေးကစား၍ လိုက်သည်ကို တပ်တွင်းသားတို့ မြင်လျှင် မလိုက်ဝံ့၍ ပြန်လေ၏။ | L45: At that time, the commander Min Kyaw Pyan Chi, thinking that if we withdraw now, they will pursue and attack us, ordered the musketeer youths and infantry soldiers to retreat first, and then he followed, covering the rear with the cavalry, and after ordering the commanders that if he heard that even one infantryman had been captured, he would punish the cavalrymen, he retreated in a disciplined and tight formation behind the commander Min Kyaw Pyan Chi; when those inside the camp saw this and came out to pursue, the soldiers, full of courage, retreated without quickening their pace, and when those inside the camp saw the commander Min Kyaw Pyan Chi following behind, turning and circling once or twice to perform cavalry maneuvers, they did not dare to pursue and returned.
A46: First 5% | B46: vol1 | C46: 85 | D46: vol1_s000562 | E46: G03.05.03 | F46: The royal force conducts an orderly retreat protected by its commander | G46: covered | H46: yes | I46: vol1_s000562_t01_df4a70c848d8; vol1_s000562_t02_0de9d23decd9 | K46: ထိုအခါ ဗိုလ်မှူး မင်းကျော်ပျံချီလည်း ယခု ငါတို့ ခွာချေသော် သူက လိုက်ထပ်ချိမ့်မည်ဟု အမှတ်ရှိ၍ သေနတ်လုလင် ခြေသည်သူရဲကို အလျင် ဆုတ်နှင့်စေ၊ ယင်းသို့မှ မြင်းတပ် နောက်က အုပ်၍ လိုက်လေ၊ ခြေသည်တစ်ယောက်မျှ သူကရသည် ကြားရလျှင် မြင်းတပ်သားတို့ကို စီရင်မည်၊ အကြီးအကြပ်တို့ကို ဆင့်ဆိုပြီးလျှင် ဗိုလ်မှူး မင်းကျော်ပျံချီနောက်အုပ်၍ စည်းစည်းကြပ်ကြပ် ဆုတ်ခွာခဲ့သည်နှင့် တပ်တွင်းသားတို့မြင်လျှင် ထွက်၍လိုက်သည်ကို ရဲခြင်းနှင့် ပြည့်စုံသော စစ်သည်တော်တို့လည်း ခြေလှမ်းမရွေ့ ပြကတေ့သာ ဆုတ်ခွာခဲ့၍ ဗိုလ်မှူးမင်းကျော်ပျံချီ နောက်က တလား, နှစ်လား လှည့်ကာ ပတ်ကာ မြင်းရေးကစား၍ လိုက်သည်ကို တပ်တွင်းသားတို့ မြင်လျှင် မလိုက်ဝံ့၍ ပြန်လေ၏။ | L46: At that time, the commander Min Kyaw Pyan Chi, thinking that if we withdraw now, they will pursue and attack us, ordered the musketeer youths and infantry soldiers to retreat first, and then he followed, covering the rear with the cavalry, and after ordering the commanders that if he heard that even one infantryman had been captured, he would punish the cavalrymen, he retreated in a disciplined and tight formation behind the commander Min Kyaw Pyan Chi; when those inside the camp saw this and came out to pursue, the soldiers, full of courage, retreated without quickening their pace, and when those inside the camp saw the commander Min Kyaw Pyan Chi following behind, turning and circling once or twice to perform cavalry maneuvers, they did not dare to pursue and returned.
A47: First 5% | B47: vol1 | C47: 85 | D47: vol1_s000562 | E47: G03.05.04 | F47: The camp defenders pursue but abandon pursuit after the rear-guard deterrence | G47: covered | H47: yes | I47: vol1_s000562_t02_0de9d23decd9 | K47: ထိုအခါ ဗိုလ်မှူး မင်းကျော်ပျံချီလည်း ယခု ငါတို့ ခွာချေသော် သူက လိုက်ထပ်ချိမ့်မည်ဟု အမှတ်ရှိ၍ သေနတ်လုလင် ခြေသည်သူရဲကို အလျင် ဆုတ်နှင့်စေ၊ ယင်းသို့မှ မြင်းတပ် နောက်က အုပ်၍ လိုက်လေ၊ ခြေသည်တစ်ယောက်မျှ သူကရသည် ကြားရလျှင် မြင်းတပ်သားတို့ကို စီရင်မည်၊ အကြီးအကြပ်တို့ကို ဆင့်ဆိုပြီးလျှင် ဗိုလ်မှူး မင်းကျော်ပျံချီနောက်အုပ်၍ စည်းစည်းကြပ်ကြပ် ဆုတ်ခွာခဲ့သည်နှင့် တပ်တွင်းသားတို့မြင်လျှင် ထွက်၍လိုက်သည်ကို ရဲခြင်းနှင့် ပြည့်စုံသော စစ်သည်တော်တို့လည်း ခြေလှမ်းမရွေ့ ပြကတေ့သာ ဆုတ်ခွာခဲ့၍ ဗိုလ်မှူးမင်းကျော်ပျံချီ နောက်က တလား, နှစ်လား လှည့်ကာ ပတ်ကာ မြင်းရေးကစား၍ လိုက်သည်ကို တပ်တွင်းသားတို့ မြင်လျှင် မလိုက်ဝံ့၍ ပြန်လေ၏။ | L47: At that time, the commander Min Kyaw Pyan Chi, thinking that if we withdraw now, they will pursue and attack us, ordered the musketeer youths and infantry soldiers to retreat first, and then he followed, covering the rear with the cavalry, and after ordering the commanders that if he heard that even one infantryman had been captured, he would punish the cavalrymen, he retreated in a disciplined and tight formation behind the commander Min Kyaw Pyan Chi; when those inside the camp saw this and came out to pursue, the soldiers, full of courage, retreated without quickening their pace, and when those inside the camp saw the commander Min Kyaw Pyan Chi following behind, turning and circling once or twice to perform cavalry maneuvers, they did not dare to pursue and returned.
A48: First 5% | B48: vol1 | C48: 85 | D48: vol1_s000563 | E48: G03.06.01 | F48: The Htilin sawbwa withdraws in anticipation of an attack from Moksobo | G48: covered | H48: yes | I48: vol1_s000563_t01_c3720c9b8980; vol1_s000563_t02_7347a534effd | K48: ယင်းသောအခါ ထီးလင်း စော်ဘွားမူကား သည် တွင် အရှည်နေချေသော် မူဆိုးပိုက ချီလာချိမ့်မည် အမှတ်ရှိ၍ ထီးလင်းက ခွာပြီးလျှင် မြစ်သာနားမှာ နေလေ၏။ | L48: At that time, the Sawbwa of Htilin, thinking that if he stayed there for long, the Muso-po would march upon him, withdrew from Htilin and stayed near Myittha.
A49: First 5% | B49: vol1 | C49: 85 | D49: vol1_s000564 | E49: G03.07.01 | F49: The Mon had attacked, killed Kwe troops and seized their weapons | G49: missing | H49: yes | K49: 39 ကွေ့ ဂုဏ္ဏအိန်တို့က မွန်များကို သတ်ခြင်း ထိုအခါ မတ္တရာအုတ်ဖို အရပ်တွင် နေသော ကွေ့ ဂုဏ္ဏအိန်တို့က မွန်တို့သည် ယမန်တွင် ငါတို့တပ်ကို တိုက်လာ သည့်ကာလ ငါတို့လည်း အားမတန်၍ ရှောင်ရှားနေရသည်နှင့် လက်နက်ကိရိယာများကို ယူသွားလေသည်၊ လူလည်း အများသေသည်၊ သည်ခါသော် မွန်တို့ကို လက်စားချေမိအောင် လှည့်ဖြားသွေးခေါ်၍ သတ်မည် ကြံပြီးလျှင်- အဝမြို့စောင့် မွန်ဗိုလ်မှူး ငွေခွန်ဝန်သို့ စေလေ၏။ | L49: 39. The Killing of the Mons by the Kwe Guna-ein: At that time, the Kwe Guna-ein who lived in the Mattara brick kiln area, thinking that when the Mons attacked our camp previously, we were unable to resist and had to flee, and they took our weapons and many people died, so this time, planning to deceive, lure, and kill the Mons to take revenge, they sent a message to the Mon commander guarding Ava, the Ngwe Khun Wun.
A50: First 5% | B50: vol1 | C50: 85 | D50: vol1_s000564 | E50: G03.07.02 | F50: Gunna Ein's Kwe plan revenge through a deceptive message to Ngwekhunwun | G50: covered | H50: yes | I50: vol1_s000564_t01_aab2d7a4b9d5; vol1_s000564_t02_cfaeb700eaca | K50: 39 ကွေ့ ဂုဏ္ဏအိန်တို့က မွန်များကို သတ်ခြင်း ထိုအခါ မတ္တရာအုတ်ဖို အရပ်တွင် နေသော ကွေ့ ဂုဏ္ဏအိန်တို့က မွန်တို့သည် ယမန်တွင် ငါတို့တပ်ကို တိုက်လာ သည့်ကာလ ငါတို့လည်း အားမတန်၍ ရှောင်ရှားနေရသည်နှင့် လက်နက်ကိရိယာများကို ယူသွားလေသည်၊ လူလည်း အများသေသည်၊ သည်ခါသော် မွန်တို့ကို လက်စားချေမိအောင် လှည့်ဖြားသွေးခေါ်၍ သတ်မည် ကြံပြီးလျှင်- အဝမြို့စောင့် မွန်ဗိုလ်မှူး ငွေခွန်ဝန်သို့ စေလေ၏။ | L50: 39. The Killing of the Mons by the Kwe Guna-ein: At that time, the Kwe Guna-ein who lived in the Mattara brick kiln area, thinking that when the Mons attacked our camp previously, we were unable to resist and had to flee, and they took our weapons and many people died, so this time, planning to deceive, lure, and kill the Mons to take revenge, they sent a message to the Mon commander guarding Ava, the Ngwe Khun Wun.
A51: First 5% | B51: vol1 | C51: 85 | D51: vol1_s000565 | E51: G03.08.01 | F51: The Kwe deceitfully offer submission and surrender of weapons | G51: covered | H51: yes | I51: vol1_s000565_t01_0315662898a2 | K51: စေဟန်ကား...ယမန်တစ်ကြိမ် ဗိုလ်မင်းတပ်မင်းများ ချီလာသည့်ကာလ စစ်ဦး ဘီလူးပါ ဖြစ်ချိမ့်မည်ကို ကြောက်လှ၍ လူကြီးတစ်စု အတွေ့ မခံဝံ့၊ တောတောင်ပုန်းလျှိုး နေပေသည်၊ ကျွန်ုပ်တို့တွင် ရှိသော လက်နက်ကိရိယာများလည်း ကျွန်ုပ်တို့နှင့် မထိုက်တန်ပေ၊ ယခု ဗိုလ်မင်း တပ်မင်းများ ချီလာလျှင် ဝှက်ထားသမျှ လက်နက်ကိရိယာများကို တစ်ခုမကျန် ကုန်စင်အောင် ဆက်သ၍ သစ္စာခံပါ တော့မည်ဟု ကွေ့တို့က စေသည်ကို မွန်တို့က ယုံကြည်၍ သံလှေနှစ်ရာ၊ လက်နက်ကိုင် လူငါးထောင်နှင့် မတ္တရာ အုတ်ဖိုသို့ မွန်တို့ ချီလာသည်ကို ပိုဝအရပ်သို့ ရောက်လျှင် အုတ်ဖိုရောက် မချီလာနှင့်တော့၊ မြို့သူရွာသားတို့ အလျင်က ကြောက်ရှိန်နှင့် မငြိမ်မဝပ် ထိတ်လန့်ပါတော့မည်ဖြစ်၍ ပိုဝအရပ်တွင် သစ္စာခံပါတော့မည်ဟု ဆိုပြီးလျှင် တဲကန္နား ဆောက်ပေး၍ အပျူအငှာ ကျွေးမွေးတွက်နပ်သည်ကို မွန်တို့လည်း အယုံအကြည် ဝမ်းမြောက်ဝမ်းသာ သောက်စားကြသည်နှင့် ယစ်မူးမေ့လျော့သည့် အခိုက်တွင် တောထဲက ဝှက်ထားသော ကွေ့လဝတို့ထွက်၍ မွန်တို့ကို ခုတ်သတ်လျှင် မွန်ဗိုလ်မှူး တပ်မှူး ဒေါဗညား အများသေလေသည်၊ လှေနှစ်ရာကျော်နှင့် ပါသည့် လက်နက် ကိရိယာများကိုလည်း ကုန်စင်အောင် သိမ်းယူလေသည်။ | L51: The message was: 'Previously, when the commanders and army leaders marched, we were so afraid that it might be the vanguard of the demons that we did not dare to be seen by a group of elders and remained hiding in the forests and mountains; the weapons we possess are not worthy of us; now, if the commanders and army leaders march, we will offer all the hidden weapons without a single one remaining and will pledge our allegiance.' The Mons believed the message sent by the Kwe and marched to the Mattara brick kiln with two hundred iron boats and five thousand armed men; when they reached the Po-wa area, they said, 'Do not march to the brick kiln; the townspeople and villagers are already fearful and will be restless and panicked, so we will pledge our allegiance in the Po-wa area,' and after saying this, they built huts and entertained them with hospitality; while the Mons were drinking and eating with trust and joy, and were intoxicated and inattentive, the Kwe-Law who were hiding in the forest came out and hacked the Mons to death, causing many, including the Mon commander and battalion leader Daw Banya, to die, and they seized all the weapons that were with the more than two hundred boats.
A52: First 5% | B52: vol1 | C52: 85 | D52: vol1_s000565 | E52: G03.08.02 | F52: The Mon commanders advance with troops and boats in response | G52: missing | H52: yes | K52: စေဟန်ကား...ယမန်တစ်ကြိမ် ဗိုလ်မင်းတပ်မင်းများ ချီလာသည့်ကာလ စစ်ဦး ဘီလူးပါ ဖြစ်ချိမ့်မည်ကို ကြောက်လှ၍ လူကြီးတစ်စု အတွေ့ မခံဝံ့၊ တောတောင်ပုန်းလျှိုး နေပေသည်၊ ကျွန်ုပ်တို့တွင် ရှိသော လက်နက်ကိရိယာများလည်း ကျွန်ုပ်တို့နှင့် မထိုက်တန်ပေ၊ ယခု ဗိုလ်မင်း တပ်မင်းများ ချီလာလျှင် ဝှက်ထားသမျှ လက်နက်ကိရိယာများကို တစ်ခုမကျန် ကုန်စင်အောင် ဆက်သ၍ သစ္စာခံပါ တော့မည်ဟု ကွေ့တို့က စေသည်ကို မွန်တို့က ယုံကြည်၍ သံလှေနှစ်ရာ၊ လက်နက်ကိုင် လူငါးထောင်နှင့် မတ္တရာ အုတ်ဖိုသို့ မွန်တို့ ချီလာသည်ကို ပိုဝအရပ်သို့ ရောက်လျှင် အုတ်ဖိုရောက် မချီလာနှင့်တော့၊ မြို့သူရွာသားတို့ အလျင်က ကြောက်ရှိန်နှင့် မငြိမ်မဝပ် ထိတ်လန့်ပါတော့မည်ဖြစ်၍ ပိုဝအရပ်တွင် သစ္စာခံပါတော့မည်ဟု ဆိုပြီးလျှင် တဲကန္နား ဆောက်ပေး၍ အပျူအငှာ ကျွေးမွေးတွက်နပ်သည်ကို မွန်တို့လည်း အယုံအကြည် ဝမ်းမြောက်ဝမ်းသာ သောက်စားကြသည်နှင့် ယစ်မူးမေ့လျော့သည့် အခိုက်တွင် တောထဲက ဝှက်ထားသော ကွေ့လဝတို့ထွက်၍ မွန်တို့ကို ခုတ်သတ်လျှင် မွန်ဗိုလ်မှူး တပ်မှူး ဒေါဗညား အများသေလေသည်၊ လှေနှစ်ရာကျော်နှင့် ပါသည့် လက်နက် ကိရိယာများကိုလည်း ကုန်စင်အောင် သိမ်းယူလေသည်။ | L52: The message was: 'Previously, when the commanders and army leaders marched, we were so afraid that it might be the vanguard of the demons that we did not dare to be seen by a group of elders and remained hiding in the forests and mountains; the weapons we possess are not worthy of us; now, if the commanders and army leaders march, we will offer all the hidden weapons without a single one remaining and will pledge our allegiance.' The Mons believed the message sent by the Kwe and marched to the Mattara brick kiln with two hundred iron boats and five thousand armed men; when they reached the Po-wa area, they said, 'Do not march to the brick kiln; the townspeople and villagers are already fearful and will be restless and panicked, so we will pledge our allegiance in the Po-wa area,' and after saying this, they built huts and entertained them with hospitality; while the Mons were drinking and eating with trust and joy, and were intoxicated and inattentive, the Kwe-Law who were hiding in the forest came out and hacked the Mons to death, causing many, including the Mon commander and battalion leader Daw Banya, to die, and they seized all the weapons that were with the more than two hundred boats.
